Workbook

Sheet I_Inputs & Assumptions
A1: CONSTRUCTION-TO-PERMANENT FINANCIAL MODEL
A2: INPUTS & ASSUMPTIONS
A4: PROJECT INFORMATION
A5: Project Name | B5: Campus Adele
A6: Location | B6: Quebec
A7: Construction Start Date | B7: 2025-03-01
A8: Construction Duration | B8: 13 | C8: months
A9: Months Until First Units Ready | B9: 16 | C9: months
A10: Gap to Permanent Financing | B10: 1 | C10: months
A11: Permanent Loan Term | B11: 60 | C11: months
A12: Exit Timing (Post-Construction) | B12: 61 | C12: months
A14: CONSTRUCTION BUDGET
A15: Land - Purchase Price | B15: 400000
A16: Land - Recognized Value | B16: 600000
A17: Assessed Property Value | B17: 15000000
A18: Hard Costs by Category | B18: Budget | C18: Phasing % | D18: Holdback % | E18: Release (mo)
A19: Site Work & Demolition | B19: 500000 | C19: Equal | D19: 0.1 | E19: 3
A20: Foundation & Structure | B20: 3000000 | C20: Front-loaded | D20: 0.1 | E20: 2
A21: Building Envelope | B21: 2000000 | C21: Mid-weighted | D21: 0.1 | E21: 3
A22: MEP Systems | B22: 2500000 | C22: Mid-weighted | D22: 0.1 | E22: 4
A23: Interior Finishes | B23: 1500000 | C23: Back-loaded | D23: 0.1 | E23: 2
A24: Landscaping & Site | B24: 300000 | C24: Back-loaded | D24: 0.1 | E24: 6
A26: Soft Costs by Category | B26: Budget | C26: Holdback %
A27: Architecture & Engineering | B27: 400000 | C27: 0.1
A28: Permits & Approvals | B28: 150000 | C28: 0
A29: Legal & Financing Fees | B29: 200000 | C29: 0
A30: Development Management | B30: 300000 | C30: 0.1
A31: Marketing & Leasing | B31: 100000 | C31: 0
A33: Contingency | B33: 500000
A35: CONSTRUCTION FINANCING - SENIOR LOAN
A36: Loan-to-Cost (LTC) % | B36: 0.7719 | C36: % | G36: ='Sources & Uses - Construction'!A4 | H36: ='Sources & Uses - Construction'!B4
A37: Interest Rate (Annual) | B37: 0.0495 | C37: % | G37: ='Sources & Uses - Construction'!A5 | H37: ='Sources & Uses - Construction'!B5
A38: Commitment Fee | B38: 0.001 | C38: % | G38: ='Sources & Uses - Construction'!A6 | H38: ='Sources & Uses - Construction'!B6
A39: Loan Amount | B39: 33627000 | C39: % | G39: ='Sources & Uses - Construction'!A7 | H39: ='Sources & Uses - Construction'!B7
A40: SUBORDINATED LOAN #1 - PREFERRED EQUITY | G40: ='Sources & Uses - Construction'!A8 | H40: ='Sources & Uses - Construction'!B8
A41: Loan Amount | B41: 0 | G41: ='Sources & Uses - Construction'!A9 | H41: ='Sources & Uses - Construction'!B9
A42: Interest Rate (Annual) | B42: 0.08 | C42: % | G42: ='Sources & Uses - Construction'!A10 | H42: ='Sources & Uses - Construction'!B10
A43: Commitment Fee | B43: 0.001 | C43: % | G43: ='Sources & Uses - Construction'!A11 | H43: ='Sources & Uses - Construction'!B11
A44: Draw Priority | B44: 1 | G44: ='Sources & Uses - Construction'!A12 | H44: ='Sources & Uses - Construction'!B12
G45: ='Sources & Uses - Construction'!A13 | H45: ='Sources & Uses - Construction'!B13
A46: SUBORDINATED LOAN #2 - MEZZANINE | G46: ='Sources & Uses - Construction'!A14 | H46: ='Sources & Uses - Construction'!B14
A47: Loan Amount | B47: 0 | G47: ='Sources & Uses - Construction'!A15 | H47: ='Sources & Uses - Construction'!B15
A48: Interest Rate (Annual) | B48: 0.1 | C48: % | G48: ='Sources & Uses - Construction'!A16 | H48: ='Sources & Uses - Construction'!B16
A49: Commitment Fee | B49: 0.001 | C49: % | G49: ='Sources & Uses - Construction'!A17 | H49: ='Sources & Uses - Construction'!B17
A50: Draw Priority | B50: 2 | G50: ='Sources & Uses - Construction'!A18 | H50: ='Sources & Uses - Construction'!B18
G51: ='Sources & Uses - Construction'!A19 | H51: ='Sources & Uses - Construction'!B19
A52: GST/QST | G52: ='Sources & Uses - Construction'!A20 | H52: ='Sources & Uses - Construction'!B20
A53: CASH MANAGEMENT | B53: 0.05 | C53: % | G53: ='Sources & Uses - Construction'!A21 | H53: ='Sources & Uses - Construction'!B21
A54: Minimum Cash Balance | B54: 100000 | C54: Target minimum cash to maintain | G54: ='Sources & Uses - Construction'!A22 | H54: ='Sources & Uses - Construction'!B22
A55: Sales Tax LOC Limit | B55: 750000 | C55: Maximum Sales Tax LOC | G55: ='Sources & Uses - Construction'!A23 | H55: ='Sources & Uses - Construction'!B23
A56: GST/QST LOC Facility Size | B56: 750000 | G56: ='Sources & Uses - Construction'!A24 | H56: ='Sources & Uses - Construction'!B24
G57: ='Sources & Uses - Construction'!A25 | H57: ='Sources & Uses - Construction'!B25
A58: PERMANENT FINANCING | G58: ='Sources & Uses - Construction'!A26 | H58: ='Sources & Uses - Construction'!B26
A59: Permanent Loan Amount | B59: 19000000 | C59: $ | G59: ='Sources & Uses - Construction'!A27 | H59: ='Sources & Uses - Construction'!B27
A60: CMB Rate | B60: 0.0329 | C60: % | G60: ='Sources & Uses - Construction'!A28 | H60: ='Sources & Uses - Construction'!B28
A61: Markup | B61: 0.0045 | C61: % | G61: ='Sources & Uses - Construction'!A29 | H61: ='Sources & Uses - Construction'!B29
A62: Contingency | B62: 0 | C62: % | G62: ='Sources & Uses - Construction'!A30 | H62: ='Sources & Uses - Construction'!B30
A63: Total Interest Rate | B63: 0.0374 | C63: % | G63: ='Sources & Uses - Construction'!A31 | H63: ='Sources & Uses - Construction'!B31
A64: Amortization Period | B64: 50 | C64: years | G64: ='Sources & Uses - Construction'!A32 | H64: ='Sources & Uses - Construction'!B32
A65: DSCR Covenant Minimum | B65: 1.1 | C65: x | G65: ='Sources & Uses - Construction'!A33 | H65: ='Sources & Uses - Construction'!B33
G66: ='Sources & Uses - Construction'!A34 | H66: ='Sources & Uses - Construction'!B34
A67: EQUITY | G67: ='Sources & Uses - Construction'!A35 | H67: ='Sources & Uses - Construction'!B35
A68: Class E (LP) Total Commitment | B68: 2800000 | G68: ='Sources & Uses - Construction'!A36 | H68: ='Sources & Uses - Construction'!B36
A69: Class A (GP) Land Contribution | B69: 0 | C69: (recognized value) | G69: ='Sources & Uses - Construction'!A37 | H69: ='Sources & Uses - Construction'!B37
A70: Preferred Return % (Annual) | B70: 0 | C70: %
A72: REVENUE ASSUMPTIONS
A73: Total Parking Spaces | B73: 47
A74: Revenue-Generating Parking Spaces | B74: 47
A75: Parking Rate | B75: 75 | C75: $/month
A76: Internet Rate per Unit | B76: 50 | C76: $/month
A77: EV Charging Stations | B77: 50
A78: EV Charging Rate | B78: 38 | C78: $/month
A79: Annual Revenue Growth | B79: 0.02 | C79: %
A80: Lease-Up Lag (Months) | B80: 2 | C80: months
A81: Stabilized Vacancy % | B81: 0.06 | C81: %
A82: Service Revenue Escalation | B82: 0.015 | C82: %
A83: OPERATING EXPENSES
A84: Municipal Tax - Mill Rate | B84: 0.0075 | C84: %
A85: School Tax - Mill Rate | B85: 0.00156 | C85: %
A86: Tax Start Delay (Post-Construction) | B86: 0 | C86: months
A87: Tax Assessment Escalation | B87: 0 | C87: %
A88: Operating Expense Line Items | B88: Annual Amount | C88: Escalation %
A89: Insurance | B89: 16989 | C89: 0.01
A90: Repairs & Maintenance | B90: 38400 | C90: 0.01
A91: Outdoor Amenities Maintenance | B91: 2000 | C91: 0.01
A92: Snow Removal, Grass, Garbage | B92: 23000 | C92: 0.01
A93: Janitor | B93: 23000 | C93: 0.01
A94: Cleaning Reserve on Turnover | B94: 7650 | C94: 0.01
A95: Security & Monitoring | B95: 9000 | C95: 0.01
A96: Internet | B96: 20000 | C96: 0.01
A97: EV Charging Stations | B97: 5000 | C97: 0.01
A98: Electricity (Common) | B98: 12200 | C98: 0.01
A99: Administration (% of EGI) | B99: 0.03 | C99: 0
A101: RESERVES | D101: Escalation %
A102: Appliance/Furniture Reserve | B102: 700 | C102: $/unit/year | D102: 0.01
A103: Structural Reserve | B103: 0.0075 | C103: % of EGI | D103: 0.01
A105: DISTRIBUTIONS
A106: Minimum Cash Balance | B106: 100000
A107: Distribution Frequency | B107: Quarterly
A109: Waterfall Structure
...

Sheet I_Budget Input Data
A1: BUDGET INPUT DATA
A2: Imported from ryanbudget.csv - Edit phasing, holdback, and eligibility as needed
A4: Row # | B4: Category | C4: Subcategory | D4: Budget Amount | E4: Phasing Pattern | F4: Holdback % | G4: Holdback Release (mo after constr) | H4: GST/QST Eligible
A5: 1 | D5: 0 | E5: Equal | F5: 0.1 | G5: 3 | H5: Yes
A6: 2 | B6: 1. LAND | C6: Land Acquisition | D6: 1600000 | E6: Upfront | F6: 0 | G6: 0 | H6: Yes
A7: 3 | B7: 1. LAND | C7: Notary and cadastre | D7: 19808 | E7: Upfront | F7: 0 | G7: 0 | H7: Yes
A8: 4 | B8: 1. LAND | C8: Cadastral operation | D8: 105360 | E8: Upfront | F8: 0 | G8: 0 | H8: Yes
A9: 5 | B9: 2. SITE SERVICING + LANDSCAPE | C9: Extension of services:Excavation & Backfill - Adjustment for Bldgs 5 & 6 | D9: 479320 | E9: Front-loaded | F9: 0.1 | G9: 3 | H9: Yes
A10: 6 | B10: 2. SITE SERVICING + LANDSCAPE | C10: Extension of services:Excavation & Backfill - Trailer pad, Access road, Septic tank | D10: 10900 | E10: Front-loaded | F10: 0.1 | G10: 3 | H10: Yes
A11: 7 | B11: 2. SITE SERVICING + LANDSCAPE | C11: Extension of services:Credit - Reservoir change | D11: 1946765 | E11: Front-loaded | F11: 0.1 | G11: 3 | H11: Yes
A12: 8 | B12: 2. SITE SERVICING + LANDSCAPE | C12: Extension of services:Credit - Reservoir change | D12: 0 | E12: Front-loaded | F12: 0.1 | G12: 3 | H12: Yes
A13: 9 | B13: 2. SITE SERVICING + LANDSCAPE | C13: Extension of services:Excavation & Backfill - Campus Civil | D13: 143113 | E13: Front-loaded | F13: 0.1 | G13: 3 | H13: Yes
A14: 10 | B14: 2. SITE SERVICING + LANDSCAPE | C14: Extension of services:Excavation & Backfill - Campus Civil | D14: 30493 | E14: Front-loaded | F14: 0.1 | G14: 3 | H14: Yes
A15: 11 | B15: 2. SITE SERVICING + LANDSCAPE | C15: Extension of services:Excavation & backfill - Extension - Mtee Ryan Civil | D15: 375295 | E15: Front-loaded | F15: 0.1 | G15: 3 | H15: Yes
A16: 12 | B16: 2. SITE SERVICING + LANDSCAPE | D16: 165563 | E16: Front-loaded | F16: 0.1 | G16: 3 | H16: Yes
A17: 13 | B17: 2. SITE SERVICING + LANDSCAPE | C17: Onsite services - civil:Excavation & Backfill (PC) | D17: 475672 | E17: Front-loaded | F17: 0.1 | G17: 3 | H17: Yes
A18: 14 | B18: 2. SITE SERVICING + LANDSCAPE | C18: Onsite services - civil:Excavation & Backfill (PC) | D18: 23100 | E18: Front-loaded | F18: 0.1 | G18: 3 | H18: Yes
A19: 15 | B19: 2. SITE SERVICING + LANDSCAPE | C19: Onsite services - civil:Excavation & Backfill (PC) | D19: 2300 | E19: Front-loaded | F19: 0.1 | G19: 3 | H19: Yes
A20: 16 | B20: 2. SITE SERVICING + LANDSCAPE | C20: Onsite services - civil:Excavation & Backfill (PC) | D20: 25102 | E20: Front-loaded | F20: 0.1 | G20: 3 | H20: Yes
A21: 17 | B21: 2. SITE SERVICING + LANDSCAPE | C21: Onsite services - civil:Excavation & Backfill (PC) | D21: 47223 | E21: Front-loaded | F21: 0.1 | G21: 3 | H21: Yes
A22: 18 | B22: 2. SITE SERVICING + LANDSCAPE | C22: Landscaping:Excavation & Backfill - Landscaping | D22: 1065794 | E22: Front-loaded | F22: 0.1 | G22: 3 | H22: Yes
A23: 19 | B23: 2. SITE SERVICING + LANDSCAPE | C23: Electrical services | D23: 252500 | E23: Front-loaded | F23: 0.1 | G23: 3 | H23: Yes
A24: 20 | B24: 2. SITE SERVICING + LANDSCAPE | C24: Electrical charging stations | D24: 124981 | E24: Front-loaded | F24: 0.1 | G24: 3 | H24: Yes
A25: 21 | B25: 3. HARD COSTS | C25: Admin and profit | D25: 1577987 | E25: Equal | F25: 0.1 | G25: 3 | H25: Yes
A26: 22 | B26: 3. HARD COSTS | C26: Insurance and bonding:Insurance | D26: 278718 | E26: Equal | F26: 0.1 | G26: 3 | H26: Yes
A27: 23 | B27: 3. HARD COSTS | D27: 140525 | E27: Equal | F27: 0.1 | G27: 3 | H27: Yes
A28: 24 | B28: 3. HARD COSTS | C28: Insurance and bonding:Wrap-up | D28: 36465 | E28: Equal | F28: 0.1 | G28: 3 | H28: Yes
A29: 25 | B29: 3. HARD COSTS | C29: Insurance and bonding:Bris des Machines | D29: 2585 | E29: Equal | F29: 0.1 | G29: 3 | H29: Yes
A30: 26 | B30: 3. HARD COSTS | C30: Insurance and bonding:L&M and Performance Bonds | D30: 0 | E30: Equal | F30: 0.1 | G30: 3 | H30: Yes
A31: 27 | B31: 3. HARD COSTS | C31: General conditions:CoSS Agent | D31: 236000 | E31: Equal | F31: 0.1 | G31: 3 | H31: Yes
A32: 28 | B32: 3. HARD COSTS | C32: General conditions:RSS Agent | D32: 213500 | E32: Equal | F32: 0.1 | G32: 3 | H32: Yes
A33: 29 | B33: 3. HARD COSTS | C33: General conditions:Superintendent 1 | D33: 303400 | E33: Equal | F33: 0.1 | G33: 3 | H33: Yes
A34: 30 | B34: 3. HARD COSTS | C34: General conditions:Superintendent 2 | D34: 266400 | E34: Equal | F34: 0.1 | G34: 3 | H34: Yes
A35: 31 | B35: 3. HARD COSTS | C35: General conditions:Project Manager | D35: 150750 | E35: Equal | F35: 0.1 | G35: 3 | H35: Yes
A36: 32 | B36: 3. HARD COSTS | C36: General conditions:Labourer | D36: 230020 | E36: Equal | F36: 0.1 | G36: 3 | H36: Yes
A37: 33 | B37: 3. HARD COSTS | C37: General Conditions: Logding | D37: 11000 | E37: Equal | F37: 0.1 | G37: 3 | H37: Yes
A38: 34 | B38: 3. HARD COSTS | C38: General conditions:Site fencing | D38: 10780 | E38: Equal | F38: 0.1 | G38: 3 | H38: Yes
A39: 35 | B39: 3. HARD COSTS | C39: General Conditions: Printing | D39: 8048 | E39: Equal | F39: 0.1 | G39: 3 | H39: Yes
... A57: 53 | B57: 3. HARD COSTS | C57: General conditions:Project signage | D57: 181830 | E57: Equal | F57: 0.1 | G57: 3 | H57: Yes
A58: 54 | B58: 3. HARD COSTS | D58: 6000 | E58: Equal | F58: 0.1 | G58: 3 | H58: Yes
A59: 55 | B59: 3. HARD COSTS | C59: General conditions:Miscellaneous | D59: 1901 | E59: Equal | F59: 0.1 | G59: 3 | H59: Yes
A60: 56 | B60: 3. HARD COSTS | C60: Formwork:Concrete purchases - Hambro floors | D60: 94276 | E60: Front-loaded | F60: 0.1 | G60: 3 | H60: Yes
A61: 57 | B61: 3. HARD COSTS | C61: Formwork:Stair slab concrete | D61: 27681 | E61: Front-loaded | F61: 0.1 | G61: 3 | H61: Yes
A62: 58 | B62: 3. HARD COSTS | C62: Concrete:Concrete purchases | D62: 97941 | E62: Front-loaded | F62: 0.1 | G62: 3 | H62: Yes
A63: 59 | B63: 3. HARD COSTS | C63: Formwork:Insulated formwork | D63: 2681518 | E63: Front-loaded | F63: 0.1 | G63: 3 | H63: Yes
A64: 60 | B64: 3. HARD COSTS | D64: 0 | E64: Equal | F64: 0.1 | G64: 3 | H64: Yes
A65: 61 | B65: 3. HARD COSTS | C65: Formwork:Wire mesh - Hambro floors | D65: 62581 | E65: Front-loaded | F65: 0.1 | G65: 3 | H65: Yes
A66: 62 | B66: 3. HARD COSTS | C66: Formwork:Cement finishing | D66: 163654 | E66: Front-loaded | F66: 0.1 | G66: 3 | H66: Yes
A67: 63 | B67: 3. HARD COSTS | C67: Formwork:Stair slab cement finishing | D67: 0 | E67: Front-loaded | F67: 0.1 | G67: 3 | H67: Yes
A68: 64 | B68: 3. HARD COSTS | C68: Formwork:Stair slab concrete pumps | D68: 0 | E68: Front-loaded | F68: 0.1 | G68: 3 | H68: Yes
A69: 65 | B69: 3. HARD COSTS | C69: Formwork:Concrete pumps | D69: 31715 | E69: Front-loaded | F69: 0.1 | G69: 3 | H69: Yes
A70: 66 | B70: 3. HARD COSTS | C70: Concrete:Concrete pumps | D70: 0 | E70: Front-loaded | F70: 0.1 | G70: 3 | H70: Yes
A71: 67 | B71: 3. HARD COSTS | C71: Concrete:Concrete accessories | D71: 79342 | E71: Front-loaded | F71: 0.1 | G71: 3 | H71: Yes
A72: 68 | B72: 3. HARD COSTS | C72: Concrete:Labour - Accessories | D72: 0 | E72: Front-loaded | F72: 0.1 | G72: 3 | H72: Yes
A73: 69 | B73: 3. HARD COSTS | C73: Concrete:Polyethylene .006 - changed to .010 2024-01-22 | D73: 0 | E73: Front-loaded | F73: 0.1 | G73: 3 | H73: Yes
A74: 70 | B74: 3. HARD COSTS | C74: Concrete:3'' Rigid insulation (4' perimeter) - changed to 2'' Blue | D74: 0 | E74: Front-loaded | F74: 0.1 | G74: 3 | H74: Yes
A75: 71 | B75: 3. HARD COSTS | C75: Concrete:Labour - Rigid insulation | D75: 0 | E75: Front-loaded | F75: 0.1 | G75: 3 | H75: Yes
A76: 72 | B76: 3. HARD COSTS | C76: Concrete:Wet cure | D76: 0 | E76: Front-loaded | F76: 0.1 | G76: 3 | H76: Yes
... A91: 87 | B91: 3. HARD COSTS | C91: Kitchen:Kitchens & vanities (QC) | D91: 844652 | E91: Back-loaded | F91: 0.1 | G91: 3 | H91: Yes
A92: 88 | B92: 3. HARD COSTS | D92: 0 | E92: Equal | F92: 0.1 | G92: 3 | H92: Yes
A93: 89 | B93: 3. HARD COSTS | C93: Kitchen:Quartz counters - Purchase | D93: 177900 | E93: Back-loaded | F93: 0.1 | G93: 3 | H93: Yes
A94: 90 | B94: 3. HARD COSTS | C94: Kitchen:Quartz counters - Installation | D94: 0 | E94: Back-loaded | F94: 0.1 | G94: 3 | H94: Yes
A95: 91 | B95: 3. HARD COSTS | C95: Carpentry rough:Roof insulation | D95: 35500 | E95: Mid-weighted | F95: 0.1 | G95: 3 | H95: Yes
A96: 92 | B96: 3. HARD COSTS | C96: Exterior finishes:Wood siding | D96: 1482450 | E96: Mid-weighted | F96: 0.1 | G96: 3 | H96: Yes
A97: 93 | B97: 3. HARD COSTS | C97: Exterior finishes:Acrylic stucco & Duroc | D97: 280000 | E97: Mid-weighted | F97: 0.1 | G97: 3 | H97: Yes
A98: 94 | B98: 3. HARD COSTS | C98: Roof, membrane:Roofing (Shingles) | D98: 280825 | E98: Mid-weighted | F98: 0.1 | G98: 3 | H98: Yes
A99: 95 | B99: 3. HARD COSTS | C99: Roof, membrane:Roofing (Winter conditions) | D99: 0 | E99: Mid-weighted | F99: 0.1 | G99: 3 | H99: Yes
A100: 96 | B100: 3. HARD COSTS | C100: Roof, membrane:Rain Gutters | D100: 36000 | E100: Mid-weighted | F100: 0.1 | G100: 3 | H100: Yes
A101: 97 | B101: 3. HARD COSTS | C101: Fenestration:Caulking | D101: 91200 | E101: Mid-weighted | F101: 0.1 | G101: 3 | H101: Yes
A102: 98 | B102: 3. HARD COSTS | C102: Doors and hardware:Wood doors | D102: 449827 | E102: Equal | F102: 0.1 | G102: 3 | H102: Yes
A103: 99 | B103: 3. HARD COSTS | D103: 49800 | E103: Equal | F103: 0.1 | G103: 3 | H103: Yes
A104: 100 | B104: 3. HARD COSTS | D104: 157600 | E104: Equal | F104: 0.1 | G104: 3 | H104: Yes
A105: 101 | B105: 3. HARD COSTS | C105: Carpentry finish:Carpentry | D105: 248100 | E105: Equal | F105: 0.1 | G105: 3 | H105: Yes
A106: 102 | B106: 3. HARD COSTS | C106: Doors and hardware:Baseboard, 1/4-round & casing | D106: 108850 | E106: Equal | F106: 0.1 | G106: 3 | H106: Yes
A107: 103 | B107: 3. HARD COSTS | C107: Carpentry finish:Shelving & Finish materials | D107: 0 | E107: Equal | F107: 0.1 | G107: 3 | H107: Yes
A108: 104 | B108: 3. HARD COSTS | C108: Fenestration:Windows & patio-doors - Supply | D108: 851388 | E108: Mid-weighted | F108: 0.1 | G108: 3 | H108: Yes
A109: 105 | B109: 3. HARD COSTS | C109: Fenestration:Transport & Handling - Quebec | D109: 0 | E109: Mid-weighted | F109: 0.1 | G109: 3 | H109: Yes
A110: 106 | B110: 3. HARD COSTS | C110: Interior systems:Drywall | D110: 2345879 | E110: Back-loaded | F110: 0.1 | G110: 3 | H110: Yes
A111: 107 | B111: 3. HARD COSTS | C111: Ceramic:Ceramic Purchase, Transport, Handling & Installation | D111: 179184 | E111: Back-loaded | F111: 0.1 | G111: 3 | H111: Yes
A112: 108 | B112: 3. HARD COSTS | C112: Ceramic:Shower walls | D112: 0 | E112: Back-loaded | F112: 0.1 | G112: 3 | H112: Yes
A113: 109 | B113: 3. HARD COSTS | C113: Ceramic:Bathroom floors (SPC) | D113: 208859 | E113: Back-loaded | F113: 0.1 | G113: 3 | H113: Yes
A114: 110 | B114: 3. HARD COSTS | C114: Floor covering:Vinyl flooring & Transport, Handling | D114: 343300 | E114: Back-loaded | F114: 0.1 | G114: 3 | H114: Yes
A115: 111 | B115: 3. HARD COSTS | D115: 0 | E115: Equal | F115: 0.1 | G115: 3 | H115: Yes
A116: 112 | B116: 3. HARD COSTS | C116: Paint:Painting | D116: 366000 | E116: Back-loaded | F116: 0.1 | G116: 3 | H116: Yes
A117: 113 | B117: 3. HARD COSTS | D117: 102000 | E117: Equal | F117: 0.1 | G117: 3 | H117: Yes
A118: 114 | B118: 3. HARD COSTS | D118: 0 | E118: Equal | F118: 0.1 | G118: 3 | H118: Yes
A119: 115 | B119: 3. HARD COSTS | C119: Railings:Foot grilles | D119: 0 | E119: Equal | F119: 0.1 | G119: 3 | H119: Yes
A120: 116 | B120: 3. HARD COSTS | C120: Railings:Interior signage | D120: 15300 | E120: Back-loaded | F120: 0.1 | G120: 3 | H120: Yes
A121: 117 | B121: 3. HARD COSTS | C121: Railings:WC acccessories | D121: 25750 | E121: Equal | F121: 0.1 | G121: 3 | H121: Yes
A122: 118 | B122: 3. HARD COSTS | C122: Plumbing:Plumbing (Rough S/I; Finish I/O) | D122: 1643900 | E122: Mid-weighted | F122: 0.1 | G122: 3 | H122: Yes
A123: 119 | B123: 3. HARD COSTS | C123: Plumbing:Plumbing finishes (S) - Toilet, Shower | D123: 377966 | E123: Mid-weighted | F123: 0.1 | G123: 3 | H123: Yes
A124: 120 | B124: 3. HARD COSTS | C124: Fire protection:Extinguishers | D124: 25500 | E124: Equal | F124: 0.1 | G124: 3 | H124: Yes
A125: 121 | B125: 3. HARD COSTS | C125: HVAC:HVAC | D125: 790030 | E125: Mid-weighted | F125: 0.1 | G125: 3 | H125: Yes
A126: 122 | B126: 3. HARD COSTS | C126: Electricity:Electricity | D126: 1866337 | E126: Mid-weighted | F126: 0.1 | G126: 3 | H126: Yes
A127: 123 | B127: 3. HARD COSTS | C127: Electricity:Lighting allowance | D127: 53300 | E127: Mid-weighted | F127: 0.1 | G127: 3 | H127: Yes
A128: 124 | B128: 3. HARD COSTS | C128: Electricity:Transport & Handling - Quebec | D128: 0 | E128: Mid-weighted | F128: 0.1 | G128: 3 | H128: Yes
A129: 125 | B129: 3. HARD COSTS | C129: Electricity:DEL Comptoirs (cuisines) | D129: 0 | E129: Mid-weighted | F129: 0.1 | G129: 3 | H129: Yes
A130: 126 | B130: 4. FF&E | C130: Appliances | D130: 403998 | E130: Back-loaded | F130: 0.05 | G130: 3 | H130: Yes
... A169: 165 | B169: 8. CONTINGENCY ALLOWANCE | C169: Contingency Non-Classified | D169: 0 | E169: As Needed | F169: 0 | G169: 0 | H169: Yes
A170: 166 | B170: HOLDBACKS | D170: 0 | E170: Equal | F170: 0.1 | G170: 3 | H170: Yes

Sheet I_Unit Rent Roll Data
A1: UNIT RENT ROLL DATA
A2: Exact import from Units-Proforma_View_Tremb.csv
A4: UnitId | B4: UnitRentalTypes | C4: Unit # | D4: Planned Delivery Date for Occupancy | E4: Projected Price Per Bedroom (from UnitRentalTypes) | F4: Projected Rate | G4: Bedroom Count (from UnitRentalTypes) | H4: Units Operations ID
A5: ADELE 1 A-101 | B5: London | C5: 101 | F5: 1905 | H5: ADELE -101 | I5: =F5*G5
A6: ADELE 1 A-201 | B6: Berlin | C6: 201 | F6: 2455 | H6: ADELE -201 | I6: =F6*G6
A7: ADELE 1 A-301 | B7: Berlin | C7: 301 | F7: 2455 | H7: ADELE -301
A8: ADELE 1 A-102 | B8: London | C8: 102 | F8: 1905 | H8: ADELE -102
A9: ADELE 1 A-202 | B9: Berlin | C9: 202 | F9: 2455 | H9: ADELE -202
A10: ADELE 1 A-302 | B10: Berlin | C10: 302 | F10: 2455 | H10: ADELE -302
A11: ADELE 1 B-101 | B11: London | C11: 101 | F11: 1905 | H11: ADELE -101
A12: ADELE 1 B-201 | B12: Paris | C12: 201 | F12: 1639 | H12: ADELE -201
A13: ADELE 1 B-202 | B13: New York | C13: 202 | F13: 1589 | H13: ADELE -202
A14: ADELE 1 B-301 | B14: Paris | C14: 301 | F14: 1639 | H14: ADELE -301
A15: ADELE 1 B-302 | B15: New York | C15: 302 | F15: 1589 | H15: ADELE -302
A16: ADELE 1 B-102 | B16: London | C16: 102 | F16: 1905 | H16: ADELE -102
A17: ADELE 1 B-202 | B17: Paris | C17: 202 | F17: 1639 | H17: ADELE -202
A18: ADELE 1 B-203 | B18: New York | C18: 203 | F18: 1589 | H18: ADELE -203
... A68: ADELE 3 H-302 | B68: New York | C68: 302 | F68: 1589 | H68: ADELE -302

Sheet I_Preferred Equity
A1: PREFERRED EQUITY TABLE
A2: Subordinated Loan #1 - Preferred Equity investors
A4: PREFERRED EQUITY INVESTORS
A5: ID | B5: Investor Name | C5: Contribution Amount | D5: Interest Rate | E5: Notes
A6: PE1 | C6: 0 | D6: 0
A7: PE2 | C7: 0 | D7: 0
A8: PE3 | C8: 0 | D8: 0
A9: PE4 | C9: 0 | D9: 0
A10: PE5 | C10: 0 | D10: 0
A11: PE6 | B11: =B32-B13-B10*2 | C11: 0 | D11: 0
A12: PE7 | C12: 0 | D12: 0
A13: PE8 | C13: 0 | D13: 0
A14: PE9 | C14: 0 | D14: 0
A15: PE10 | C15: 0 | D15: 0
A17: TOTAL | B17: Preferred Equity | C17: =SUM(C6:C15) | D17: Weighted Avg: | E17: =SUMPRODUCT(C6:C15,D6:D15)/C17
A20: INSTRUCTIONS:
A21: • Enter investor names in column B (yellow cells)
A22: • Enter contribution amounts in column C (yellow cells)
A23: • Enter interest rates in column D (yellow cells)
A24: • Add any notes in column E
A25: • Total will update automatically
A26: • This total is linked to Sources & Uses - Construction
B30: =-B13
B36: =B16
B37: =B32
B38: =B36-B37

Sheet I_Mezzanine Debt
A1: MEZZANINE DEBT TABLE
A2: Subordinated Loan #2 - Mezzanine lenders
A4: MEZZANINE LENDERS
A5: ID | B5: Lender Name | C5: Loan Amount | D5: Interest Rate | E5: Notes
A6: MEZZ1 | C6: 0 | D6: 0
A7: MEZZ2 | C7: 0 | D7: 0
A8: MEZZ3 | C8: 0 | D8: 0
A9: MEZZ4 | C9: 0 | D9: 0
A10: MEZZ5 | C10: 0 | D10: 0
A11: MEZZ6 | C11: 0 | D11: 0
A12: MEZZ7 | C12: 0 | D12: 0
A13: MEZZ8 | C13: 0 | D13: 0
A14: MEZZ9 | C14: 0 | D14: 0
A15: MEZZ10 | C15: 0 | D15: 0
A17: TOTAL | B17: Mezzanine Debt | C17: =SUM(C6:C15) | D17: Weighted Avg: | E17: =SUMPRODUCT(C6:C15,D6:D15)/C17
A20: INSTRUCTIONS:
A21: • Enter lender names in column B (yellow cells)
A22: • Enter loan amounts in column C (yellow cells)
A23: • Enter interest rates in column D (yellow cells)
A24: • Add any notes in column E
A25: • Total will update automatically
A26: • This total is linked to Sources & Uses - Construction
