Workbook

Sheet I_Inputs & Assumptions
A1: CONSTRUCTION-TO-PERMANENT FINANCIAL MODEL
A2: INPUTS & ASSUMPTIONS
A4: PROJECT INFORMATION
A5: Project Name | B5: Campus Adele
A6: Location | B6: Quebec
A7: Construction Start Date | B7: 2025-03-01
A8: Construction Duration | B8: 13 | C8: months
A9: Months Until First Units Ready | B9: 16 | C9: months
A10: Gap to Permanent Financing | B10: 1 | C10: months
A11: Permanent Loan Term | B11: 60 | C11: months
A12: Exit Timing (Post-Construction) | B12: 61 | C12: months
A14: CONSTRUCTION BUDGET
A15: Land - Purchase Price | B15: 400000
A16: Land - Recognized Value | B16: 600000
A17: Assessed Property Value | B17: 15000000
A18: Hard Costs by Category | B18: Budget | C18: Phasing % | D18: Holdback % | E18: Release (mo)
A19: Site Work & Demolition | B19: 500000 | C19: Equal | D19: 0.1 | E19: 3
A20: Foundation & Structure | B20: 3000000 | C20: Front-loaded | D20: 0.1 | E20: 2
A21: Building Envelope | B21: 2000000 | C21: Mid-weighted | D21: 0.1 | E21: 3
A22: MEP Systems | B22: 2500000 | C22: Mid-weighted | D22: 0.1 | E22: 4
A23: Interior Finishes | B23: 1500000 | C23: Back-loaded | D23: 0.1 | E23: 2
A24: Landscaping & Site | B24: 300000 | C24: Back-loaded | D24: 0.1 | E24: 6
A26: Soft Costs by Category | B26: Budget | C26: Holdback %
A27: Architecture & Engineering | B27: 400000 | C27: 0.1
A28: Permits & Approvals | B28: 150000 | C28: 0
A29: Legal & Financing Fees | B29: 200000 | C29: 0
A30: Development Management | B30: 300000 | C30: 0.1
A31: Marketing & Leasing | B31: 100000 | C31: 0
A33: Contingency | B33: 500000
A35: CONSTRUCTION FINANCING - SENIOR LOAN
A36: Loan-to-Cost (LTC) % | B36: 0.7719 | C36: % | G36: ='Sources & Uses - Construction'!A4 -> SOURCES OF FUNDS | H36: ='Sources & Uses - Construction'!B4 -> Amount
A37: Interest Rate (Annual) | B37: 0.0495 | C37: % | G37: ='Sources & Uses - Construction'!A5 -> In disbursement priority order (1→5) | H37: ='Sources & Uses - Construction'!B5 -> 0
A38: Commitment Fee | B38: 0.001 | C38: % | G38: ='Sources & Uses - Construction'!A6 -> 1. Class A Equity (GP - Land Contribution) | H38: ='Sources & Uses - Construction'!B6 -> 15
A39: Loan Amount | B39: 33627000 | C39: % | G39: ='Sources & Uses - Construction'!A7 -> 2. Class E Equity (LP Units) | H39: ='Sources & Uses - Construction'!B7 -> 2800015
A40: SUBORDINATED LOAN #1 - PREFERRED EQUITY | G40: ='Sources & Uses - Construction'!A8 -> 3. Subordinated Loan #1 (Preferred Equity) | H40: ='Sources & Uses - Construction'!B8 -> 0
A41: Loan Amount | B41: 0 | G41: ='Sources & Uses - Construction'!A9 -> 4. Subordinated Loan #2 (Mezzanine) | H41: ='Sources & Uses - Construction'!B9 -> 0
A42: Interest Rate (Annual) | B42: 0.08 | C42: % | G42: ='Sources & Uses - Construction'!A10 -> 0 | H42: ='Sources & Uses - Construction'!B10 -> 0
A43: Commitment Fee | B43: 0.001 | C43: % | G43: ='Sources & Uses - Construction'!A11 -> Required Additional Equity | H43: ='Sources & Uses - Construction'!B11 -> 7137311.9
A44: Draw Priority | B44: 1 | G44: ='Sources & Uses - Construction'!A12 -> 0 | H44: ='Sources & Uses - Construction'!B12 -> 0
G45: ='Sources & Uses - Construction'!A13 -> 5. Senior Construction Loan | H45: ='Sources & Uses - Construction'!B13 -> 33628383
A46: SUBORDINATED LOAN #2 - MEZZANINE | G46: ='Sources & Uses - Construction'!A14 -> 0 | H46: ='Sources & Uses - Construction'!B14 -> 0
A47: Loan Amount | B47: 0 | G47: ='Sources & Uses - Construction'!A15 -> 0 | H47: ='Sources & Uses - Construction'!B15 -> 0
A48: Interest Rate (Annual) | B48: 0.1 | C48: % | G48: ='Sources & Uses - Construction'!A16 -> TOTAL SOURCES | H48: ='Sources & Uses - Construction'!B16 -> 43565725
A49: Commitment Fee | B49: 0.001 | C49: % | G49: ='Sources & Uses - Construction'!A17 -> 0 | H49: ='Sources & Uses - Construction'!B17 -> 0
A50: Draw Priority | B50: 2 | G50: ='Sources & Uses - Construction'!A18 -> 0 | H50: ='Sources & Uses - Construction'!B18 -> 0
G51: ='Sources & Uses - Construction'!A19 -> USES OF FUNDS | H51: ='Sources & Uses - Construction'!B19 -> Amount
A52: GST/QST | G52: ='Sources & Uses - Construction'!A20 -> 1. LAND | H52: ='Sources & Uses - Construction'!B20 -> 1725168
A53: CASH MANAGEMENT | B53: 0.05 | C53: % | G53: ='Sources & Uses - Construction'!A21 -> 2. SITE SERVICING + LANDSCAPE | H53: ='Sources & Uses - Construction'!B21 -> 5168121
A54: Minimum Cash Balance | B54: 100000 | C54: Target minimum cash to maintain | G54: ='Sources & Uses - Construction'!A22 -> 3. HARD COSTS | H54: ='Sources & Uses - Construction'!B22 -> 25732155
A55: Sales Tax LOC Limit | B55: 750000 | C55: Maximum Sales Tax LOC | G55: ='Sources & Uses - Construction'!A23 -> 4. FF&E | H55: ='Sources & Uses - Construction'!B23 -> 1792768
A56: GST/QST LOC Facility Size | B56: 750000 | G56: ='Sources & Uses - Construction'!A24 -> 5. PROFESSIONAL FEES | H56: ='Sources & Uses - Construction'!B24 -> 3283546
G57: ='Sources & Uses - Construction'!A25 -> 6. FINANCE AND ADMINISTRATION | H57: ='Sources & Uses - Construction'!B25 -> 3276350
A58: PERMANENT FINANCING | G58: ='Sources & Uses - Construction'!A26 -> 7. TAX ASSESSMENT | H58: ='Sources & Uses - Construction'!B26 -> 2087617
A59: Permanent Loan Amount | B59: 19000000 | C59: $ | G59: ='Sources & Uses - Construction'!A27 -> 8. CONTINGENCY ALLOWANCE | H59: ='Sources & Uses - Construction'!B27 -> 500000
A60: CMB Rate | B60: 0.0329 | C60: % | G60: ='Sources & Uses - Construction'!A28 -> Capitalized Interest | H60: ='Sources & Uses - Construction'!B28 -> 0
A61: Markup | B61: 0.0045 | C61: % | G61: ='Sources & Uses - Construction'!A29 -> GST/QST Paid (Gross) | H61: ='Sources & Uses - Construction'!B29 -> 0
A62: Contingency | B62: 0 | C62: % | G62: ='Sources & Uses - Construction'!A30 -> 0 | H62: ='Sources & Uses - Construction'!B30 -> 0
A63: Total Interest Rate | B63: 0.0374 | C63: % | G63: ='Sources & Uses - Construction'!A31 -> 0 | H63: ='Sources & Uses - Construction'!B31 -> 0
A64: Amortization Period | B64: 50 | C64: years | G64: ='Sources & Uses - Construction'!A32 -> TOTAL USES | H64: ='Sources & Uses - Construction'!B32 -> 43565725
A65: DSCR Covenant Minimum | B65: 1.1 | C65: x | G65: ='Sources & Uses - Construction'!A33 -> 0 | H65: ='Sources & Uses - Construction'!B33 -> 0
G66: ='Sources & Uses - Construction'!A34 -> 0 | H66: ='Sources & Uses - Construction'!B34 -> 0
A67: EQUITY | G67: ='Sources & Uses - Construction'!A35 -> RECONCILIATION | H67: ='Sources & Uses - Construction'!B35 -> 0
A68: Class E (LP) Total Commitment | B68: 2800000 | G68: ='Sources & Uses - Construction'!A36 -> Total Sources | H68: ='Sources & Uses - Construction'!B36 -> 43565725
A69: Class A (GP) Land Contribution | B69: 0 | C69: (recognized value) | G69: ='Sources & Uses - Construction'!A37 -> Total Uses | H69: ='Sources & Uses - Construction'!B37 -> 43565725
A70: Preferred Return % (Annual) | B70: 0 | C70: %
A72: REVENUE ASSUMPTIONS
A73: Total Parking Spaces | B73: 47
A74: Revenue-Generating Parking Spaces | B74: 47
A75: Parking Rate | B75: 75 | C75: $/month
A76: Internet Rate per Unit | B76: 50 | C76: $/month
A77: EV Charging Stations | B77: 50
A78: EV Charging Rate | B78: 38 | C78: $/month
A79: Annual Revenue Growth | B79: 0.02 | C79: %
A80: Lease-Up Lag (Months) | B80: 2 | C80: months
A81: Stabilized Vacancy % | B81: 0.06 | C81: %
A82: Service Revenue Escalation | B82: 0.015 | C82: %
A83: OPERATING EXPENSES
A84: Municipal Tax - Mill Rate | B84: 0.0075 | C84: %
A85: School Tax - Mill Rate | B85: 0.00156 | C85: %
A86: Tax Start Delay (Post-Construction) | B86: 0 | C86: months
A87: Tax Assessment Escalation | B87: 0 | C87: %
A88: Operating Expense Line Items | B88: Annual Amount | C88: Escalation %
A89: Insurance | B89: 16989 | C89: 0.01
A90: Repairs & Maintenance | B90: 38400 | C90: 0.01
A91: Outdoor Amenities Maintenance | B91: 2000 | C91: 0.01
A92: Snow Removal, Grass, Garbage | B92: 23000 | C92: 0.01
A93: Janitor | B93: 23000 | C93: 0.01
A94: Cleaning Reserve on Turnover | B94: 7650 | C94: 0.01
A95: Security & Monitoring | B95: 9000 | C95: 0.01
A96: Internet | B96: 20000 | C96: 0.01
A97: EV Charging Stations | B97: 5000 | C97: 0.01
A98: Electricity (Common) | B98: 12200 | C98: 0.01
A99: Administration (% of EGI) | B99: 0.03 | C99: 0
A101: RESERVES | D101: Escalation %
A102: Appliance/Furniture Reserve | B102: 700 | C102: $/unit/year | D102: 0.01
A103: Structural Reserve | B103: 0.0075 | C103: % of EGI | D103: 0.01
A105: DISTRIBUTIONS
A106: Minimum Cash Balance | B106: 100000
A107: Distribution Frequency | B107: Quarterly
A109: Waterfall Structure
...

Sheet I_Budget Input Data
A1: BUDGET INPUT DATA
A2: Imported from ryanbudget.csv - Edit phasing, holdback, and eligibility as needed
A4: Row # | B4: Category | C4: Subcategory | D4: Budget Amount | E4: Phasing Pattern | F4: Holdback % | G4: Holdback Release (mo after constr) | H4: GST/QST Eligible
A5: 1 | D5: 0 | E5: Equal | F5: 0.1 | G5: 3 | H5: Yes
A6: 2 | B6: 1. LAND | C6: Land Acquisition | D6: 1600000 | E6: Upfront | F6: 0 | G6: 0 | H6: Yes
A7: 3 | B7: 1. LAND | C7: Notary and cadastre | D7: 19808 | E7: Upfront | F7: 0 | G7: 0 | H7: Yes
A8: 4 | B8: 1. LAND | C8: Cadastral operation | D8: 105360 | E8: Upfront | F8: 0 | G8: 0 | H8: Yes
A9: 5 | B9: 2. SITE SERVICING + LANDSCAPE | C9: Extension of services:Excavation & Backfill - Adjustment for Bldgs 5 & 6 | D9: 479320 | E9: Front-loaded | F9: 0.1 | G9: 3 | H9: Yes
A10: 6 | B10: 2. SITE SERVICING + LANDSCAPE | C10: Extension of services:Excavation & Backfill - Trailer pad, Access road, Septic tank | D10: 10900 | E10: Front-loaded | F10: 0.1 | G10: 3 | H10: Yes
A11: 7 | B11: 2. SITE SERVICING + LANDSCAPE | C11: Extension of services:Credit - Reservoir change | D11: 1946765 | E11: Front-loaded | F11: 0.1 | G11: 3 | H11: Yes
A12: 8 | B12: 2. SITE SERVICING + LANDSCAPE | C12: Extension of services:Credit - Reservoir change | D12: 0 | E12: Front-loaded | F12: 0.1 | G12: 3 | H12: Yes
A13: 9 | B13: 2. SITE SERVICING + LANDSCAPE | C13: Extension of services:Excavation & Backfill - Campus Civil | D13: 143113 | E13: Front-loaded | F13: 0.1 | G13: 3 | H13: Yes
A14: 10 | B14: 2. SITE SERVICING + LANDSCAPE | C14: Extension of services:Excavation & Backfill - Campus Civil | D14: 30493 | E14: Front-loaded | F14: 0.1 | G14: 3 | H14: Yes
A15: 11 | B15: 2. SITE SERVICING + LANDSCAPE | C15: Extension of services:Excavation & backfill - Extension - Mtee Ryan Civil | D15: 375295 | E15: Front-loaded | F15: 0.1 | G15: 3 | H15: Yes
A16: 12 | B16: 2. SITE SERVICING + LANDSCAPE | D16: 165563 | E16: Front-loaded | F16: 0.1 | G16: 3 | H16: Yes
A17: 13 | B17: 2. SITE SERVICING + LANDSCAPE | C17: Onsite services - civil:Excavation & Backfill (PC) | D17: 475672 | E17: Front-loaded | F17: 0.1 | G17: 3 | H17: Yes
A18: 14 | B18: 2. SITE SERVICING + LANDSCAPE | C18: Onsite services - civil:Excavation & Backfill (PC) | D18: 23100 | E18: Front-loaded | F18: 0.1 | G18: 3 | H18: Yes
A19: 15 | B19: 2. SITE SERVICING + LANDSCAPE | C19: Onsite services - civil:Excavation & Backfill (PC) | D19: 2300 | E19: Front-loaded | F19: 0.1 | G19: 3 | H19: Yes
A20: 16 | B20: 2. SITE SERVICING + LANDSCAPE | C20: Onsite services - civil:Excavation & Backfill (PC) | D20: 25102 | E20: Front-loaded | F20: 0.1 | G20: 3 | H20: Yes
A21: 17 | B21: 2. SITE SERVICING + LANDSCAPE | C21: Onsite services - civil:Excavation & Backfill (PC) | D21: 47223 | E21: Front-loaded | F21: 0.1 | G21: 3 | H21: Yes
A22: 18 | B22: 2. SITE SERVICING + LANDSCAPE | C22: Landscaping:Excavation & Backfill - Landscaping | D22: 1065794 | E22: Front-loaded | F22: 0.1 | G22: 3 | H22: Yes
A23: 19 | B23: 2. SITE SERVICING + LANDSCAPE | C23: Electrical services | D23: 252500 | E23: Front-loaded | F23: 0.1 | G23: 3 | H23: Yes
A24: 20 | B24: 2. SITE SERVICING + LANDSCAPE | C24: Electrical charging stations | D24: 124981 | E24: Front-loaded | F24: 0.1 | G24: 3 | H24: Yes
A25: 21 | B25: 3. HARD COSTS | C25: Admin and profit | D25: 1577987 | E25: Equal | F25: 0.1 | G25: 3 | H25: Yes
A26: 22 | B26: 3. HARD COSTS | C26: Insurance and bonding:Insurance | D26: 278718 | E26: Equal | F26: 0.1 | G26: 3 | H26: Yes
A27: 23 | B27: 3. HARD COSTS | D27: 140525 | E27: Equal | F27: 0.1 | G27: 3 | H27: Yes
A28: 24 | B28: 3. HARD COSTS | C28: Insurance and bonding:Wrap-up | D28: 36465 | E28: Equal | F28: 0.1 | G28: 3 | H28: Yes
A29: 25 | B29: 3. HARD COSTS | C29: Insurance and bonding:Bris des Machines | D29: 2585 | E29: Equal | F29: 0.1 | G29: 3 | H29: Yes
A30: 26 | B30: 3. HARD COSTS | C30: Insurance and bonding:L&M and Performance Bonds | D30: 0 | E30: Equal | F30: 0.1 | G30: 3 | H30: Yes
A31: 27 | B31: 3. HARD COSTS | C31: General conditions:CoSS Agent | D31: 236000 | E31: Equal | F31: 0.1 | G31: 3 | H31: Yes
A32: 28 | B32: 3. HARD COSTS | C32: General conditions:RSS Agent | D32: 213500 | E32: Equal | F32: 0.1 | G32: 3 | H32: Yes
A33: 29 | B33: 3. HARD COSTS | C33: General conditions:Superintendent 1 | D33: 303400 | E33: Equal | F33: 0.1 | G33: 3 | H33: Yes
A34: 30 | B34: 3. HARD COSTS | C34: General conditions:Superintendent 2 | D34: 266400 | E34: Equal | F34: 0.1 | G34: 3 | H34: Yes
A35: 31 | B35: 3. HARD COSTS | C35: General conditions:Project Manager | D35: 150750 | E35: Equal | F35: 0.1 | G35: 3 | H35: Yes
A36: 32 | B36: 3. HARD COSTS | C36: General conditions:Labourer | D36: 230020 | E36: Equal | F36: 0.1 | G36: 3 | H36: Yes
A37: 33 | B37: 3. HARD COSTS | C37: General Conditions: Logding | D37: 11000 | E37: Equal | F37: 0.1 | G37: 3 | H37: Yes
A38: 34 | B38: 3. HARD COSTS | C38: General conditions:Site fencing | D38: 10780 | E38: Equal | F38: 0.1 | G38: 3 | H38: Yes
A39: 35 | B39: 3. HARD COSTS | C39: General Conditions: Printing | D39: 8048 | E39: Equal | F39: 0.1 | G39: 3 | H39: Yes
... A57: 53 | B57: 3. HARD COSTS | C57: General conditions:Project signage | D57: 181830 | E57: Equal | F57: 0.1 | G57: 3 | H57: Yes
A58: 54 | B58: 3. HARD COSTS | D58: 6000 | E58: Equal | F58: 0.1 | G58: 3 | H58: Yes
A59: 55 | B59: 3. HARD COSTS | C59: General conditions:Miscellaneous | D59: 1901 | E59: Equal | F59: 0.1 | G59: 3 | H59: Yes
A60: 56 | B60: 3. HARD COSTS | C60: Formwork:Concrete purchases - Hambro floors | D60: 94276 | E60: Front-loaded | F60: 0.1 | G60: 3 | H60: Yes
A61: 57 | B61: 3. HARD COSTS | C61: Formwork:Stair slab concrete | D61: 27681 | E61: Front-loaded | F61: 0.1 | G61: 3 | H61: Yes
A62: 58 | B62: 3. HARD COSTS | C62: Concrete:Concrete purchases | D62: 97941 | E62: Front-loaded | F62: 0.1 | G62: 3 | H62: Yes
A63: 59 | B63: 3. HARD COSTS | C63: Formwork:Insulated formwork | D63: 2681518 | E63: Front-loaded | F63: 0.1 | G63: 3 | H63: Yes
A64: 60 | B64: 3. HARD COSTS | D64: 0 | E64: Equal | F64: 0.1 | G64: 3 | H64: Yes
A65: 61 | B65: 3. HARD COSTS | C65: Formwork:Wire mesh - Hambro floors | D65: 62581 | E65: Front-loaded | F65: 0.1 | G65: 3 | H65: Yes
A66: 62 | B66: 3. HARD COSTS | C66: Formwork:Cement finishing | D66: 163654 | E66: Front-loaded | F66: 0.1 | G66: 3 | H66: Yes
A67: 63 | B67: 3. HARD COSTS | C67: Formwork:Stair slab cement finishing | D67: 0 | E67: Front-loaded | F67: 0.1 | G67: 3 | H67: Yes
A68: 64 | B68: 3. HARD COSTS | C68: Formwork:Stair slab concrete pumps | D68: 0 | E68: Front-loaded | F68: 0.1 | G68: 3 | H68: Yes
A69: 65 | B69: 3. HARD COSTS | C69: Formwork:Concrete pumps | D69: 31715 | E69: Front-loaded | F69: 0.1 | G69: 3 | H69: Yes
A70: 66 | B70: 3. HARD COSTS | C70: Concrete:Concrete pumps | D70: 0 | E70: Front-loaded | F70: 0.1 | G70: 3 | H70: Yes
A71: 67 | B71: 3. HARD COSTS | C71: Concrete:Concrete accessories | D71: 79342 | E71: Front-loaded | F71: 0.1 | G71: 3 | H71: Yes
A72: 68 | B72: 3. HARD COSTS | C72: Concrete:Labour - Accessories | D72: 0 | E72: Front-loaded | F72: 0.1 | G72: 3 | H72: Yes
A73: 69 | B73: 3. HARD COSTS | C73: Concrete:Polyethylene .006 - changed to .010 2024-01-22 | D73: 0 | E73: Front-loaded | F73: 0.1 | G73: 3 | H73: Yes
A74: 70 | B74: 3. HARD COSTS | C74: Concrete:3'' Rigid insulation (4' perimeter) - changed to 2'' Blue | D74: 0 | E74: Front-loaded | F74: 0.1 | G74: 3 | H74: Yes
A75: 71 | B75: 3. HARD COSTS | C75: Concrete:Labour - Rigid insulation | D75: 0 | E75: Front-loaded | F75: 0.1 | G75: 3 | H75: Yes
A76: 72 | B76: 3. HARD COSTS | C76: Concrete:Wet cure | D76: 0 | E76: Front-loaded | F76: 0.1 | G76: 3 | H76: Yes
... A91: 87 | B91: 3. HARD COSTS | C91: Kitchen:Kitchens & vanities (QC) | D91: 844652 | E91: Back-loaded | F91: 0.1 | G91: 3 | H91: Yes
A92: 88 | B92: 3. HARD COSTS | D92: 0 | E92: Equal | F92: 0.1 | G92: 3 | H92: Yes
A93: 89 | B93: 3. HARD COSTS | C93: Kitchen:Quartz counters - Purchase | D93: 177900 | E93: Back-loaded | F93: 0.1 | G93: 3 | H93: Yes
A94: 90 | B94: 3. HARD COSTS | C94: Kitchen:Quartz counters - Installation | D94: 0 | E94: Back-loaded | F94: 0.1 | G94: 3 | H94: Yes
A95: 91 | B95: 3. HARD COSTS | C95: Carpentry rough:Roof insulation | D95: 35500 | E95: Mid-weighted | F95: 0.1 | G95: 3 | H95: Yes
A96: 92 | B96: 3. HARD COSTS | C96: Exterior finishes:Wood siding | D96: 1482450 | E96: Mid-weighted | F96: 0.1 | G96: 3 | H96: Yes
A97: 93 | B97: 3. HARD COSTS | C97: Exterior finishes:Acrylic stucco & Duroc | D97: 280000 | E97: Mid-weighted | F97: 0.1 | G97: 3 | H97: Yes
A98: 94 | B98: 3. HARD COSTS | C98: Roof, membrane:Roofing (Shingles) | D98: 280825 | E98: Mid-weighted | F98: 0.1 | G98: 3 | H98: Yes
A99: 95 | B99: 3. HARD COSTS | C99: Roof, membrane:Roofing (Winter conditions) | D99: 0 | E99: Mid-weighted | F99: 0.1 | G99: 3 | H99: Yes
A100: 96 | B100: 3. HARD COSTS | C100: Roof, membrane:Rain Gutters | D100: 36000 | E100: Mid-weighted | F100: 0.1 | G100: 3 | H100: Yes
A101: 97 | B101: 3. HARD COSTS | C101: Fenestration:Caulking | D101: 91200 | E101: Mid-weighted | F101: 0.1 | G101: 3 | H101: Yes
A102: 98 | B102: 3. HARD COSTS | C102: Doors and hardware:Wood doors | D102: 449827 | E102: Equal | F102: 0.1 | G102: 3 | H102: Yes
A103: 99 | B103: 3. HARD COSTS | D103: 49800 | E103: Equal | F103: 0.1 | G103: 3 | H103: Yes
A104: 100 | B104: 3. HARD COSTS | D104: 157600 | E104: Equal | F104: 0.1 | G104: 3 | H104: Yes
A105: 101 | B105: 3. HARD COSTS | C105: Carpentry finish:Carpentry | D105: 248100 | E105: Equal | F105: 0.1 | G105: 3 | H105: Yes
A106: 102 | B106: 3. HARD COSTS | C106: Doors and hardware:Baseboard, 1/4-round & casing | D106: 108850 | E106: Equal | F106: 0.1 | G106: 3 | H106: Yes
A107: 103 | B107: 3. HARD COSTS | C107: Carpentry finish:Shelving & Finish materials | D107: 0 | E107: Equal | F107: 0.1 | G107: 3 | H107: Yes
A108: 104 | B108: 3. HARD COSTS | C108: Fenestration:Windows & patio-doors - Supply | D108: 851388 | E108: Mid-weighted | F108: 0.1 | G108: 3 | H108: Yes
A109: 105 | B109: 3. HARD COSTS | C109: Fenestration:Transport & Handling - Quebec | D109: 0 | E109: Mid-weighted | F109: 0.1 | G109: 3 | H109: Yes
A110: 106 | B110: 3. HARD COSTS | C110: Interior systems:Drywall | D110: 2345879 | E110: Back-loaded | F110: 0.1 | G110: 3 | H110: Yes
A111: 107 | B111: 3. HARD COSTS | C111: Ceramic:Ceramic Purchase, Transport, Handling & Installation | D111: 179184 | E111: Back-loaded | F111: 0.1 | G111: 3 | H111: Yes
A112: 108 | B112: 3. HARD COSTS | C112: Ceramic:Shower walls | D112: 0 | E112: Back-loaded | F112: 0.1 | G112: 3 | H112: Yes
A113: 109 | B113: 3. HARD COSTS | C113: Ceramic:Bathroom floors (SPC) | D113: 208859 | E113: Back-loaded | F113: 0.1 | G113: 3 | H113: Yes
A114: 110 | B114: 3. HARD COSTS | C114: Floor covering:Vinyl flooring & Transport, Handling | D114: 343300 | E114: Back-loaded | F114: 0.1 | G114: 3 | H114: Yes
A115: 111 | B115: 3. HARD COSTS | D115: 0 | E115: Equal | F115: 0.1 | G115: 3 | H115: Yes
A116: 112 | B116: 3. HARD COSTS | C116: Paint:Painting | D116: 366000 | E116: Back-loaded | F116: 0.1 | G116: 3 | H116: Yes
A117: 113 | B117: 3. HARD COSTS | D117: 102000 | E117: Equal | F117: 0.1 | G117: 3 | H117: Yes
A118: 114 | B118: 3. HARD COSTS | D118: 0 | E118: Equal | F118: 0.1 | G118: 3 | H118: Yes
A119: 115 | B119: 3. HARD COSTS | C119: Railings:Foot grilles | D119: 0 | E119: Equal | F119: 0.1 | G119: 3 | H119: Yes
A120: 116 | B120: 3. HARD COSTS | C120: Railings:Interior signage | D120: 15300 | E120: Back-loaded | F120: 0.1 | G120: 3 | H120: Yes
A121: 117 | B121: 3. HARD COSTS | C121: Railings:WC acccessories | D121: 25750 | E121: Equal | F121: 0.1 | G121: 3 | H121: Yes
A122: 118 | B122: 3. HARD COSTS | C122: Plumbing:Plumbing (Rough S/I; Finish I/O) | D122: 1643900 | E122: Mid-weighted | F122: 0.1 | G122: 3 | H122: Yes
A123: 119 | B123: 3. HARD COSTS | C123: Plumbing:Plumbing finishes (S) - Toilet, Shower | D123: 377966 | E123: Mid-weighted | F123: 0.1 | G123: 3 | H123: Yes
A124: 120 | B124: 3. HARD COSTS | C124: Fire protection:Extinguishers | D124: 25500 | E124: Equal | F124: 0.1 | G124: 3 | H124: Yes
A125: 121 | B125: 3. HARD COSTS | C125: HVAC:HVAC | D125: 790030 | E125: Mid-weighted | F125: 0.1 | G125: 3 | H125: Yes
A126: 122 | B126: 3. HARD COSTS | C126: Electricity:Electricity | D126: 1866337 | E126: Mid-weighted | F126: 0.1 | G126: 3 | H126: Yes
A127: 123 | B127: 3. HARD COSTS | C127: Electricity:Lighting allowance | D127: 53300 | E127: Mid-weighted | F127: 0.1 | G127: 3 | H127: Yes
A128: 124 | B128: 3. HARD COSTS | C128: Electricity:Transport & Handling - Quebec | D128: 0 | E128: Mid-weighted | F128: 0.1 | G128: 3 | H128: Yes
A129: 125 | B129: 3. HARD COSTS | C129: Electricity:DEL Comptoirs (cuisines) | D129: 0 | E129: Mid-weighted | F129: 0.1 | G129: 3 | H129: Yes
A130: 126 | B130: 4. FF&E | C130: Appliances | D130: 403998 | E130: Back-loaded | F130: 0.05 | G130: 3 | H130: Yes
... A169: 165 | B169: 8. CONTINGENCY ALLOWANCE | C169: Contingency Non-Classified | D169: 0 | E169: As Needed | F169: 0 | G169: 0 | H169: Yes
A170: 166 | B170: HOLDBACKS | D170: 0 | E170: Equal | F170: 0.1 | G170: 3 | H170: Yes

Sheet I_Unit Rent Roll Data
A1: UNIT RENT ROLL DATA
A2: Exact import from Units-Proforma_View_Tremb.csv
A4: UnitId | B4: UnitRentalTypes | C4: Unit # | D4: Planned Delivery Date for Occupancy | E4: Projected Price Per Bedroom (from UnitRentalTypes) | F4: Projected Rate | G4: Bedroom Count (from UnitRentalTypes) | H4: Units Operations ID
A5: ADELE 1 A-101 | B5: London | C5: 101 | F5: 1905 | H5: ADELE -101 | I5: =F5*G5 -> 0
A6: ADELE 1 A-201 | B6: Berlin | C6: 201 | F6: 2455 | H6: ADELE -201 | I6: =F6*G6 -> 0
A7: ADELE 1 A-301 | B7: Berlin | C7: 301 | F7: 2455 | H7: ADELE -301
A8: ADELE 1 A-102 | B8: London | C8: 102 | F8: 1905 | H8: ADELE -102
A9: ADELE 1 A-202 | B9: Berlin | C9: 202 | F9: 2455 | H9: ADELE -202
A10: ADELE 1 A-302 | B10: Berlin | C10: 302 | F10: 2455 | H10: ADELE -302
A11: ADELE 1 B-101 | B11: London | C11: 101 | F11: 1905 | H11: ADELE -101
A12: ADELE 1 B-201 | B12: Paris | C12: 201 | F12: 1639 | H12: ADELE -201
A13: ADELE 1 B-202 | B13: New York | C13: 202 | F13: 1589 | H13: ADELE -202
A14: ADELE 1 B-301 | B14: Paris | C14: 301 | F14: 1639 | H14: ADELE -301
A15: ADELE 1 B-302 | B15: New York | C15: 302 | F15: 1589 | H15: ADELE -302
A16: ADELE 1 B-102 | B16: London | C16: 102 | F16: 1905 | H16: ADELE -102
A17: ADELE 1 B-202 | B17: Paris | C17: 202 | F17: 1639 | H17: ADELE -202
A18: ADELE 1 B-203 | B18: New York | C18: 203 | F18: 1589 | H18: ADELE -203
... A68: ADELE 3 H-302 | B68: New York | C68: 302 | F68: 1589 | H68: ADELE -302

Sheet i_Cap Table
A1: CAPITALIZATION TABLE
A2: Investor equity commitments and capital calls
A4: INVESTOR COMMITMENTS
A5: Investor Name | B5: Class | C5: Commitment Amount | D5: % of Class | E5: % of Total Equity
A6: Vafkor | B6: E | C6: 750000 | D6: =C6/SUMIF($B$6,"E",$C$6) -> 1 | E6: =C6/SUM($C$6) -> 1
A7: Masteko Inc | B7: E | C7: 500000 | D7: =C7/SUMIF($B$6:$B$7,"E",$C$6:$C$7) -> 0.4 | E7: =C7/SUM($C$6:$C$7) -> 0.4
A8: Gerome | B8: A | C8: 4.5 | D8: =C8/SUMIF($B$6:$B$8,"A",$C$6:$C$8) -> 1 | E8: =C8/SUM($C$6:$C$8) -> 3.599987e-06
A9: Julie Maranda Medicine Professional Corporation | B9: A | C9: 10.5 | D9: =C9/SUMIF($B$6:$B$9,"A",$C$6:$C$9) -> 0.7 | E9: =C9/SUM($C$6:$C$9) -> 8.3998992e-06
A10: Masteko Inc (Additional) | B10: E | C10: 3152 | D10: =C10/SUMIF($B$6:$B$10,"E",$C$6:$C$10) -> 0.0025152575 | E10: =C10/SUM($C$6:$C$10) -> 0.0025152274
A11: Michel Roux Holding Co | B11: E | C11: 250000 | D11: =C11/SUMIF($B$6:$B$11,"E",$C$6:$C$11) -> 0.16631718 | E11: =C11/SUM($C$6:$C$11) -> 0.16631552
A12: Dr Éric Tardif C.P. Inc. | B12: E | C12: 250000 | D12: =C12/SUMIF($B$6:$B$12,"E",$C$6:$C$12) -> 0.1426003 | E12: =C12/SUM($C$6:$C$12) -> 0.14259908
A13: Tristan Koran | B13: E | C13: 100000 | D13: =C13/SUMIF($B$6:$B$13,"E",$C$6:$C$13) -> 0.053962114 | E13: =C13/SUM($C$6:$C$13) -> 0.053961677
A14: Additional Equity Required | B14: E | C14: ='I_Inputs & Assumptions'!B68-SUMIF(B6:B13,"E",C6:C13) -> 946848 | D14: =C14/SUMIF($B$6:$B$14,"E",$C$6:$C$14) -> 0.33816 | E14: =C14/SUM($C$6:$C$14) -> 0.33815819
A15: CLASS A SUBTOTAL (GP - Land Contribution) | B15: A | C15: =SUMIF(B6:B14,"A",C6:C14) -> 15 | D15: 100.00% | E15: =C15/SUM(C6:C14) -> 5.3571142e-06
A16: CLASS E SUBTOTAL (LP Units) | B16: E | C16: =SUMIF(B6:B14,"E",C6:C14) -> 2800000 | D16: 100.00% | E16: =C16/SUM(C6:C14) -> 0.99999464
A18: TOTAL EQUITY COMMITMENTS | C18: =C15+C16 -> 2800015 | E18: 100.00%
A21: CAPITAL CALLS DURING CONSTRUCTION
A22: Based on pro-rata share when Class E equity is called
A24: Investor Name | B24: Class | C24: Commitment | D24: % of Class E | E24: Total Called | F24: Remaining
A25: Vafkor | B25: E | C25: =C6 -> 750000 | D25: =C25/C$16 -> 0.26785714 | E25: =C25 -> 750000 | F25: =C25-E25 -> 0
A26: Masteko Inc | B26: E | C26: =C7 -> 500000 | D26: =C26/C$16 -> 0.17857143 | E26: =C26 -> 500000 | F26: =C26-E26 -> 0
A27: Gerome | B27: A | C27: =C8 -> 4.5 | D27: N/A - Class A | E27: =C27 -> 4.5 | F27: =C27-E27 -> 0
A28: Julie Maranda Medicine Professional Corporation | B28: A | C28: =C9 -> 10.5 | D28: N/A - Class A | E28: =C28 -> 10.5 | F28: =C28-E28 -> 0
A29: Masteko Inc (Additional) | B29: E | C29: =C10 -> 3152 | D29: =C29/C$16 -> 0.0011257143 | E29: =C29 -> 3152 | F29: =C29-E29 -> 0
A30: Michel Roux Holding Co | B30: E | C30: =C11 -> 250000 | D30: =C30/C$16 -> 0.089285714 | E30: =C30 -> 250000 | F30: =C30-E30 -> 0
A31: Dr Éric Tardif C.P. Inc. | B31: E | C31: =C12 -> 250000 | D31: =C31/C$16 -> 0.089285714 | E31: =C31 -> 250000 | F31: =C31-E31 -> 0
A32: Tristan Koran | B32: E | C32: =C13 -> 100000 | D32: =C32/C$16 -> 0.035714286 | E32: =C32 -> 100000 | F32: =C32-E32 -> 0
A33: Additional Equity Required | B33: E | C33: =C14 -> 946848 | D33: =C33/C$16 -> 0.33816 | E33: =C33 -> 946848 | F33: =C33-E33 -> 0
A34: TOTAL CAPITAL CALLED | C34: =SUM(C25:C33) -> 2800015 | E34: =SUM(E25:E33) -> 2800015 | F34: =SUM(F25:F33) -> 0
A37: NOTE: 'Total Called' is now editable (yellow cells)
A38: • By default, Total Called = Commitment | B38: =C18 -> 2800015
A39: • Edit Total Called amounts as capital is actually called | B39: =E34 -> 2800015
A40: • Senior Construction Financing and other tabs reference these values | B40: ='Senior Construction Financing'!B57 -> 2800015
A41: Difference (Should be close to $0) | B41: =B40-B39 -> 0

Sheet I_Preferred Equity
A1: PREFERRED EQUITY TABLE
A2: Subordinated Loan #1 - Preferred Equity investors
A4: PREFERRED EQUITY INVESTORS
A5: ID | B5: Investor Name | C5: Contribution Amount | D5: Interest Rate | E5: Notes
A6: PE1 | C6: 0 | D6: 0
A7: PE2 | C7: 0 | D7: 0
A8: PE3 | C8: 0 | D8: 0
A9: PE4 | C9: 0 | D9: 0
A10: PE5 | C10: 0 | D10: 0
A11: PE6 | B11: =B32-B13-B10*2 -> 0 | C11: 0 | D11: 0
A12: PE7 | C12: 0 | D12: 0
A13: PE8 | C13: 0 | D13: 0
A14: PE9 | C14: 0 | D14: 0
A15: PE10 | C15: 0 | D15: 0
A17: TOTAL | B17: Preferred Equity | C17: =SUM(C6:C15) -> 0 | D17: Weighted Avg: | E17: =SUMPRODUCT(C6:C15,D6:D15)/C17 -> #DIV/0!
A20: INSTRUCTIONS:
A21: • Enter investor names in column B (yellow cells)
A22: • Enter contribution amounts in column C (yellow cells)
A23: • Enter interest rates in column D (yellow cells)
A24: • Add any notes in column E
A25: • Total will update automatically
A26: • This total is linked to Sources & Uses - Construction
B30: =-B13 -> 0
B36: =B16 -> 0
B37: =B32 -> 0
B38: =B36-B37 -> 0

Sheet I_Mezzanine Debt
A1: MEZZANINE DEBT TABLE
A2: Subordinated Loan #2 - Mezzanine lenders
A4: MEZZANINE LENDERS
A5: ID | B5: Lender Name | C5: Loan Amount | D5: Interest Rate | E5: Notes
A6: MEZZ1 | C6: 0 | D6: 0
A7: MEZZ2 | C7: 0 | D7: 0
A8: MEZZ3 | C8: 0 | D8: 0
A9: MEZZ4 | C9: 0 | D9: 0
A10: MEZZ5 | C10: 0 | D10: 0
A11: MEZZ6 | C11: 0 | D11: 0
A12: MEZZ7 | C12: 0 | D12: 0
A13: MEZZ8 | C13: 0 | D13: 0
A14: MEZZ9 | C14: 0 | D14: 0
A15: MEZZ10 | C15: 0 | D15: 0
A17: TOTAL | B17: Mezzanine Debt | C17: =SUM(C6:C15) -> 0 | D17: Weighted Avg: | E17: =SUMPRODUCT(C6:C15,D6:D15)/C17 -> #DIV/0!
A20: INSTRUCTIONS:
A21: • Enter lender names in column B (yellow cells)
A22: • Enter loan amounts in column C (yellow cells)
A23: • Enter interest rates in column D (yellow cells)
A24: • Add any notes in column E
A25: • Total will update automatically
A26: • This total is linked to Sources & Uses - Construction

Sheet Construction Budget & Draws
A1: CONSTRUCTION BUDGET & DRAWS
A2: References Budget Input Data tab
A4: BUDGET SUMMARY BY CATEGORY
A5: 1. LAND | B5: =SUMIF('I_Budget Input Data'!$B:$B,"1. LAND",'I_Budget Input Data'!$D:$D) -> 1725168
A6: 2. SITE SERVICING + LANDSCAPE | B6: =SUMIF('I_Budget Input Data'!$B:$B,"2. SITE SERVICING + LANDSCAPE",'I_Budget Input Data'!$D:$D) -> 5168121
A7: 3. HARD COSTS | B7: =SUMIF('I_Budget Input Data'!$B:$B,"3. HARD COSTS",'I_Budget Input Data'!$D:$D) -> 25732155
A8: 4. FF&E | B8: =SUMIF('I_Budget Input Data'!$B:$B,"4. FF&E",'I_Budget Input Data'!$D:$D) -> 1792768
A9: 5. PROFESSIONAL FEES | B9: =SUMIF('I_Budget Input Data'!$B:$B,"5. PROFESSIONAL FEES",'I_Budget Input Data'!$D:$D) -> 3283546
A10: 6. FINANCE AND ADMINISTRATION | B10: =SUMIF('I_Budget Input Data'!$B:$B,"6. FINANCE AND ADMINISTRATION",'I_Budget Input Data'!$D:$D) -> 3276350
A11: 7. TAX ASSESSMENT | B11: =SUMIF('I_Budget Input Data'!$B:$B,"7. TAX ASSESSMENT",'I_Budget Input Data'!$D:$D) -> 2087617
A12: 8. CONTINGENCY ALLOWANCE | B12: =SUMIF('I_Budget Input Data'!$B:$B,"8. CONTINGENCY ALLOWANCE",'I_Budget Input Data'!$D:$D) -> 500000
A14: TOTAL PROJECT COST (Before Cap Interest) | B14: =SUM(B5:B12) -> 43565725
A15: Capitalized Interest (from Financing tabs) | B15: ='Senior Construction Financing'!B56 -> 0
A16: =B174 -> Construction interest | B16: =-C174 -> -1592483
A17: GRAND TOTAL PROJECT COST | B17: =B14+IF(ISNUMBER(B15),B15,0) -> 43565725
A20: MONTHLY DRAW SCHEDULE
A21: Detailed monthly draws by line item
A22: Phasing logic:
A23: Category | B23: Subcategory | C23: Budget Amount | D23: Planned Budget Amount | E23: Checksum | F23: Month 1 | G23: Month 2 | H23: Month 3 | I23: Month 4 | J23: Month 5 | K23: Month 6 | L23: Month 7 | M23: Month 8 | N23: Month 9 | O23: Month 10 | P23: Month 11 | Q23: Month 12 | R23: Month 13 | S23: Month 14 | T23: Month 15 | U23: Month 16 | V23: Month 17 | W23: Month 18 | X23: Month 19 | Y23: Month 20 | Z23: Month 21 | AA23: Month 22 | AB23: Month 23 | AC23: Month 24 | AD23: Month 25 | AE23: Month 26 | AF23: Month 27 | AG23: Month 28 | AH23: Month 29 | AI23: Month 30 | AJ23: Month 31 | AK23: Month 32 | AL23: Month 33 | AM23: Month 34 | AN23: Month 35 | AO23: Month 36
A24: ='I_Budget Input Data'!B6 -> 1. LAND | B24: ='I_Budget Input Data'!C6 -> Land Acquisition | C24: ='I_Budget Input Data'!D6 -> 1600000 | D24: =SUM(F24:AO24) -> 1600000 | E24: =C24-D24 -> 0 | F24: ='Draw Calc (Hidden)'!C6 -> 1600000 | G24: ='Draw Calc (Hidden)'!D6 -> 0 | H24: ='Draw Calc (Hidden)'!E6 -> 0 | I24: ='Draw Calc (Hidden)'!F6 -> 0 | J24: ='Draw Calc (Hidden)'!G6 -> 0 | K24: ='Draw Calc (Hidden)'!H6 -> 0 | L24: ='Draw Calc (Hidden)'!I6 -> 0 | M24: ='Draw Calc (Hidden)'!J6 -> 0 | ... AO24: ='Draw Calc (Hidden)'!AL6 -> 0
A25: ='I_Budget Input Data'!B7 -> 1. LAND | B25: ='I_Budget Input Data'!C7 -> Notary and cadastre | C25: ='I_Budget Input Data'!D7 -> 19808 | D25: =SUM(F25:AO25) -> 19808 | E25: =C25-D25 -> 0 | F25: ='Draw Calc (Hidden)'!C7 -> 19808 | G25: ='Draw Calc (Hidden)'!D7 -> 0 | H25: ='Draw Calc (Hidden)'!E7 -> 0 | I25: ='Draw Calc (Hidden)'!F7 -> 0 | J25: ='Draw Calc (Hidden)'!G7 -> 0 | K25: ='Draw Calc (Hidden)'!H7 -> 0 | L25: ='Draw Calc (Hidden)'!I7 -> 0 | M25: ='Draw Calc (Hidden)'!J7 -> 0 | ... AO25: ='Draw Calc (Hidden)'!AL7 -> 0
A26: ='I_Budget Input Data'!B8 -> 1. LAND | B26: ='I_Budget Input Data'!C8 -> Cadastral operation | C26: ='I_Budget Input Data'!D8 -> 105360 | D26: =SUM(F26:AO26) -> 105360 | E26: =C26-D26 -> 0 | F26: ='Draw Calc (Hidden)'!C8 -> 105360 | G26: ='Draw Calc (Hidden)'!D8 -> 0 | H26: ='Draw Calc (Hidden)'!E8 -> 0 | I26: ='Draw Calc (Hidden)'!F8 -> 0 | J26: ='Draw Calc (Hidden)'!G8 -> 0 | K26: ='Draw Calc (Hidden)'!H8 -> 0 | L26: ='Draw Calc (Hidden)'!I8 -> 0 | M26: ='Draw Calc (Hidden)'!J8 -> 0 | ... AO26: ='Draw Calc (Hidden)'!AL8 -> 0
A27: ='I_Budget Input Data'!B9 -> 2. SITE SERVICING + LANDSCAPE | B27: ='I_Budget Input Data'!C9 -> Extension of services:Excavation & Backfill - Adjustment for Bldgs 5 & 6 | C27: ='I_Budget Input Data'!D9 -> 479320 | D27: =SUM(F27:AO27) -> 471945.85 | E27: =C27-D27 -> 7374.1538 | F27: ='Draw Calc (Hidden)'!C9 -> 44244.923 | G27: ='Draw Calc (Hidden)'!D9 -> 44244.923 | H27: ='Draw Calc (Hidden)'!E9 -> 44244.923 | I27: ='Draw Calc (Hidden)'!F9 -> 44244.923 | J27: ='Draw Calc (Hidden)'!G9 -> 44244.923 | K27: ='Draw Calc (Hidden)'!H9 -> 44244.923 | L27: ='Draw Calc (Hidden)'!I9 -> 29496.615 | M27: ='Draw Calc (Hidden)'!J9 -> 29496.615 | ... AO27: ='Draw Calc (Hidden)'!AL9 -> 0
A28: ='I_Budget Input Data'!B10 -> 2. SITE SERVICING + LANDSCAPE | B28: ='I_Budget Input Data'!C10 -> Extension of services:Excavation & Backfill - Trailer pad, Access road, Septic tank | C28: ='I_Budget Input Data'!D10 -> 10900 | D28: =SUM(F28:AO28) -> 10732.308 | E28: =C28-D28 -> 167.69231 | F28: ='Draw Calc (Hidden)'!C10 -> 1006.1538 | G28: ='Draw Calc (Hidden)'!D10 -> 1006.1538 | H28: ='Draw Calc (Hidden)'!E10 -> 1006.1538 | I28: ='Draw Calc (Hidden)'!F10 -> 1006.1538 | J28: ='Draw Calc (Hidden)'!G10 -> 1006.1538 | K28: ='Draw Calc (Hidden)'!H10 -> 1006.1538 | L28: ='Draw Calc (Hidden)'!I10 -> 670.76923 | M28: ='Draw Calc (Hidden)'!J10 -> 670.76923 | ... AO28: ='Draw Calc (Hidden)'!AL10 -> 0
A29: ='I_Budget Input Data'!B11 -> 2. SITE SERVICING + LANDSCAPE | B29: ='I_Budget Input Data'!C11 -> Extension of services:Credit - Reservoir change | C29: ='I_Budget Input Data'!D11 -> 1946765 | D29: =SUM(F29:AO29) -> 1916814.8 | E29: =C29-D29 -> 29950.231 | F29: ='Draw Calc (Hidden)'!C11 -> 179701.38 | G29: ='Draw Calc (Hidden)'!D11 -> 179701.38 | H29: ='Draw Calc (Hidden)'!E11 -> 179701.38 | I29: ='Draw Calc (Hidden)'!F11 -> 179701.38 | J29: ='Draw Calc (Hidden)'!G11 -> 179701.38 | K29: ='Draw Calc (Hidden)'!H11 -> 179701.38 | L29: ='Draw Calc (Hidden)'!I11 -> 119800.92 | M29: ='Draw Calc (Hidden)'!J11 -> 119800.92 | ... AO29: ='Draw Calc (Hidden)'!AL11 -> 0
A30: ='I_Budget Input Data'!B12 -> 2. SITE SERVICING + LANDSCAPE | B30: ='I_Budget Input Data'!C12 -> Extension of services:Credit - Reservoir change | C30: ='I_Budget Input Data'!D12 -> 0 | D30: =SUM(F30:AO30) -> 0 | E30: =C30-D30 -> 0 | F30: ='Draw Calc (Hidden)'!C12 -> 0 | G30: ='Draw Calc (Hidden)'!D12 -> 0 | H30: ='Draw Calc (Hidden)'!E12 -> 0 | I30: ='Draw Calc (Hidden)'!F12 -> 0 | J30: ='Draw Calc (Hidden)'!G12 -> 0 | K30: ='Draw Calc (Hidden)'!H12 -> 0 | L30: ='Draw Calc (Hidden)'!I12 -> 0 | M30: ='Draw Calc (Hidden)'!J12 -> 0 | ... AO30: ='Draw Calc (Hidden)'!AL12 -> 0
A31: ='I_Budget Input Data'!B13 -> 2. SITE SERVICING + LANDSCAPE | B31: ='I_Budget Input Data'!C13 -> Extension of services:Excavation & Backfill - Campus Civil | C31: ='I_Budget Input Data'!D13 -> 143113 | D31: =SUM(F31:AO31) -> 140911.26 | E31: =C31-D31 -> 2201.7385 | F31: ='Draw Calc (Hidden)'!C13 -> 13210.431 | G31: ='Draw Calc (Hidden)'!D13 -> 13210.431 | H31: ='Draw Calc (Hidden)'!E13 -> 13210.431 | I31: ='Draw Calc (Hidden)'!F13 -> 13210.431 | J31: ='Draw Calc (Hidden)'!G13 -> 13210.431 | K31: ='Draw Calc (Hidden)'!H13 -> 13210.431 | L31: ='Draw Calc (Hidden)'!I13 -> 8806.9538 | M31: ='Draw Calc (Hidden)'!J13 -> 8806.9538 | ... AO31: ='Draw Calc (Hidden)'!AL13 -> 0
A32: ='I_Budget Input Data'!B14 -> 2. SITE SERVICING + LANDSCAPE | B32: ='I_Budget Input Data'!C14 -> Extension of services:Excavation & Backfill - Campus Civil | C32: ='I_Budget Input Data'!D14 -> 30493 | D32: =SUM(F32:AO32) -> 30023.877 | E32: =C32-D32 -> 469.12308 | F32: ='Draw Calc (Hidden)'!C14 -> 2814.7385 | G32: ='Draw Calc (Hidden)'!D14 -> 2814.7385 | H32: ='Draw Calc (Hidden)'!E14 -> 2814.7385 | I32: ='Draw Calc (Hidden)'!F14 -> 2814.7385 | J32: ='Draw Calc (Hidden)'!G14 -> 2814.7385 | K32: ='Draw Calc (Hidden)'!H14 -> 2814.7385 | L32: ='Draw Calc (Hidden)'!I14 -> 1876.4923 | M32: ='Draw Calc (Hidden)'!J14 -> 1876.4923 | ... AO32: ='Draw Calc (Hidden)'!AL14 -> 0
A33: ='I_Budget Input Data'!B15 -> 2. SITE SERVICING + LANDSCAPE | B33: ='I_Budget Input Data'!C15 -> Extension of services:Excavation & backfill - Extension - Mtee Ryan Civil | C33: ='I_Budget Input Data'!D15 -> 375295 | D33: =SUM(F33:AO33) -> 369521.23 | E33: =C33-D33 -> 5773.7692 | F33: ='Draw Calc (Hidden)'!C15 -> 34642.615 | G33: ='Draw Calc (Hidden)'!D15 -> 34642.615 | H33: ='Draw Calc (Hidden)'!E15 -> 34642.615 | I33: ='Draw Calc (Hidden)'!F15 -> 34642.615 | J33: ='Draw Calc (Hidden)'!G15 -> 34642.615 | K33: ='Draw Calc (Hidden)'!H15 -> 34642.615 | L33: ='Draw Calc (Hidden)'!I15 -> 23095.077 | M33: ='Draw Calc (Hidden)'!J15 -> 23095.077 | ... AO33: ='Draw Calc (Hidden)'!AL15 -> 0
A34: ='I_Budget Input Data'!B16 -> 2. SITE SERVICING + LANDSCAPE | B34: ='I_Budget Input Data'!C16 -> 0 | C34: ='I_Budget Input Data'!D16 -> 165563 | D34: =SUM(F34:AO34) -> 163015.88 | E34: =C34-D34 -> 2547.1231 | F34: ='Draw Calc (Hidden)'!C16 -> 15282.738 | G34: ='Draw Calc (Hidden)'!D16 -> 15282.738 | H34: ='Draw Calc (Hidden)'!E16 -> 15282.738 | I34: ='Draw Calc (Hidden)'!F16 -> 15282.738 | J34: ='Draw Calc (Hidden)'!G16 -> 15282.738 | K34: ='Draw Calc (Hidden)'!H16 -> 15282.738 | L34: ='Draw Calc (Hidden)'!I16 -> 10188.492 | M34: ='Draw Calc (Hidden)'!J16 -> 10188.492 | ... AO34: ='Draw Calc (Hidden)'!AL16 -> 0
A35: ='I_Budget Input Data'!B17 -> 2. SITE SERVICING + LANDSCAPE | B35: ='I_Budget Input Data'!C17 -> Onsite services - civil:Excavation & Backfill (PC) | C35: ='I_Budget Input Data'!D17 -> 475672 | D35: =SUM(F35:AO35) -> 468353.97 | E35: =C35-D35 -> 7318.0308 | F35: ='Draw Calc (Hidden)'!C17 -> 43908.185 | G35: ='Draw Calc (Hidden)'!D17 -> 43908.185 | H35: ='Draw Calc (Hidden)'!E17 -> 43908.185 | I35: ='Draw Calc (Hidden)'!F17 -> 43908.185 | J35: ='Draw Calc (Hidden)'!G17 -> 43908.185 | K35: ='Draw Calc (Hidden)'!H17 -> 43908.185 | L35: ='Draw Calc (Hidden)'!I17 -> 29272.123 | M35: ='Draw Calc (Hidden)'!J17 -> 29272.123 | ... AO35: ='Draw Calc (Hidden)'!AL17 -> 0
... A188: ='I_Budget Input Data'!B170 -> HOLDBACKS | B188: ='I_Budget Input Data'!C170 -> 0 | C188: ='I_Budget Input Data'!D170 -> 0 | D188: =SUM(F188:AO188) -> 0 | E188: =C188-D188 -> 0 | F188: ='Draw Calc (Hidden)'!C170 -> 0 | G188: ='Draw Calc (Hidden)'!D170 -> 0 | H188: ='Draw Calc (Hidden)'!E170 -> 0 | I188: ='Draw Calc (Hidden)'!F170 -> 0 | J188: ='Draw Calc (Hidden)'!G170 -> 0 | K188: ='Draw Calc (Hidden)'!H170 -> 0 | L188: ='Draw Calc (Hidden)'!I170 -> 0 | M188: ='Draw Calc (Hidden)'!J170 -> 0 | ... AO188: ='Draw Calc (Hidden)'!AL170 -> 0
A190: TOTAL | B190: All Line Items | C190: =SUM(C24:C188) -> 43565725 | D190: =SUM(D24:D188) -> 43343780 | E190: =SUM(E24:E188) -> 221944.75 | F190: =SUM(F24:F188) -> 4759939 | G190: =SUM(G24:G188) -> 3034771 | H190: =SUM(H24:H188) -> 3034771 | I190: =SUM(I24:I188) -> 3279863.2 | J190: =SUM(J24:J188) -> 3279863.2 | ... AO190: =SUM(AO24:AO188) -> 0
A193: CONSTRUCTION PERIOD CASH FLOW
A194: Professional CFO-grade tracking - Subordinated sources deployed BEFORE Senior Loan
A196: Item | B196: Description | C196: Type | D196: Total | F196: ='Time Axis'!B4 -> 45747 | G196: ='Time Axis'!B5 -> 45777 | H196: ='Time Axis'!B6 -> 45808 | I196: ='Time Axis'!B7 -> 45838 | J196: ='Time Axis'!B8 -> 45869 | K196: ='Time Axis'!B9 -> 45900 | L196: ='Time Axis'!B10 -> 45930 | M196: ='Time Axis'!B11 -> 45961 | N196: ='Time Axis'!B12 -> 45991 | O196: ='Time Axis'!B13 -> 46022 | P196: ='Time Axis'!B14 -> 46053 | Q196: ='Time Axis'!B15 -> 46081 | R196: ='Time Axis'!B16 -> 46112 | S196: ='Time Axis'!B17 -> 46142 | T196: ='Time Axis'!B18 -> 46173 | U196: ='Time Axis'!B19 -> 46203 | V196: ='Time Axis'!B20 -> 46234 | W196: ='Time Axis'!B21 -> 46265 | X196: ='Time Axis'!B22 -> 46295 | Y196: ='Time Axis'!B23 -> 46326 | Z196: ='Time Axis'!B24 -> 46356 | AA196: ='Time Axis'!B25 -> 46387 | AB196: ='Time Axis'!B26 -> 46418 | AC196: ='Time Axis'!B27 -> 46446 | AD196: ='Time Axis'!B28 -> 46477 | AE196: ='Time Axis'!B29 -> 46507 | AF196: ='Time Axis'!B30 -> 46538 | AG196: ='Time Axis'!B31 -> 46568 | AH196: ='Time Axis'!B32 -> 46599 | AI196: ='Time Axis'!B33 -> 46630 | AJ196: ='Time Axis'!B34 -> 46660 | AK196: ='Time Axis'!B35 -> 46691 | AL196: ='Time Axis'!B36 -> 46721 | AM196: ='Time Axis'!B37 -> 46752 | AN196: ='Time Axis'!B38 -> 46783 | AO196: ='Time Axis'!B39 -> 46812
A197: OPENING BALANCE | B197: Cash at beginning of month | C197: Balance | D197: =F197 -> 0 | F197: 0 | G197: =F213 -> 5177402.9 | H197: =G213 -> 2142631.9 | I197: =H213 -> 100000 | J197: =I213 -> 100000 | K197: =J213 -> 100000 | L197: =K213 -> 100000 | M197: =L213 -> 100000 | N197: =M213 -> 100000 | ... AO197: =AN213 -> 100000
A198: CASH INFLOWS | B198: Sources of cash
A199: 1. Class A Equity (Land) | B199: From Sources & Uses - upfront | C199: Input | D199: =IFERROR('Sources & Uses - Construction'!B6,0) -> 15 | F199: =D199 -> 15 | G199: 0 | H199: 0 | I199: 0 | J199: 0 | K199: 0 | L199: 0 | M199: 0 | N199: 0 | O199: 0 | P199: 0 | Q199: 0 | R199: 0 | S199: 0 | T199: 0 | U199: 0 | V199: 0 | W199: 0 | X199: 0 | Y199: 0 | Z199: 0 | AA199: 0 | AB199: 0 | AC199: 0 | AD199: 0 | AE199: 0 | AF199: 0 | AG199: 0 | AH199: 0 | AI199: 0 | AJ199: 0 | AK199: 0 | AL199: 0 | AM199: 0 | AN199: 0 | AO199: 0
A200: 2. Class E Equity Calls | B200: From Sources & Uses - as needed | C200: Input | D200: =IFERROR('Sources & Uses - Construction'!B7,0) -> 2800015 | F200: =D200 -> 2800015 | G200: 0 | H200: 0 | I200: 0 | J200: 0 | K200: 0 | L200: 0 | M200: 0 | N200: 0 | O200: 0 | P200: 0 | Q200: 0 | R200: 0 | S200: 0 | T200: 0 | U200: 0 | V200: 0 | W200: 0 | X200: 0 | Y200: 0 | Z200: 0 | AA200: 0 | AB200: 0 | AC200: 0 | AD200: 0 | AE200: 0 | AF200: 0 | AG200: 0 | AH200: 0 | AI200: 0 | AJ200: 0 | AK200: 0 | AL200: 0 | AM200: 0 | AN200: 0 | AO200: 0
A201: 3. Preferred Equity Draws | B201: From Sources & Uses - as needed | C201: Input | D201: =IFERROR('Sources & Uses - Construction'!B8,0) -> 0 | F201: =D201 -> 0 | G201: 0 | H201: 0 | I201: 0 | J201: 0 | K201: 0 | L201: 0 | M201: 0 | N201: 0 | O201: 0 | P201: 0 | Q201: 0 | R201: 0 | S201: 0 | T201: 0 | U201: 0 | V201: 0 | W201: 0 | X201: 0 | Y201: 0 | Z201: 0 | AA201: 0 | AB201: 0 | AC201: 0 | AD201: 0 | AE201: 0 | AF201: 0 | AG201: 0 | AH201: 0 | AI201: 0 | AJ201: 0 | AK201: 0 | AL201: 0 | AM201: 0 | AN201: 0 | AO201: 0
A202: 4. Mezzanine Debt Draws | B202: From Sources & Uses - as needed | C202: Input | D202: =IFERROR('Sources & Uses - Construction'!B9,0) -> 0 | F202: =D202 -> 0 | G202: 0 | H202: 0 | I202: 0 | J202: 0 | K202: 0 | L202: 0 | M202: 0 | N202: 0 | O202: 0 | P202: 0 | Q202: 0 | R202: 0 | S202: 0 | T202: 0 | U202: 0 | V202: 0 | W202: 0 | X202: 0 | Y202: 0 | Z202: 0 | AA202: 0 | AB202: 0 | AC202: 0 | AD202: 0 | AE202: 0 | AF202: 0 | AG202: 0 | AH202: 0 | AI202: 0 | AJ202: 0 | AK202: 0 | AL202: 0 | AM202: 0 | AN202: 0 | AO202: 0
A203: 5. Required Additional Equity | B203: Additional capital if needed | C203: Input | D203: =IFERROR('Sources & Uses - Construction'!B11,0) -> 7137311.9 | F203: =D203 -> 7137311.9 | G203: 0 | H203: 0 | I203: 0 | J203: 0 | K203: 0 | L203: 0 | M203: 0 | N203: 0 | O203: 0 | P203: 0 | Q203: 0 | R203: 0 | S203: 0 | T203: 0 | U203: 0 | V203: 0 | W203: 0 | X203: 0 | Y203: 0 | Z203: 0 | AA203: 0 | AB203: 0 | AC203: 0 | AD203: 0 | AE203: 0 | AF203: 0 | AG203: 0 | AH203: 0 | AI203: 0 | AJ203: 0 | AK203: 0 | AL203: 0 | AM203: 0 | AN203: 0 | AO203: 0
A204: 6. SENIOR LOAN ADVANCE | B204: Covers construction after subordinated | C204: Calc | D204: =SUM(F204:AN204) -> 33506438 | F204: =MIN(MAX(0,'I_Inputs & Assumptions'!$B$54-(F197+(F199+F200+F201+F202+F203)-F211)),MAX(0,E218)) -> 0 | G204: =MIN(MAX(0,'I_Inputs & Assumptions'!$B$54-(G197+(G199+G200+G201+G202+G203)-G211)),MAX(0,F218)) -> 0 | H204: =MIN(MAX(0,'I_Inputs & Assumptions'!$B$54-(H197+(H199+H200+H201+H202+H203)-H211)),MAX(0,G218)) -> 992139.13 | I204: =MIN(MAX(0,'I_Inputs & Assumptions'!$B$54-(I197+(I199+I200+I201+I202+I203)-I211)),MAX(0,H218)) -> 3279863.2 | J204: =MIN(MAX(0,'I_Inputs & Assumptions'!$B$54-(J197+(J199+J200+J201+J202+J203)-J211)),MAX(0,I218)) -> 3279863.2 | K204: =MIN(MAX(0,'I_Inputs & Assumptions'!$B$54-(K197+(K199+K200+K201+K202+K203)-K211)),MAX(0,J218)) -> 3279863.2 | L204: =MIN(MAX(0,'I_Inputs & Assumptions'!$B$54-(L197+(L199+L200+L201+L202+L203)-L211)),MAX(0,K218)) -> 3081065.9 | M204: =MIN(MAX(0,'I_Inputs & Assumptions'!$B$54-(M197+(M199+M200+M201+M202+M203)-M211)),MAX(0,L218)) -> 3081065.9 | ... AO204: =MIN(MAX(0,'I_Inputs & Assumptions'!$B$54-(AO197+(AO199+AO200+AO201+AO202+AO203)-AO211)),MAX(0,AN218)) -> 0
A205: 7. Interdisbursement LOC Draw | B205: Maintains $100k minimum (max $1M total) | C205: Calc | D205: =SUM(F205:AN205) -> 0 | F205: =MIN(MAX(0,100000-(F197+F199+F200+F201+F202+F203+F204-F211)),MAX(0,1000000-0)) -> 0 | G205: =MIN(MAX(0,100000-(G197+G199+G200+G201+G202+G203+G204-G211)),MAX(0,1000000-F215)) -> 0 | H205: =MIN(MAX(0,100000-(H197+H199+H200+H201+H202+H203+H204-H211)),MAX(0,1000000-G215)) -> 0 | I205: =MIN(MAX(0,100000-(I197+I199+I200+I201+I202+I203+I204-I211)),MAX(0,1000000-H215)) -> 0 | J205: =MIN(MAX(0,100000-(J197+J199+J200+J201+J202+J203+J204-J211)),MAX(0,1000000-I215)) -> 0 | K205: =MIN(MAX(0,100000-(K197+K199+K200+K201+K202+K203+K204-K211)),MAX(0,1000000-J215)) -> 0 | L205: =MIN(MAX(0,100000-(L197+L199+L200+L201+L202+L203+L204-L211)),MAX(0,1000000-K215)) -> 0 | M205: =MIN(MAX(0,100000-(M197+M199+M200+M201+M202+M203+M204-M211)),MAX(0,1000000-L215)) -> 0 | N205: =MIN(MAX(0,100000-(N197+N199+N200+N201+N202+N203+N204-N211)),MAX(0,1000000-M215)) -> 0 | ... AO205: =MIN(MAX(0,100000-(AO197+AO199+AO200+AO201+AO202+AO203+AO204-AO211)),MAX(0,1000000-AN215)) -> 0
A206: TOTAL INFLOWS | B206: Sum of all sources | D206: =SUM(D199:D205) -> 43443780 | F206: =SUM(F199:F205) -> 9937341.9 | G206: =SUM(G199:G205) -> 0 | H206: =SUM(H199:H205) -> 992139.13 | I206: =SUM(I199:I205) -> 3279863.2 | J206: =SUM(J199:J205) -> 3279863.2 | K206: =SUM(K199:K205) -> 3279863.2 | L206: =SUM(L199:L205) -> 3081065.9 | M206: =SUM(M199:M205) -> 3081065.9 | ... AO206: =SUM(AO199:AO205) -> 0
A207: CASH OUTFLOWS | B207: Uses of cash
A208: Construction Costs | B208: From budget schedule (row 190) | C208: Calc | D208: =SUM(F208:AN208) -> 43343780 | F208: =F190 -> 4759939 | G208: =G190 -> 3034771 | H208: =H190 -> 3034771 | I208: =I190 -> 3279863.2 | J208: =J190 -> 3279863.2 | K208: =K190 -> 3279863.2 | L208: =L190 -> 3081065.9 | M208: =M190 -> 3081065.9 | ... AO208: =AO190 -> 0
A209: Interest Payments | B209: On LOC balances | C209: Input | D209: =SUM(F209:AN209) -> 0 | F209: 0 | G209: 0 | H209: 0 | I209: 0 | J209: 0 | K209: 0 | L209: 0 | M209: 0 | N209: 0 | O209: 0 | P209: 0 | Q209: 0 | R209: 0 | S209: 0 | T209: 0 | U209: 0 | V209: 0 | W209: 0 | X209: 0 | Y209: 0 | Z209: 0 | AA209: 0 | AB209: 0 | AC209: 0 | AD209: 0 | AE209: 0 | AF209: 0 | AG209: 0 | AH209: 0 | AI209: 0 | AJ209: 0 | AK209: 0 | AL209: 0 | AM209: 0 | AN209: 0 | AO209: 0
A210: Interdisbursement LOC Repayments | B210: Paydown of LOC | C210: Input | D210: =SUM(F210:AN210) -> 0 | F210: 0 | G210: 0 | H210: 0 | I210: 0 | J210: 0 | K210: 0 | L210: 0 | M210: 0 | N210: 0 | O210: 0 | P210: 0 | Q210: 0 | R210: 0 | S210: 0 | T210: 0 | U210: 0 | V210: 0 | W210: 0 | X210: 0 | Y210: 0 | Z210: 0 | AA210: 0 | AB210: 0 | AC210: 0 | AD210: 0 | AE210: 0 | AF210: 0 | AG210: 0 | AH210: 0 | AI210: 0 | AJ210: 0 | AK210: 0 | AL210: 0 | AM210: 0 | AN210: 0 | AO210: 0
A211: TOTAL OUTFLOWS | B211: Sum of all uses | D211: =SUM(D208:D210) -> 43343780 | F211: =SUM(F208:F210) -> 4759939 | G211: =SUM(G208:G210) -> 3034771 | H211: =SUM(H208:H210) -> 3034771 | I211: =SUM(I208:I210) -> 3279863.2 | J211: =SUM(J208:J210) -> 3279863.2 | K211: =SUM(K208:K210) -> 3279863.2 | L211: =SUM(L208:L210) -> 3081065.9 | M211: =SUM(M208:M210) -> 3081065.9 | ... AO211: =SUM(AO208:AO210) -> 0
A212: NET CASH FLOW | B212: Inflows - Outflows | D212: =D206-D211 -> 100000 | F212: =F206-F211 -> 5177402.9 | G212: =G206-G211 -> -3034771 | H212: =H206-H211 -> -2042631.9 | I212: =I206-I211 -> 0 | J212: =J206-J211 -> 0 | K212: =K206-K211 -> 0 | L212: =L206-L211 -> 0 | M212: =M206-M211 -> 0 | ... AO212: =AO206-AO211 -> 0
A213: CLOSING BALANCE | B213: Opening + Net Cash Flow | D213: =AN213 -> 100000 | F213: =F197+F212 -> 5177402.9 | G213: =G197+G212 -> 2142631.9 | H213: =H197+H212 -> 100000 | I213: =I197+I212 -> 100000 | J213: =J197+J212 -> 100000 | K213: =K197+K212 -> 100000 | L213: =L197+L212 -> 100000 | M213: =M197+M212 -> 100000 | ... AO213: =AO197+AO212 -> 100000
A214: Cash vs $100k Minimum | B214: Closing - $100,000 (should be ≥ $0) | C214: Check | D214: ≥ $0 is OK | F214: =F213-100000 -> 5077402.9 | G214: =G213-100000 -> 2042631.9 | H214: =H213-100000 -> 0 | I214: =I213-100000 -> 0 | J214: =J213-100000 -> 0 | K214: =K213-100000 -> 0 | L214: =L213-100000 -> 0 | M214: =M213-100000 -> 0 | ... AO214: =AO213-100000 -> 0
A215: Interdisbursement LOC Balance | B215: Cumulative balance (should be ≤ $1M) | C215: Check | D215: =AN215 -> 0 | F215: =F205-F210 -> 0 | G215: =F215+G205-G210 -> 0 | H215: =G215+H205-H210 -> 0 | I215: =H215+I205-I210 -> 0 | J215: =I215+J205-J210 -> 0 | K215: =J215+K205-K210 -> 0 | L215: =K215+L205-L210 -> 0 | M215: =L215+M205-M210 -> 0 | N215: =M215+N205-N210 -> 0 | ... AO215: =AN215+AO205-AO210 -> 0
A216: Total Sources Check | B216: Cash Flow Total vs Sources & Uses | C216: Check
B218: Senior Loan Advance Left | F218: =MAX(0,'Sources & Uses - Construction'!$B$13-SUM($F204:F204)) -> 33628383 | G218: =MAX(0,'Sources & Uses - Construction'!$B$13-SUM($F204:G204)) -> 33628383 | H218: =MAX(0,'Sources & Uses - Construction'!$B$13-SUM($F204:H204)) -> 32636244 | I218: =MAX(0,'Sources & Uses - Construction'!$B$13-SUM($F204:I204)) -> 29356381 | J218: =MAX(0,'Sources & Uses - Construction'!$B$13-SUM($F204:J204)) -> 26076518 | K218: =MAX(0,'Sources & Uses - Construction'!$B$13-SUM($F204:K204)) -> 22796654 | L218: =MAX(0,'Sources & Uses - Construction'!$B$13-SUM($F204:L204)) -> 19715588 | M218: =MAX(0,'Sources & Uses - Construction'!$B$13-SUM($F204:M204)) -> 16634523 | ... AA218: =MAX(0,'Sources & Uses - Construction'!$B$13-SUM($F204:AA204)) -> 121944.75 | AB218: =MAX(0,'Sources & Uses - Construction'!$B$13-SUM($F204:AA204)) -> 121944.75 | AC218: =MAX(0,'Sources & Uses - Construction'!$B$13-SUM($F204:AB204)) -> 121944.75 | AD218: =MAX(0,'Sources & Uses - Construction'!$B$13-SUM($F204:AC204)) -> 121944.75 | AE218: =MAX(0,'Sources & Uses - Construction'!$B$13-SUM($F204:AD204)) -> 121944.75 | AF218: =MAX(0,'Sources & Uses - Construction'!$B$13-SUM($F204:AE204)) -> 121944.75 | AG218: =MAX(0,'Sources & Uses - Construction'!$B$13-SUM($F204:AF204)) -> 121944.75 | AH218: =MAX(0,'Sources & Uses - Construction'!$B$13-SUM($F204:AG204)) -> 121944.75 | AI218: =MAX(0,'Sources & Uses - Construction'!$B$13-SUM($F204:AH204)) -> 121944.75 | ... AO218: =MAX(0,'Sources & Uses - Construction'!$B$13-SUM($F204:AN204)) -> 121944.75
A220: BUSINESS RULES & VALIDATION
A221: Automated checks to ensure model integrity
A223: Check Description | B223: Formula | C223: Result | D223: Status
A224: 1. Minimum Cash Balance ($100k) | B224: All closing balances ≥ $100,000 | C224: =MIN(F213:AN213)-100000 -> 0 | D224: =IF(C224>=0,"✓ PASS","✗ FAIL") -> ✓ PASS
A225: 2. Senior Loan vs Maximum | B225: Total drawn ≤ S&U maximum | C225: =D204-IFERROR('Sources & Uses - Construction'!B13,0) -> -121944.75 | D225: =IF(C225<=0,"✓ PASS","✗ FAIL") -> ✓ PASS
A226: 3. Interdisbursement LOC Limit ($1M) | B226: All LOC balances ≤ $1,000,000 | C226: =MAX(F215:AN215)-1000000 -> -1000000 | D226: =IF(C226<=0,"✓ PASS","✗ FAIL") -> ✓ PASS
A227: 4. Total Sources Synchronization | B227: Cash Flow total = S&U total | C227: =(D199+D200+D201+D202+D203+D204)-IFERROR('Sources & Uses - Construction'!B16,0) -> -121944.75 | D227: =IF(ABS(C227)<1,"✓ PASS","✗ FAIL") -> ✗ FAIL
A229: OVERALL MODEL STATUS | B229: All checks must pass | C229: =COUNTIF(D224:D228,"✓ PASS") -> 3 | D229: =IF(C229=4,"✓✓ MODEL VALID ✓✓","⚠ ISSUES DETECTED ⚠") -> ⚠ ISSUES DETECTED ⚠
A232: CHECKSUMS - SOURCES & USES RECONCILIATION
A233: Verify all sources match between Cash Flow and Sources & Uses
A235: Source Item | B235: Cash Flow Total | C235: Sources & Uses | D235: Difference
A236: Class A Equity | B236: =D199 -> 15 | C236: =IFERROR('Sources & Uses - Construction'!B6,0) -> 15 | D236: =B236-C236 -> 0
A237: Class E Equity | B237: =D200 -> 2800015 | C237: =IFERROR('Sources & Uses - Construction'!B7,0) -> 2800015 | D237: =B237-C237 -> 0
A238: Preferred Equity | B238: =D201 -> 0 | C238: =IFERROR('Sources & Uses - Construction'!B8,0) -> 0 | D238: =B238-C238 -> 0
A239: Mezzanine Debt | B239: =D202 -> 0 | C239: =IFERROR('Sources & Uses - Construction'!B9,0) -> 0 | D239: =B239-C239 -> 0
A240: Required Additional | B240: =D203 -> 7137311.9 | C240: =IFERROR('Sources & Uses - Construction'!B11,0) -> 7137311.9 | D240: =B240-C240 -> 0
A241: Senior Loan | B241: =D204 -> 33506438 | C241: =IFERROR('Sources & Uses - Construction'!B13,0) -> 33628383 | D241: =B241-C241 -> -121944.75
A242: Interdisbursement LOC | B242: =D205 -> 0 | C242: N/A | D242: N/A
A243: TOTAL SOURCES | B243: =B236+B237+B238+B239+B240+B241 -> 43443780 | C243: =IFERROR('Sources & Uses - Construction'!B16,0) -> 43565725 | D243: =B243-C243 -> -121944.75
A244: Status | D244: =IF(ABS(D243)<1,"✓ RECONCILED","✗ NOT RECONCILED") -> ✗ NOT RECONCILED

Sheet Sources & Uses - Construction
A1: SOURCES & USES - CONSTRUCTION PERIOD
A2: Static summary of construction funding
A4: SOURCES OF FUNDS | B4: Amount
A5: In disbursement priority order (1→5)
A6: 1. Class A Equity (GP - Land Contribution) | B6: ='i_Cap Table'!C15 -> 15 | C6: Land contribution (upfront)
A7: 2. Class E Equity (LP Units) | B7: ='i_Cap Table'!E34 -> 2800015 | C7: From Cap Table - called during construction
A8: 3. Subordinated Loan #1 (Preferred Equity) | B8: ='I_Preferred Equity'!C17 -> 0 | C8: From Preferred Equity table
A9: 4. Subordinated Loan #2 (Mezzanine) | B9: ='I_Mezzanine Debt'!C17 -> 0 | C9: From Mezzanine Debt table
A11: Required Additional Equity | B11: =B32-B13-SUM(B5:B9) -> 7137311.9 | C11: Calculated gap - additional equity needed
A13: 5. Senior Construction Loan | B13: ='Senior Construction Financing'!B9 -> 33628383 | C13: Residual only - after all subordinated
A16: TOTAL SOURCES | B16: =SUM(B6:B14)-B10 -> 43565725
A19: USES OF FUNDS | B19: Amount
A20: 1. LAND | B20: =SUMIF('I_Budget Input Data'!$B:$B,"1. LAND",'I_Budget Input Data'!$D:$D) -> 1725168
A21: 2. SITE SERVICING + LANDSCAPE | B21: =SUMIF('I_Budget Input Data'!$B:$B,"2. SITE SERVICING + LANDSCAPE",'I_Budget Input Data'!$D:$D) -> 5168121
A22: 3. HARD COSTS | B22: =SUMIF('I_Budget Input Data'!$B:$B,"3. HARD COSTS",'I_Budget Input Data'!$D:$D) -> 25732155
A23: 4. FF&E | B23: =SUMIF('I_Budget Input Data'!$B:$B,"4. FF&E",'I_Budget Input Data'!$D:$D) -> 1792768
A24: 5. PROFESSIONAL FEES | B24: =SUMIF('I_Budget Input Data'!$B:$B,"5. PROFESSIONAL FEES",'I_Budget Input Data'!$D:$D) -> 3283546
A25: 6. FINANCE AND ADMINISTRATION | B25: =SUMIF('I_Budget Input Data'!$B:$B,"6. FINANCE AND ADMINISTRATION",'I_Budget Input Data'!$D:$D) -> 3276350
A26: 7. TAX ASSESSMENT | B26: =SUMIF('I_Budget Input Data'!$B:$B,"7. TAX ASSESSMENT",'I_Budget Input Data'!$D:$D) -> 2087617
A27: 8. CONTINGENCY ALLOWANCE | B27: =SUMIF('I_Budget Input Data'!$B:$B,"8. CONTINGENCY ALLOWANCE",'I_Budget Input Data'!$D:$D) -> 500000
A28: Capitalized Interest | B28: =IFERROR('Senior Construction Financing'!B56, 0) -> 0
A29: GST/QST Paid (Gross) | B29: 0 | C29: Set to $0
A32: TOTAL USES | B32: =SUM(B19:B29) -> 43565725
A35: RECONCILIATION
A36: Total Sources | B36: =B16 -> 43565725
A37: Total Uses | B37: =B32 -> 43565725
A38: Difference (Should be $0) | B38: =B36-B37 -> 0
A39: Status | B39: =IF(ABS(B38)<1,"✓ BALANCED","✗ NOT BALANCED") -> ✓ BALANCED

Sheet Senior Construction Financing
A1: SENIOR CONSTRUCTION FINANCING
A2: Monthly tracking of construction loan draws, interest, and equity calls
A4: LOAN PARAMETERS
A5: Loan-to-Cost (LTC): | B5: ='I_Inputs & Assumptions'!B36 -> 0.7719
A6: Interest Rate (Annual): | B6: ='I_Inputs & Assumptions'!B37 -> 0.0495
A7: Commitment Fee: | B7: ='I_Inputs & Assumptions'!B38 -> 0.001
A8: Total Project Cost (from Budget): | B8: ='Construction Budget & Draws'!C190 -> 43565725
A9: Maximum Loan Amount (LTC × Cost): | B9: =B8*B5 -> 33628383
A12: MONTHLY CONSTRUCTION LOAN SCHEDULE
A13: Month | B13: Date | C13: Phase | D13: Beg Balance | E13: Construction Draws | F13: Less: Holdback (10%) | G13: Net Draw | H13: Senior Loan Advance | I13: Interest Accrued | J13: Commitment Fee | K13: End Balance | L13: Cumul Cap Interest | M13: Equity Called (Class E) | N13: Cash Balance Check
A14: 1 | B14: ='Time Axis'!B4 -> 45747 | C14: ='Time Axis'!C4 -> Construction | D14: 0 | E14: ='Construction Budget & Draws'!F$190 -> 4759939 | F14: =-E14*0.1 -> -475993.9 | G14: =E14+F14 -> 4283945.1 | H14: {=TRANSPOSE('Construction Budget & Draws'!F204:AO204)} -> 0 | I14: =IF(C14="Construction",(D14)*$B$6/12,0) -> 0 | J14: =$B$9*$B$7 -> 33628.383 | N14: =#REF!+M14-G14 -> #REF!
A15: 2 | B15: ='Time Axis'!B5 -> 45777 | C15: ='Time Axis'!C5 -> Construction | D15: =K14 -> 0 | E15: ='Construction Budget & Draws'!G$190 -> 3034771 | F15: =-E15*0.1 -> -303477.1 | G15: =E15+F15 -> 2731293.9 | H15: 0 | I15: =IF(C15="Construction",(D15)*$B$6/12,0) -> 0 | J15: 0 | N15: =H15+M15-G15 -> -2731293.9
A16: 3 | B16: ='Time Axis'!B6 -> 45808 | C16: ='Time Axis'!C6 -> Construction | D16: =K15 -> 0 | E16: ='Construction Budget & Draws'!H$190 -> 3034771 | F16: =-E16*0.1 -> -303477.1 | G16: =E16+F16 -> 2731293.9 | H16: 992139.13 | I16: =IF(C16="Construction",(D16)*$B$6/12,0) -> 0 | J16: 0 | N16: =H16+M16-G16 -> -1739154.8
A17: 4 | B17: ='Time Axis'!B7 -> 45838 | C17: ='Time Axis'!C7 -> Construction | D17: =K16 -> 0 | E17: ='Construction Budget & Draws'!I$190 -> 3279863.2 | F17: =-E17*0.1 -> -327986.32 | G17: =E17+F17 -> 2951876.9 | H17: 3279863.2 | I17: =IF(C17="Construction",(D17)*$B$6/12,0) -> 0 | J17: 0 | N17: =H17+M17-G17 -> 327986.32
A18: 5 | B18: ='Time Axis'!B8 -> 45869 | C18: ='Time Axis'!C8 -> Construction | D18: =K17 -> 0 | E18: ='Construction Budget & Draws'!J$190 -> 3279863.2 | F18: =-E18*0.1 -> -327986.32 | G18: =E18+F18 -> 2951876.9 | H18: 3279863.2 | I18: =IF(C18="Construction",(D18)*$B$6/12,0) -> 0 | J18: 0 | N18: =H18+M18-G18 -> 327986.32
A19: 6 | B19: ='Time Axis'!B9 -> 45900 | C19: ='Time Axis'!C9 -> Construction | D19: =K18 -> 0 | E19: ='Construction Budget & Draws'!K$190 -> 3279863.2 | F19: =-E19*0.1 -> -327986.32 | G19: =E19+F19 -> 2951876.9 | H19: 3279863.2 | I19: =IF(C19="Construction",(D19)*$B$6/12,0) -> 0 | J19: 0 | N19: =H19+M19-G19 -> 327986.32
A20: 7 | B20: ='Time Axis'!B10 -> 45930 | C20: ='Time Axis'!C10 -> Construction | D20: =K19 -> 0 | E20: ='Construction Budget & Draws'!L$190 -> 3081065.9 | F20: =-E20*0.1 -> -308106.59 | G20: =E20+F20 -> 2772959.3 | H20: 3081065.9 | I20: =IF(C20="Construction",(D20)*$B$6/12,0) -> 0 | J20: 0 | N20: =H20+M20-G20 -> 308106.59
A21: 8 | B21: ='Time Axis'!B11 -> 45961 | C21: ='Time Axis'!C11 -> Construction | D21: =K20 -> 0 | E21: ='Construction Budget & Draws'!M$190 -> 3081065.9 | F21: =-E21*0.1 -> -308106.59 | G21: =E21+F21 -> 2772959.3 | H21: 3081065.9 | I21: =IF(C21="Construction",(D21)*$B$6/12,0) -> 0 | J21: 0 | N21: =H21+M21-G21 -> 308106.59
A22: 9 | B22: ='Time Axis'!B12 -> 45991 | C22: ='Time Axis'!C12 -> Construction | D22: =K21 -> 0 | E22: ='Construction Budget & Draws'!N$190 -> 3081065.9 | F22: =-E22*0.1 -> -308106.59 | G22: =E22+F22 -> 2772959.3 | H22: 3081065.9 | I22: =IF(C22="Construction",(D22)*$B$6/12,0) -> 0 | J22: 0 | N22: =H22+M22-G22 -> 308106.59
A23: 10 | B23: ='Time Axis'!B13 -> 46022 | C23: ='Time Axis'!C13 -> Construction | D23: =K22 -> 0 | E23: ='Construction Budget & Draws'!O$190 -> 2835973.7 | F23: =-E23*0.1 -> -283597.37 | G23: =E23+F23 -> 2552376.3 | H23: 2835973.7 | I23: =IF(C23="Construction",(D23)*$B$6/12,0) -> 0 | J23: 0 | N23: =H23+M23-G23 -> 283597.37
A24: 11 | B24: ='Time Axis'!B14 -> 46053 | C24: ='Time Axis'!C14 -> Construction | D24: =K23 -> 0 | E24: ='Construction Budget & Draws'!P$190 -> 2835973.7 | F24: =-E24*0.1 -> -283597.37 | G24: =E24+F24 -> 2552376.3 | H24: 2835973.7 | I24: =IF(C24="Construction",(D24)*$B$6/12,0) -> 0 | J24: 0 | N24: =H24+M24-G24 -> 283597.37
A25: 12 | B25: ='Time Axis'!B15 -> 46081 | C25: ='Time Axis'!C15 -> Construction | D25: =K24 -> 0 | E25: ='Construction Budget & Draws'!Q$190 -> 2835973.7 | F25: =-E25*0.1 -> -283597.37 | G25: =E25+F25 -> 2552376.3 | H25: 2835973.7 | I25: =IF(C25="Construction",(D25)*$B$6/12,0) -> 0 | J25: 0 | N25: =H25+M25-G25 -> 283597.37
A26: 13 | B26: ='Time Axis'!B16 -> 46112 | C26: ='Time Axis'!C16 -> Construction | D26: =K25 -> 0 | E26: ='Construction Budget & Draws'!R$190 -> 4923590.7 | F26: =-E26*0.1 -> -492359.07 | G26: =E26+F26 -> 4431231.6 | H26: 4923590.7 | I26: =IF(C26="Construction",(D26)*$B$6/12,0) -> 0 | J26: 0 | N26: =H26+M26-G26 -> 492359.07
A27: 14 | B27: ='Time Axis'!B17 -> 46142 | C27: ='Time Axis'!C17 -> Lease-Up | D27: =K26 -> 0 | E27: ='Construction Budget & Draws'!S$190 -> 0 | F27: =-E27*0.1 -> 0 | G27: =E27+F27 -> 0 | H27: 0 | I27: =IF(C27="Construction",(D27)*$B$6/12,0) -> 0 | J27: 0 | N27: =H27+M27-G27 -> 0
A28: 15 | B28: ='Time Axis'!B18 -> 46173 | C28: ='Time Axis'!C18 -> Stabilized | D28: =K27 -> 0 | E28: ='Construction Budget & Draws'!T$190 -> 0 | F28: =-E28*0.1 -> 0 | G28: =E28+F28 -> 0 | H28: 0 | I28: =IF(C28="Construction",(D28)*$B$6/12,0) -> 0 | J28: 0 | N28: =H28+M28-G28 -> 0
A29: 16 | B29: ='Time Axis'!B19 -> 46203 | C29: ='Time Axis'!C19 -> Stabilized | D29: =K28 -> 0 | E29: ='Construction Budget & Draws'!U$190 -> 0 | F29: =-E29*0.1 -> 0 | G29: =E29+F29 -> 0 | H29: 0 | I29: =IF(C29="Construction",(D29)*$B$6/12,0) -> 0 | J29: 0 | N29: =H29+M29-G29 -> 0
A30: 17 | B30: ='Time Axis'!B20 -> 46234 | C30: ='Time Axis'!C20 -> Stabilized | D30: =K29 -> 0 | E30: ='Construction Budget & Draws'!V$190 -> 0 | F30: =-E30*0.1 -> 0 | G30: =E30+F30 -> 0 | H30: 0 | I30: =IF(C30="Construction",(D30)*$B$6/12,0) -> 0 | J30: 0 | N30: =H30+M30-G30 -> 0
A31: 18 | B31: ='Time Axis'!B21 -> 46265 | C31: ='Time Axis'!C21 -> Stabilized | D31: =K30 -> 0 | E31: ='Construction Budget & Draws'!W$190 -> 0 | F31: =-E31*0.1 -> 0 | G31: =E31+F31 -> 0 | H31: 0 | I31: =IF(C31="Construction",(D31)*$B$6/12,0) -> 0 | J31: 0 | N31: =H31+M31-G31 -> 0
A32: 19 | B32: ='Time Axis'!B22 -> 46295 | C32: ='Time Axis'!C22 -> Stabilized | D32: =K31 -> 0 | E32: ='Construction Budget & Draws'!X$190 -> 0 | F32: =-E32*0.1 -> 0 | G32: =E32+F32 -> 0 | H32: 0 | I32: =IF(C32="Construction",(D32)*$B$6/12,0) -> 0 | J32: 0 | N32: =H32+M32-G32 -> 0
A33: 20 | B33: ='Time Axis'!B23 -> 46326 | C33: ='Time Axis'!C23 -> Stabilized | D33: =K32 -> 0 | E33: ='Construction Budget & Draws'!Y$190 -> 0 | F33: =-E33*0.1 -> 0 | G33: =E33+F33 -> 0 | H33: 0 | I33: =IF(C33="Construction",(D33)*$B$6/12,0) -> 0 | J33: 0 | N33: =H33+M33-G33 -> 0
A34: 21 | B34: ='Time Axis'!B24 -> 46356 | C34: ='Time Axis'!C24 -> Stabilized | D34: =K33 -> 0 | E34: ='Construction Budget & Draws'!Z$190 -> 0 | F34: =-E34*0.1 -> 0 | G34: =E34+F34 -> 0 | H34: 0 | I34: =IF(C34="Construction",(D34)*$B$6/12,0) -> 0 | J34: 0 | N34: =H34+M34-G34 -> 0
A35: 22 | B35: ='Time Axis'!B25 -> 46387 | C35: ='Time Axis'!C25 -> Stabilized | D35: =K34 -> 0 | E35: ='Construction Budget & Draws'!AA$190 -> 0 | F35: =-E35*0.1 -> 0 | G35: =E35+F35 -> 0 | H35: 0 | I35: =IF(C35="Construction",(D35)*$B$6/12,0) -> 0 | J35: 0 | N35: =H35+M35-G35 -> 0
A36: 23 | B36: ='Time Axis'!B26 -> 46418 | C36: ='Time Axis'!C26 -> Stabilized | D36: =K35 -> 0 | E36: ='Construction Budget & Draws'!AB$190 -> 0 | F36: =-E36*0.1 -> 0 | G36: =E36+F36 -> 0 | H36: 0 | I36: =IF(C36="Construction",(D36)*$B$6/12,0) -> 0 | J36: 0 | N36: =H36+M36-G36 -> 0
A37: 24 | B37: ='Time Axis'!B27 -> 46446 | C37: ='Time Axis'!C27 -> Stabilized | D37: =K36 -> 0 | E37: ='Construction Budget & Draws'!AC$190 -> 0 | F37: =-E37*0.1 -> 0 | G37: =E37+F37 -> 0 | H37: 0 | I37: =IF(C37="Construction",(D37)*$B$6/12,0) -> 0 | J37: 0 | N37: =H37+M37-G37 -> 0
A38: 25 | B38: ='Time Axis'!B28 -> 46477 | C38: ='Time Axis'!C28 -> Stabilized | D38: =K37 -> 0 | E38: ='Construction Budget & Draws'!AD$190 -> 0 | F38: =-E38*0.1 -> 0 | G38: =E38+F38 -> 0 | H38: 0 | I38: =IF(C38="Construction",(D38)*$B$6/12,0) -> 0 | J38: 0 | N38: =H38+M38-G38 -> 0
A39: 26 | B39: ='Time Axis'!B29 -> 46507 | C39: ='Time Axis'!C29 -> Stabilized | D39: =K38 -> 0 | E39: ='Construction Budget & Draws'!AE$190 -> 0 | F39: =-E39*0.1 -> 0 | G39: =E39+F39 -> 0 | H39: 0 | I39: =IF(C39="Construction",(D39)*$B$6/12,0) -> 0 | J39: 0 | N39: =H39+M39-G39 -> 0
A40: 27 | B40: ='Time Axis'!B30 -> 46538 | C40: ='Time Axis'!C30 -> Stabilized | D40: =K39 -> 0 | E40: ='Construction Budget & Draws'!AF$190 -> 0 | F40: =-E40*0.1 -> 0 | G40: =E40+F40 -> 0 | H40: 0 | I40: =IF(C40="Construction",(D40)*$B$6/12,0) -> 0 | J40: 0 | N40: =H40+M40-G40 -> 0
A41: 28 | B41: ='Time Axis'!B31 -> 46568 | C41: ='Time Axis'!C31 -> Stabilized | D41: =K40 -> 0 | E41: ='Construction Budget & Draws'!AG$190 -> 0 | F41: =-E41*0.1 -> 0 | G41: =E41+F41 -> 0 | H41: 0 | I41: =IF(C41="Construction",(D41)*$B$6/12,0) -> 0 | J41: 0 | N41: =H41+M41-G41 -> 0
A42: 29 | B42: ='Time Axis'!B32 -> 46599 | C42: ='Time Axis'!C32 -> Stabilized | D42: =K41 -> 0 | E42: ='Construction Budget & Draws'!AH$190 -> 0 | F42: =-E42*0.1 -> 0 | G42: =E42+F42 -> 0 | H42: 0 | I42: =IF(C42="Construction",(D42)*$B$6/12,0) -> 0 | J42: 0 | N42: =H42+M42-G42 -> 0
A43: 30 | B43: ='Time Axis'!B33 -> 46630 | C43: ='Time Axis'!C33 -> Stabilized | D43: =K42 -> 0 | E43: ='Construction Budget & Draws'!AI$190 -> 0 | F43: =-E43*0.1 -> 0 | G43: =E43+F43 -> 0 | H43: 0 | I43: =IF(C43="Construction",(D43)*$B$6/12,0) -> 0 | J43: 0 | N43: =H43+M43-G43 -> 0
A44: 31 | B44: ='Time Axis'!B34 -> 46660 | C44: ='Time Axis'!C34 -> Stabilized | D44: =K43 -> 0 | E44: ='Construction Budget & Draws'!AJ$190 -> 0 | F44: =-E44*0.1 -> 0 | G44: =E44+F44 -> 0 | H44: 0 | I44: =IF(C44="Construction",(D44)*$B$6/12,0) -> 0 | J44: 0 | N44: =H44+M44-G44 -> 0
A45: 32 | B45: ='Time Axis'!B35 -> 46691 | C45: ='Time Axis'!C35 -> Stabilized | D45: =K44 -> 0 | E45: ='Construction Budget & Draws'!AK$190 -> 0 | F45: =-E45*0.1 -> 0 | G45: =E45+F45 -> 0 | H45: 0 | I45: =IF(C45="Construction",(D45)*$B$6/12,0) -> 0 | J45: 0 | N45: =H45+M45-G45 -> 0
A46: 33 | B46: ='Time Axis'!B36 -> 46721 | C46: ='Time Axis'!C36 -> Stabilized | D46: =K45 -> 0 | E46: ='Construction Budget & Draws'!AL$190 -> 0 | F46: =-E46*0.1 -> 0 | G46: =E46+F46 -> 0 | H46: 0 | I46: =IF(C46="Construction",(D46)*$B$6/12,0) -> 0 | J46: 0 | N46: =H46+M46-G46 -> 0
A47: 34 | B47: ='Time Axis'!B37 -> 46752 | C47: ='Time Axis'!C37 -> Stabilized | D47: =K46 -> 0 | E47: ='Construction Budget & Draws'!AM$190 -> 0 | F47: =-E47*0.1 -> 0 | G47: =E47+F47 -> 0 | H47: 0 | I47: =IF(C47="Construction",(D47)*$B$6/12,0) -> 0 | J47: 0 | N47: =H47+M47-G47 -> 0
A48: 35 | B48: ='Time Axis'!B38 -> 46783 | C48: ='Time Axis'!C38 -> Stabilized | D48: =K47 -> 0 | E48: ='Construction Budget & Draws'!AN$190 -> 0 | F48: =-E48*0.1 -> 0 | G48: =E48+F48 -> 0 | H48: 0 | I48: =IF(C48="Construction",(D48)*$B$6/12,0) -> 0 | J48: 0 | N48: =H48+M48-G48 -> 0
A49: 36 | B49: ='Time Axis'!B39 -> 46812 | C49: ='Time Axis'!C39 -> Stabilized | D49: =K48 -> 0 | E49: ='Construction Budget & Draws'!AO$190 -> 0 | F49: =-E49*0.1 -> 0 | G49: =E49+F49 -> 0 | H49: 0 | I49: =IF(C49="Construction",(D49)*$B$6/12,0) -> 0 | J49: 0 | N49: =H49+M49-G49 -> 0
A52: CONSTRUCTION PERIOD SUMMARY | B52: =SUM(E14:E49) -> 43343780
A53: Total Construction Draws: | B53: =SUM(E14:E49) -> 43343780
A54: Total Holdback: | B54: =SUM(F14:F49) -> -4334378
A55: Total Senior Loan Advanced: | B55: =SUM(H14:H49) -> 33506438
A56: Total Capitalized Interest: | B56: =L49 -> 0
A57: Total Class E Equity Called: | B57: ='i_Cap Table'!E34 -> 2800015
A58: Senior Loan Balance at Refi: | B58: =K49 -> 0

Sheet Draw Calc (Hidden)
A1: DETAILED PHASING CALCULATION
A2: Row alignment matches Budget Input Data exactly
A4: Category | B4: Subcategory | C4: Mo 1 | D4: Mo 2 | E4: Mo 3 | F4: Mo 4 | G4: Mo 5 | H4: Mo 6 | I4: Mo 7 | J4: Mo 8 | K4: Mo 9 | L4: Mo 10 | M4: Mo 11 | N4: Mo 12 | O4: Mo 13 | P4: Mo 14 | Q4: Mo 15 | R4: Mo 16 | S4: Mo 17 | T4: Mo 18 | U4: Mo 19 | V4: Mo 20 | W4: Mo 21 | X4: Mo 22 | Y4: Mo 23 | Z4: Mo 24 | AA4: Mo 25 | AB4: Mo 26 | AC4: Mo 27 | AD4: Mo 28 | AE4: Mo 29 | AF4: Mo 30 | AG4: Mo 31 | AH4: Mo 32 | AI4: Mo 33 | AJ4: Mo 34 | AK4: Mo 35 | AL4: Mo 36
C5: 0 | D5: 0 | E5: 0 | F5: 0 | G5: 0 | H5: 0 | I5: 0 | J5: 0 | K5: 0 | L5: 0 | M5: 0 | N5: 0 | O5: 0 | P5: 0 | Q5: 0 | R5: 0 | S5: 0 | T5: 0 | U5: 0 | V5: 0 | W5: 0 | X5: 0 | Y5: 0 | Z5: 0 | AA5: 0 | AB5: 0 | AC5: 0 | AD5: 0 | AE5: 0 | AF5: 0 | AG5: 0 | AH5: 0 | AI5: 0 | AJ5: 0 | AK5: 0 | AL5: 0
A6: 1. LAND | B6: Land Acquisition | C6: =IF(1<='I_Inputs & Assumptions'!$B$8,IF('I_Budget Input Data'!$E$6="Upfront",IF(1=1,'I_Budget Input Data'!$D$6,0),IF('I_Budget Input Data'!$E$6="Equal",'I_Budget Input Data'!$D$6/'I_Inputs & Assumptions'!$B$8,IF('I_Budget Input Data'!$E$6="Front-loaded",IF(1<='I_Inputs & Assumptions'!$B$8/2,'I_Budget Input Data'!$D$6*0.6/('I_Inputs & Assumptions'!$B$8/2),'I_Budget Input Data'!$D$6*0.4/('I_Inputs & Assumptions'!$B$8/2)),IF('I_Budget Input Data'!$E$6="Back-loaded",IF(1<='I_Inputs & Assumptions'!$B$8/2,'I_Budget Input Data'!$D$6*0.4/('I_Inputs & Assumptions'!$B$8/2),'I_Budget Input Data'!$D$6*0.6/('I_Inputs & Assumptions'!$B$8/2)),IF('I_Budget Input Data'!$E$6="Mid-weighted",IF(1<='I_Inputs & Assumptions'!$B$8/4,'I_Budget Input Data'!$D$6*0.2/('I_Inputs & Assumptions'!$B$8/4),IF(1<='I_Inputs & Assumptions'!$B$8*0.75,'I_Budget Input Data'!$D$6*0.6/('I_Inputs & Assumptions'!$B$8/2),'I_Budget Input Data'!$D$6*0.2/('I_Inputs & Assumptions'!$B$8/4))),IF('I_Budget Input Data'!$E$6="At Completion",IF(1='I_Inputs & Assumptions'!$B$8,'I_Budget Input Data'!$D$6,0),'I_Budget Input Data'!$D$6/'I_Inputs & Assumptions'!$B$8)))))),0) -> 1600000 | D6: =IF(2<='I_Inputs & Assumptions'!$B$8,IF('I_Budget Input Data'!$E$6="Upfront",IF(2=1,'I_Budget Input Data'!$D$6,0),IF('I_Budget Input Data'!$E$6="Equal",'I_Budget Input Data'!$D$6/'I_Inputs & Assumptions'!$B$8,IF('I_Budget Input Data'!$E$6="Front-loaded",IF(2<='I_Inputs & Assumptions'!$B$8/2,'I_Budget Input Data'!$D$6*0.6/('I_Inputs & Assumptions'!$B$8/2),'I_Budget Input Data'!$D$6*0.4/('I_Inputs & Assumptions'!$B$8/2)),IF('I_Budget Input Data'!$E$6="Back-loaded",IF(2<='I_Inputs & Assumptions'!$B$8/2,'I_Budget Input Data'!$D$6*0.4/('I_Inputs & Assumptions'!$B$8/2),'I_Budget Input Data'!$D$6*0.6/('I_Inputs & Assumptions'!$B$8/2)),IF('I_Budget Input Data'!$E$6="Mid-weighted",IF(2<='I_Inputs & Assumptions'!$B$8/4,'I_Budget Input Data'!$D$6*0.2/('I_Inputs & Assumptions'!$B$8/4),IF(2<='I_Inputs & Assumptions'!$B$8*0.75,'I_Budget Input Data'!$D$6*0.6/('I_Inputs & Assumptions'!$B$8/2),'I_Budget Input Data'!$D$6*0.2/('I_Inputs & Assumptions'!$B$8/4))),IF('I_Budget Input Data'!$E$6="At Completion",IF(2='I_Inputs & Assumptions'!$B$8,'I_Budget Input Data'!$D$6,0),'I_Budget Input Data'!$D$6/'I_Inputs & Assumptions'!$B$8)))))),0) -> 0 | E6: =IF(3<='I_Inputs & Assumptions'!$B$8,IF('I_Budget Input Data'!$E$6="Upfront",IF(3=1,'I_Budget Input Data'!$D$6,0),IF('I_Budget Input Data'!$E$6="Equal",'I_Budget Input Data'!$D$6/'I_Inputs & Assumptions'!$B$8,IF('I_Budget Input Data'!$E$6="Front-loaded",IF(3<='I_Inputs & Assumptions'!$B$8/2,'I_Budget Input Data'!$D$6*0.6/('I_Inputs & Assumptions'!$B$8/2),'I_Budget Input Data'!$D$6*0.4/('I_Inputs & Assumptions'!$B$8/2)),IF('I_Budget Input Data'!$E$6="Back-loaded",IF(3<='I_Inputs & Assumptions'!$B$8/2,'I_Budget Input Data'!$D$6*0.4/('I_Inputs & Assumptions'!$B$8/2),'I_Budget Input Data'!$D$6*0.6/('I_Inputs & Assumptions'!$B$8/2)),IF('I_Budget Input Data'!$E$6="Mid-weighted",IF(3<='I_Inputs & Assumptions'!$B$8/4,'I_Budget Input Data'!$D$6*0.2/('I_Inputs & Assumptions'!$B$8/4),IF(3<='I_Inputs & Assumptions'!$B$8*0.75,'I_Budget Input Data'!$D$6*0.6/('I_Inputs & Assumptions'!$B$8/2),'I_Budget Input Data'!$D$6*0.2/('I_Inputs & Assumptions'!$B$8/4))),IF('I_Budget Input Data'!$E$6="At Completion",IF(3='I_Inputs & Assumptions'!$B$8,'I_Budget Input Data'!$D$6,0),'I_Budget Input Data'!$D$6/'I_Inputs & Assumptions'!$B$8)))))),0) -> 0 | F6: =IF(4<='I_Inputs & Assumptions'!$B$8,IF('I_Budget Input Data'!$E$6="Upfront",IF(4=1,'I_Budget Input Data'!$D$6,0),IF('I_Budget Input Data'!$E$6="Equal",'I_Budget Input Data'!$D$6/'I_Inputs & Assumptions'!$B$8,IF('I_Budget Input Data'!$E$6="Front-loaded",IF(4<='I_Inputs & Assumptions'!$B$8/2,'I_Budget Input Data'!$D$6*0.6/('I_Inputs & Assumptions'!$B$8/2),'I_Budget Input Data'!$D$6*0.4/('I_Inputs & Assumptions'!$B$8/2)),IF('I_Budget Input Data'!$E$6="Back-loaded",IF(4<='I_Inputs & Assumptions'!$B$8/2,'I_Budget Input Data'!$D$6*0.4/('I_Inputs & Assumptions'!$B$8/2),'I_Budget Input Data'!$D$6*0.6/('I_Inputs & Assumptions'!$B$8/2)),IF('I_Budget Input Data'!$E$6="Mid-weighted",IF(4<='I_Inputs & Assumptions'!$B$8/4,'I_Budget Input Data'!$D$6*0.2/('I_Inputs & Assumptions'!$B$8/4),IF(4<='I_Inputs & Assumptions'!$B$8*0.75,'I_Budget Input Data'!$D$6*0.6/('I_Inputs & Assumptions'!$B$8/2),'I_Budget Input Data'!$D$6*0.2/('I_Inputs & Assumptions'!$B$8/4))),IF('I_Budget Input Data'!$E$6="At Completion",IF(4='I_Inputs & Assumptions'!$B$8,'I_Budget Input Data'!$D$6,0),'I_Budget Input Data'!$D$6/'I_Inputs & Assumptions'!$B$8)))))),0) -> 0 | G6: =IF(5<='I_Inputs & Assumptions'!$B$8,IF('I_Budget Input Data'!$E$6="Upfront",IF(5=1,'I_Budget Input Data'!$D$6,0),IF('I_Budget Input Data'!$E$6="Equal",'I_Budget Input Data'!$D$6/'I_Inputs & Assumptions'!$B$8,IF('I_Budget Input Data'!$E$6="Front-loaded",IF(5<='I_Inputs & Assumptions'!$B$8/2,'I_Budget Input Data'!$D$6*0.6/('I_Inputs & Assumptions'!$B$8/2),'I_Budget Input Data'!$D$6*0.4/('I_Inputs & Assumptions'!$B$8/2)),IF('I_Budget Input Data'!$E$6="Back-loaded",IF(5<='I_Inputs & Assumptions'!$B$8/2,'I_Budget Input Data'!$D$6*0.4/('I_Inputs & Assumptions'!$B$8/2),'I_Budget Input Data'!$D$6*0.6/('I_Inputs & Assumptions'!$B$8/2)),IF('I_Budget Input Data'!$E$6="Mid-weighted",IF(5<='I_Inputs & Assumptions'!$B$8/4,'I_Budget Input Data'!$D$6*0.2/('I_Inputs & Assumptions'!$B$8/4),IF(5<='I_Inputs & Assumptions'!$B$8*0.75,'I_Budget Input Data'!$D$6*0.6/('I_Inputs & Assumptions'!$B$8/2),'I_Budget Input Data'!$D$6*0.2/('I_Inputs & Assumptions'!$B$8/4))),IF('I_Budget Input Data'!$E$6="At Completion",IF(5='I_Inputs & Assumptions'!$B$8,'I_Budget Input Data'!$D$6,0),'I_Budget Input Data'!$D$6/'I_Inputs & Assumptions'!$B$8)))))),0) -> 0 | H6: =IF(6<='I_Inputs & Assumptions'!$B$8,IF('I_Budget Input Data'!$E$6="Upfront",IF(6=1,'I_Budget Input Data'!$D$6,0),IF('I_Budget Input Data'!$E$6="Equal",'I_Budget Input Data'!$D$6/'I_Inputs & Assumptions'!$B$8,IF('I_Budget Input Data'!$E$6="Front-loaded",IF(6<='I_Inputs & Assumptions'!$B$8/2,'I_Budget Input Data'!$D$6*0.6/('I_Inputs & Assumptions'!$B$8/2),'I_Budget Input Data'!$D$6*0.4/('I_Inputs & Assumptions'!$B$8/2)),IF('I_Budget Input Data'!$E$6="Back-loaded",IF(6<='I_Inputs & Assumptions'!$B$8/2,'I_Budget Input Data'!$D$6*0.4/('I_Inputs & Assumptions'!$B$8/2),'I_Budget Input Data'!$D$6*0.6/('I_Inputs & Assumptions'!$B$8/2)),IF('I_Budget Input Data'!$E$6="Mid-weighted",IF(6<='I_Inputs & Assumptions'!$B$8/4,'I_Budget Input Data'!$D$6*0.2/('I_Inputs & Assumptions'!$B$8/4),IF(6<='I_Inputs & Assumptions'!$B$8*0.75,'I_Budget Input Data'!$D$6*0.6/('I_Inputs & Assumptions'!$B$8/2),'I_Budget Input Data'!$D$6*0.2/('I_Inputs & Assumptions'!$B$8/4))),IF('I_Budget Input Data'!$E$6="At Completion",IF(6='I_Inputs & Assumptions'!$B$8,'I_Budget Input Data'!$D$6,0),'I_Budget Input Data'!$D$6/'I_Inputs & Assumptions'!$B$8)))))),0) -> 0 | I6: =IF(7<='I_Inputs & Assumptions'!$B$8,IF('I_Budget Input Data'!$E$6="Upfront",IF(7=1,'I_Budget Input Data'!$D$6,0),IF('I_Budget Input Data'!$E$6="Equal",'I_Budget Input Data'!$D$6/'I_Inputs & Assumptions'!$B$8,IF('I_Budget Input Data'!$E$6="Front-loaded",IF(7<='I_Inputs & Assumptions'!$B$8/2,'I_Budget Input Data'!$D$6*0.6/('I_Inputs & Assumptions'!$B$8/2),'I_Budget Input Data'!$D$6*0.4/('I_Inputs & Assumptions'!$B$8/2)),IF('I_Budget Input Data'!$E$6="Back-loaded",IF(7<='I_Inputs & Assumptions'!$B$8/2,'I_Budget Input Data'!$D$6*0.4/('I_Inputs & Assumptions'!$B$8/2),'I_Budget Input Data'!$D$6*0.6/('I_Inputs & Assumptions'!$B$8/2)),IF('I_Budget Input Data'!$E$6="Mid-weighted",IF(7<='I_Inputs & Assumptions'!$B$8/4,'I_Budget Input Data'!$D$6*0.2/('I_Inputs & Assumptions'!$B$8/4),IF(7<='I_Inputs & Assumptions'!$B$8*0.75,'I_Budget Input Data'!$D$6*0.6/('I_Inputs & Assumptions'!$B$8/2),'I_Budget Input Data'!$D$6*0.2/('I_Inputs & Assumptions'!$B$8/4))),IF('I_Budget Input Data'!$E$6="At Completion",IF(7='I_Inputs & Assumptions'!$B$8,'I_Budget Input Data'!$D$6,0),'I_Budget Input Data'!$D$6/'I_Inputs & Assumptions'!$B$8)))))),0) -> 0 | J6: =IF(8<='I_Inputs & Assumptions'!$B$8,IF('I_Budget Input Data'!$E$6="Upfront",IF(8=1,'I_Budget Input Data'!$D$6,0),IF('I_Budget Input Data'!$E$6="Equal",'I_Budget Input Data'!$D$6/'I_Inputs & Assumptions'!$B$8,IF('I_Budget Input Data'!$E$6="Front-loaded",IF(8<='I_Inputs & Assumptions'!$B$8/2,'I_Budget Input Data'!$D$6*0.6/('I_Inputs & Assumptions'!$B$8/2),'I_Budget Input Data'!$D$6*0.4/('I_Inputs & Assumptions'!$B$8/2)),IF('I_Budget Input Data'!$E$6="Back-loaded",IF(8<='I_Inputs & Assumptions'!$B$8/2,'I_Budget Input Data'!$D$6*0.4/('I_Inputs & Assumptions'!$B$8/2),'I_Budget Input Data'!$D$6*0.6/('I_Inputs & Assumptions'!$B$8/2)),IF('I_Budget Input Data'!$E$6="Mid-weighted",IF(8<='I_Inputs & Assumptions'!$B$8/4,'I_Budget Input Data'!$D$6*0.2/('I_Inputs & Assumptions'!$B$8/4),IF(8<='I_Inputs & Assumptions'!$B$8*0.75,'I_Budget Input Data'!$D$6*0.6/('I_Inputs & Assumptions'!$B$8/2),'I_Budget Input Data'!$D$6*0.2/('I_Inputs & Assumptions'!$B$8/4))),IF('I_Budget Input Data'!$E$6="At Completion",IF(8='I_Inputs & Assumptions'!$B$8,'I_Budget Input Data'!$D$6,0),'I_Budget Input Data'!$D$6/'I_Inputs & Assumptions'!$B$8)))))),0) -> 0 | K6: =IF(9<='I_Inputs & Assumptions'!$B$8,IF('I_Budget Input Data'!$E$6="Upfront",IF(9=1,'I_Budget Input Data'!$D$6,0),IF('I_Budget Input Data'!$E$6="Equal",'I_Budget Input Data'!$D$6/'I_Inputs & Assumptions'!$B$8,IF('I_Budget Input Data'!$E$6="Front-loaded",IF(9<='I_Inputs & Assumptions'!$B$8/2,'I_Budget Input Data'!$D$6*0.6/('I_Inputs & Assumptions'!$B$8/2),'I_Budget Input Data'!$D$6*0.4/('I_Inputs & Assumptions'!$B$8/2)),IF('I_Budget Input Data'!$E$6="Back-loaded",IF(9<='I_Inputs & Assumptions'!$B$8/2,'I_Budget Input Data'!$D$6*0.4/('I_Inputs & Assumptions'!$B$8/2),'I_Budget Input Data'!$D$6*0.6/('I_Inputs & Assumptions'!$B$8/2)),IF('I_Budget Input Data'!$E$6="Mid-weighted",IF(9<='I_Inputs & Assumptions'!$B$8/4,'I_Budget Input Data'!$D$6*0.2/('I_Inputs & Assumptions'!$B$8/4),IF(9<='I_Inputs & Assumptions'!$B$8*0.75,'I_Budget Input Data'!$D$6*0.6/('I_Inputs & Assumptions'!$B$8/2),'I_Budget Input Data'!$D$6*0.2/('I_Inputs & Assumptions'!$B$8/4))),IF('I_Budget Input Data'!$E$6="At Completion",IF(9='I_Inputs & Assumptions'!$B$8,'I_Budget Input Data'!$D$6,0),'I_Budget Input Data'!$D$6/'I_Inputs & Assumptions'!$B$8)))))),0) -> 0 | L6: =IF(10<='I_Inputs & Assumptions'!$B$8,IF('I_Budget Input Data'!$E$6="Upfront",IF(10=1,'I_Budget Input Data'!$D$6,0),IF('I_Budget Input Data'!$E$6="Equal",'I_Budget Input Data'!$D$6/'I_Inputs & Assumptions'!$B$8,IF('I_Budget Input Data'!$E$6="Front-loaded",IF(10<='I_Inputs & Assumptions'!$B$8/2,'I_Budget Input Data'!$D$6*0.6/('I_Inputs & Assumptions'!$B$8/2),'I_Budget Input Data'!$D$6*0.4/('I_Inputs & Assumptions'!$B$8/2)),IF('I_Budget Input Data'!$E$6="Back-loaded",IF(10<='I_Inputs & Assumptions'!$B$8/2,'I_Budget Input Data'!$D$6*0.4/('I_Inputs & Assumptions'!$B$8/2),'I_Budget Input Data'!$D$6*0.6/('I_Inputs & Assumptions'!$B$8/2)),IF('I_Budget Input Data'!$E$6="Mid-weighted",IF(10<='I_Inputs & Assumptions'!$B$8/4,'I_Budget Input Data'!$D$6*0.2/('I_Inputs & Assumptions'!$B$8/4),IF(10<='I_Inputs & Assumptions'!$B$8*0.75,'I_Budget Input Data'!$D$6*0.6/('I_Inputs & Assumptions'!$B$8/2),'I_Budget Input Data'!$D$6*0.2/('I_Inputs & Assumptions'!$B$8/4))),IF('I_Budget Input Data'!$E$6="At Completion",IF(10='I_Inputs & Assumptions'!$B$8,'I_Budget Input Data'!$D$6,0),'I_Budget Input Data'!$D$6/'I_Inputs & Assumptions'!$B$8)))))),0) -> 0 | M6: =IF(11<='I_Inputs & Assumptions'!$B$8,IF('I_Budget Input Data'!$E$6="Upfront",IF(11=1,'I_Budget Input Data'!$D$6,0),IF('I_Budget Input Data'!$E$6="Equal",'I_Budget Input Data'!$D$6/'I_Inputs & Assumptions'!$B$8,IF('I_Budget Input Data'!$E$6="Front-loaded",IF(11<='I_Inputs & Assumptions'!$B$8/2,'I_Budget Input Data'!$D$6*0.6/('I_Inputs & Assumptions'!$B$8/2),'I_Budget Input Data'!$D$6*0.4/('I_Inputs & Assumptions'!$B$8/2)),IF('I_Budget Input Data'!$E$6="Back-loaded",IF(11<='I_Inputs & Assumptions'!$B$8/2,'I_Budget Input Data'!$D$6*0.4/('I_Inputs & Assumptions'!$B$8/2),'I_Budget Input Data'!$D$6*0.6/('I_Inputs & Assumptions'!$B$8/2)),IF('I_Budget Input Data'!$E$6="Mid-weighted",IF(11<='I_Inputs & Assumptions'!$B$8/4,'I_Budget Input Data'!$D$6*0.2/('I_Inputs & Assumptions'!$B$8/4),IF(11<='I_Inputs & Assumptions'!$B$8*0.75,'I_Budget Input Data'!$D$6*0.6/('I_Inputs & Assumptions'!$B$8/2),'I_Budget Input Data'!$D$6*0.2/('I_Inputs & Assumptions'!$B$8/4))),IF('I_Budget Input Data'!$E$6="At Completion",IF(11='I_Inputs & Assumptions'!$B$8,'I_Budget Input Data'!$D$6,0),'I_Budget Input Data'!$D$6/'I_Inputs & Assumptions'!$B$8)))))),0) -> 0 | N6: =IF(12<='I_Inputs & Assumptions'!$B$8,IF('I_Budget Input Data'!$E$6="Upfront",IF(12=1,'I_Budget Input Data'!$D$6,0),IF('I_Budget Input Data'!$E$6="Equal",'I_Budget Input Data'!$D$6/'I_Inputs & Assumptions'!$B$8,IF('I_Budget Input Data'!$E$6="Front-loaded",IF(12<='I_Inputs & Assumptions'!$B$8/2,'I_Budget Input Data'!$D$6*0.6/('I_Inputs & Assumptions'!$B$8/2),'I_Budget Input Data'!$D$6*0.4/('I_Inputs & Assumptions'!$B$8/2)),IF('I_Budget Input Data'!$E$6="Back-loaded",IF(12<='I_Inputs & Assumptions'!$B$8/2,'I_Budget Input Data'!$D$6*0.4/('I_Inputs & Assumptions'!$B$8/2),'I_Budget Input Data'!$D$6*0.6/('I_Inputs & Assumptions'!$B$8/2)),IF('I_Budget Input Data'!$E$6="Mid-weighted",IF(12<='I_Inputs & Assumptions'!$B$8/4,'I_Budget Input Data'!$D$6*0.2/('I_Inputs & Assumptions'!$B$8/4),IF(12<='I_Inputs & Assumptions'!$B$8*0.75,'I_Budget Input Data'!$D$6*0.6/('I_Inputs & Assumptions'!$B$8/2),'I_Budget Input Data'!$D$6*0.2/('I_Inputs & Assumptions'!$B$8/4))),IF('I_Budget Input Data'!$E$6="At Completion",IF(12='I_Inputs & Assumptions'!$B$8,'I_Budget Input Data'!$D$6,0),'I_Budget Input Data'!$D$6/'I_Inputs & Assumptions'!$B$8)))))),0) -> 0 | O6: =IF(13<='I_Inputs & Assumptions'!$B$8,IF('I_Budget Input Data'!$E$6="Upfront",IF(13=1,'I_Budget Input Data'!$D$6,0),IF('I_Budget Input Data'!$E$6="Equal",'I_Budget Input Data'!$D$6/'I_Inputs & Assumptions'!$B$8,IF('I_Budget Input Data'!$E$6="Front-loaded",IF(13<='I_Inputs & Assumptions'!$B$8/2,'I_Budget Input Data'!$D$6*0.6/('I_Inputs & Assumptions'!$B$8/2),'I_Budget Input Data'!$D$6*0.4/('I_Inputs & Assumptions'!$B$8/2)),IF('I_Budget Input Data'!$E$6="Back-loaded",IF(13<='I_Inputs & Assumptions'!$B$8/2,'I_Budget Input Data'!$D$6*0.4/('I_Inputs & Assumptions'!$B$8/2),'I_Budget Input Data'!$D$6*0.6/('I_Inputs & Assumptions'!$B$8/2)),IF('I_Budget Input Data'!$E$6="Mid-weighted",IF(13<='I_Inputs & Assumptions'!$B$8/4,'I_Budget Input Data'!$D$6*0.2/('I_Inputs & Assumptions'!$B$8/4),IF(13<='I_Inputs & Assumptions'!$B$8*0.75,'I_Budget Input Data'!$D$6*0.6/('I_Inputs & Assumptions'!$B$8/2),'I_Budget Input Data'!$D$6*0.2/('I_Inputs & Assumptions'!$B$8/4))),IF('I_Budget Input Data'!$E$6="At Completion",IF(13='I_Inputs & Assumptions'!$B$8,'I_Budget Input Data'!$D$6,0),'I_Budget Input Data'!$D$6/'I_Inputs & Assumptions'!$B$8)))))),0) -> 0 | P6: =IF(14<='I_Inputs & Assumptions'!$B$8,IF('I_Budget Input Data'!$E$6="Upfront",IF(14=1,'I_Budget Input Data'!$D$6,0),IF('I_Budget Input Data'!$E$6="Equal",'I_Budget Input Data'!$D$6/'I_Inputs & Assumptions'!$B$8,IF('I_Budget Input Data'!$E$6="Front-loaded",IF(14<='I_Inputs & Assumptions'!$B$8/2,'I_Budget Input Data'!$D$6*0.6/('I_Inputs & Assumptions'!$B$8/2),'I_Budget Input Data'!$D$6*0.4/('I_Inputs & Assumptions'!$B$8/2)),IF('I_Budget Input Data'!$E$6="Back-loaded",IF(14<='I_Inputs & Assumptions'!$B$8/2,'I_Budget Input Data'!$D$6*0.4/('I_Inputs & Assumptions'!$B$8/2),'I_Budget Input Data'!$D$6*0.6/('I_Inputs & Assumptions'!$B$8/2)),IF('I_Budget Input Data'!$E$6="Mid-weighted",IF(14<='I_Inputs & Assumptions'!$B$8/4,'I_Budget Input Data'!$D$6*0.2/('I_Inputs & Assumptions'!$B$8/4),IF(14<='I_Inputs & Assumptions'!$B$8*0.75,'I_Budget Input Data'!$D$6*0.6/('I_Inputs & Assumptions'!$B$8/2),'I_Budget Input Data'!$D$6*0.2/('I_Inputs & Assumptions'!$B$8/4))),IF('I_Budget Input Data'!$E$6="At Completion",IF(14='I_Inputs & Assumptions'!$B$8,'I_Budget Input Data'!$D$6,0),'I_Budget Input Data'!$D$6/'I_Inputs & Assumptions'!$B$8)))))),0) -> 0 | Q6: =IF(15<='I_Inputs & Assumptions'!$B$8,IF('I_Budget Input Data'!$E$6="Upfront",IF(15=1,'I_Budget Input Data'!$D$6,0),IF('I_Budget Input Data'!$E$6="Equal",'I_Budget Input Data'!$D$6/'I_Inputs & Assumptions'!$B$8,IF('I_Budget Input Data'!$E$6="Front-loaded",IF(15<='I_Inputs & Assumptions'!$B$8/2,'I_Budget Input Data'!$D$6*0.6/('I_Inputs & Assumptions'!$B$8/2),'I_Budget Input Data'!$D$6*0.4/('I_Inputs & Assumptions'!$B$8/2)),IF('I_Budget Input Data'!$E$6="Back-loaded",IF(15<='I_Inputs & Assumptions'!$B$8/2,'I_Budget Input Data'!$D$6*0.4/('I_Inputs & Assumptions'!$B$8/2),'I_Budget Input Data'!$D$6*0.6/('I_Inputs & Assumptions'!$B$8/2)),IF('I_Budget Input Data'!$E$6="Mid-weighted",IF(15<='I_Inputs & Assumptions'!$B$8/4,'I_Budget Input Data'!$D$6*0.2/('I_Inputs & Assumptions'!$B$8/4),IF(15<='I_Inputs & Assumptions'!$B$8*0.75,'I_Budget Input Data'!$D$6*0.6/('I_Inputs & Assumptions'!$B$8/2),'I_Budget Input Data'!$D$6*0.2/('I_Inputs & Assumptions'!$B$8/4))),IF('I_Budget Input Data'!$E$6="At Completion",IF(15='I_Inputs & Assumptions'!$B$8,'I_Budget Input Data'!$D$6,0),'I_Budget Input Data'!$D$6/'I_Inputs & Assumptions'!$B$8)))))),0) -> 0 | R6: =IF(16<='I_Inputs & Assumptions'!$B$8,IF('I_Budget Input Data'!$E$6="Upfront",IF(16=1,'I_Budget Input Data'!$D$6,0),IF('I_Budget Input Data'!$E$6="Equal",'I_Budget Input Data'!$D$6/'I_Inputs & Assumptions'!$B$8,IF('I_Budget Input Data'!$E$6="Front-loaded",IF(16<='I_Inputs & Assumptions'!$B$8/2,'I_Budget Input Data'!$D$6*0.6/('I_Inputs & Assumptions'!$B$8/2),'I_Budget Input Data'!$D$6*0.4/('I_Inputs & Assumptions'!$B$8/2)),IF('I_Budget Input Data'!$E$6="Back-loaded",IF(16<='I_Inputs & Assumptions'!$B$8/2,'I_Budget Input Data'!$D$6*0.4/('I_Inputs & Assumptions'!$B$8/2),'I_Budget Input Data'!$D$6*0.6/('I_Inputs & Assumptions'!$B$8/2)),IF('I_Budget Input Data'!$E$6="Mid-weighted",IF(16<='I_Inputs & Assumptions'!$B$8/4,'I_Budget Input Data'!$D$6*0.2/('I_Inputs & Assumptions'!$B$8/4),IF(16<='I_Inputs & Assumptions'!$B$8*0.75,'I_Budget Input Data'!$D$6*0.6/('I_Inputs & Assumptions'!$B$8/2),'I_Budget Input Data'!$D$6*0.2/('I_Inputs & Assumptions'!$B$8/4))),IF('I_Budget Input Data'!$E$6="At Completion",IF(16='I_Inputs & Assumptions'!$B$8,'I_Budget Input Data'!$D$6,0),'I_Budget Input Data'!$D$6/'I_Inputs & Assumptions'!$B$8)))))),0) -> 0 | S6: =IF(17<='I_Inputs & Assumptions'!$B$8,IF('I_Budget Input Data'!$E$6="Upfront",IF(17=1,'I_Budget Input Data'!$D$6,0),IF('I_Budget Input Data'!$E$6="Equal",'I_Budget Input Data'!$D$6/'I_Inputs & Assumptions'!$B$8,IF('I_Budget Input Data'!$E$6="Front-loaded",IF(17<='I_Inputs & Assumptions'!$B$8/2,'I_Budget Input Data'!$D$6*0.6/('I_Inputs & Assumptions'!$B$8/2),'I_Budget Input Data'!$D$6*0.4/('I_Inputs & Assumptions'!$B$8/2)),IF('I_Budget Input Data'!$E$6="Back-loaded",IF(17<='I_Inputs & Assumptions'!$B$8/2,'I_Budget Input Data'!$D$6*0.4/('I_Inputs & Assumptions'!$B$8/2),'I_Budget Input Data'!$D$6*0.6/('I_Inputs & Assumptions'!$B$8/2)),IF('I_Budget Input Data'!$E$6="Mid-weighted",IF(17<='I_Inputs & Assumptions'!$B$8/4,'I_Budget Input Data'!$D$6*0.2/('I_Inputs & Assumptions'!$B$8/4),IF(17<='I_Inputs & Assumptions'!$B$8*0.75,'I_Budget Input Data'!$D$6*0.6/('I_Inputs & Assumptions'!$B$8/2),'I_Budget Input Data'!$D$6*0.2/('I_Inputs & Assumptions'!$B$8/4))),IF('I_Budget Input Data'!$E$6="At Completion",IF(17='I_Inputs & Assumptions'!$B$8,'I_Budget Input Data'!$D$6,0),'I_Budget Input Data'!$D$6/'I_Inputs & Assumptions'!$B$8)))))),0) -> 0 | T6: =IF(18<='I_Inputs & Assumptions'!$B$8,IF('I_Budget Input Data'!$E$6="Upfront",IF(18=1,'I_Budget Input Data'!$D$6,0),IF('I_Budget Input Data'!$E$6="Equal",'I_Budget Input Data'!$D$6/'I_Inputs & Assumptions'!$B$8,IF('I_Budget Input Data'!$E$6="Front-loaded",IF(18<='I_Inputs & Assumptions'!$B$8/2,'I_Budget Input Data'!$D$6*0.6/('I_Inputs & Assumptions'!$B$8/2),'I_Budget Input Data'!$D$6*0.4/('I_Inputs & Assumptions'!$B$8/2)),IF('I_Budget Input Data'!$E$6="Back-loaded",IF(18<='I_Inputs & Assumptions'!$B$8/2,'I_Budget Input Data'!$D$6*0.4/('I_Inputs & Assumptions'!$B$8/2),'I_Budget Input Data'!$D$6*0.6/('I_Inputs & Assumptions'!$B$8/2)),IF('I_Budget Input Data'!$E$6="Mid-weighted",IF(18<='I_Inputs & Assumptions'!$B$8/4,'I_Budget Input Data'!$D$6*0.2/('I_Inputs & Assumptions'!$B$8/4),IF(18<='I_Inputs & Assumptions'!$B$8*0.75,'I_Budget Input Data'!$D$6*0.6/('I_Inputs & Assumptions'!$B$8/2),'I_Budget Input Data'!$D$6*0.2/('I_Inputs & Assumptions'!$B$8/4))),IF('I_Budget Input Data'!$E$6="At Completion",IF(18='I_Inputs & Assumptions'!$B$8,'I_Budget Input Data'!$D$6,0),'I_Budget Input Data'!$D$6/'I_Inputs & Assumptions'!$B$8)))))),0) -> 0 | U6: =IF(19<='I_Inputs & Assumptions'!$B$8,IF('I_Budget Input Data'!$E$6="Upfront",IF(19=1,'I_Budget Input Data'!$D$6,0),IF('I_Budget Input Data'!$E$6="Equal",'I_Budget Input Data'!$D$6/'I_Inputs & Assumptions'!$B$8,IF('I_Budget Input Data'!$E$6="Front-loaded",IF(19<='I_Inputs & Assumptions'!$B$8/2,'I_Budget Input Data'!$D$6*0.6/('I_Inputs & Assumptions'!$B$8/2),'I_Budget Input Data'!$D$6*0.4/('I_Inputs & Assumptions'!$B$8/2)),IF('I_Budget Input Data'!$E$6="Back-loaded",IF(19<='I_Inputs & Assumptions'!$B$8/2,'I_Budget Input Data'!$D$6*0.4/('I_Inputs & Assumptions'!$B$8/2),'I_Budget Input Data'!$D$6*0.6/('I_Inputs & Assumptions'!$B$8/2)),IF('I_Budget Input Data'!$E$6="Mid-weighted",IF(19<='I_Inputs & Assumptions'!$B$8/4,'I_Budget Input Data'!$D$6*0.2/('I_Inputs & Assumptions'!$B$8/4),IF(19<='I_Inputs & Assumptions'!$B$8*0.75,'I_Budget Input Data'!$D$6*0.6/('I_Inputs & Assumptions'!$B$8/2),'I_Budget Input Data'!$D$6*0.2/('I_Inputs & Assumptions'!$B$8/4))),IF('I_Budget Input Data'!$E$6="At Completion",IF(19='I_Inputs & Assumptions'!$B$8,'I_Budget Input Data'!$D$6,0),'I_Budget Input Data'!$D$6/'I_Inputs & Assumptions'!$B$8)))))),0) -> 0 | V6: =IF(20<='I_Inputs & Assumptions'!$B$8,IF('I_Budget Input Data'!$E$6="Upfront",IF(20=1,'I_Budget Input Data'!$D$6,0),IF('I_Budget Input Data'!$E$6="Equal",'I_Budget Input Data'!$D$6/'I_Inputs & Assumptions'!$B$8,IF('I_Budget Input Data'!$E$6="Front-loaded",IF(20<='I_Inputs & Assumptions'!$B$8/2,'I_Budget Input Data'!$D$6*0.6/('I_Inputs & Assumptions'!$B$8/2),'I_Budget Input Data'!$D$6*0.4/('I_Inputs & Assumptions'!$B$8/2)),IF('I_Budget Input Data'!$E$6="Back-loaded",IF(20<='I_Inputs & Assumptions'!$B$8/2,'I_Budget Input Data'!$D$6*0.4/('I_Inputs & Assumptions'!$B$8/2),'I_Budget Input Data'!$D$6*0.6/('I_Inputs & Assumptions'!$B$8/2)),IF('I_Budget Input Data'!$E$6="Mid-weighted",IF(20<='I_Inputs & Assumptions'!$B$8/4,'I_Budget Input Data'!$D$6*0.2/('I_Inputs & Assumptions'!$B$8/4),IF(20<='I_Inputs & Assumptions'!$B$8*0.75,'I_Budget Input Data'!$D$6*0.6/('I_Inputs & Assumptions'!$B$8/2),'I_Budget Input Data'!$D$6*0.2/('I_Inputs & Assumptions'!$B$8/4))),IF('I_Budget Input Data'!$E$6="At Completion",IF(20='I_Inputs & Assumptions'!$B$8,'I_Budget Input Data'!$D$6,0),'I_Budget Input Data'!$D$6/'I_Inputs & Assumptions'!$B$8)))))),0) -> 0 | W6: =IF(21<='I_Inputs & Assumptions'!$B$8,IF('I_Budget Input Data'!$E$6="Upfront",IF(21=1,'I_Budget Input Data'!$D$6,0),IF('I_Budget Input Data'!$E$6="Equal",'I_Budget Input Data'!$D$6/'I_Inputs & Assumptions'!$B$8,IF('I_Budget Input Data'!$E$6="Front-loaded",IF(21<='I_Inputs & Assumptions'!$B$8/2,'I_Budget Input Data'!$D$6*0.6/('I_Inputs & Assumptions'!$B$8/2),'I_Budget Input Data'!$D$6*0.4/('I_Inputs & Assumptions'!$B$8/2)),IF('I_Budget Input Data'!$E$6="Back-loaded",IF(21<='I_Inputs & Assumptions'!$B$8/2,'I_Budget Input Data'!$D$6*0.4/('I_Inputs & Assumptions'!$B$8/2),'I_Budget Input Data'!$D$6*0.6/('I_Inputs & Assumptions'!$B$8/2)),IF('I_Budget Input Data'!$E$6="Mid-weighted",IF(21<='I_Inputs & Assumptions'!$B$8/4,'I_Budget Input Data'!$D$6*0.2/('I_Inputs & Assumptions'!$B$8/4),IF(21<='I_Inputs & Assumptions'!$B$8*0.75,'I_Budget Input Data'!$D$6*0.6/('I_Inputs & Assumptions'!$B$8/2),'I_Budget Input Data'!$D$6*0.2/('I_Inputs & Assumptions'!$B$8/4))),IF('I_Budget Input Data'!$E$6="At Completion",IF(21='I_Inputs & Assumptions'!$B$8,'I_Budget Input Data'!$D$6,0),'I_Budget Input Data'!$D$6/'I_Inputs & Assumptions'!$B$8)))))),0) -> 0 | X6: =IF(22<='I_Inputs & Assumptions'!$B$8,IF('I_Budget Input Data'!$E$6="Upfront",IF(22=1,'I_Budget Input Data'!$D$6,0),IF('I_Budget Input Data'!$E$6="Equal",'I_Budget Input Data'!$D$6/'I_Inputs & Assumptions'!$B$8,IF('I_Budget Input Data'!$E$6="Front-loaded",IF(22<='I_Inputs & Assumptions'!$B$8/2,'I_Budget Input Data'!$D$6*0.6/('I_Inputs & Assumptions'!$B$8/2),'I_Budget Input Data'!$D$6*0.4/('I_Inputs & Assumptions'!$B$8/2)),IF('I_Budget Input Data'!$E$6="Back-loaded",IF(22<='I_Inputs & Assumptions'!$B$8/2,'I_Budget Input Data'!$D$6*0.4/('I_Inputs & Assumptions'!$B$8/2),'I_Budget Input Data'!$D$6*0.6/('I_Inputs & Assumptions'!$B$8/2)),IF('I_Budget Input Data'!$E$6="Mid-weighted",IF(22<='I_Inputs & Assumptions'!$B$8/4,'I_Budget Input Data'!$D$6*0.2/('I_Inputs & Assumptions'!$B$8/4),IF(22<='I_Inputs & Assumptions'!$B$8*0.75,'I_Budget Input Data'!$D$6*0.6/('I_Inputs & Assumptions'!$B$8/2),'I_Budget Input Data'!$D$6*0.2/('I_Inputs & Assumptions'!$B$8/4))),IF('I_Budget Input Data'!$E$6="At Completion",IF(22='I_Inputs & Assumptions'!$B$8,'I_Budget Input Data'!$D$6,0),'I_Budget Input Data'!$D$6/'I_Inputs & Assumptions'!$B$8)))))),0) -> 0 | Y6: =IF(23<='I_Inputs & Assumptions'!$B$8,IF('I_Budget Input Data'!$E$6="Upfront",IF(23=1,'I_Budget Input Data'!$D$6,0),IF('I_Budget Input Data'!$E$6="Equal",'I_Budget Input Data'!$D$6/'I_Inputs & Assumptions'!$B$8,IF('I_Budget Input Data'!$E$6="Front-loaded",IF(23<='I_Inputs & Assumptions'!$B$8/2,'I_Budget Input Data'!$D$6*0.6/('I_Inputs & Assumptions'!$B$8/2),'I_Budget Input Data'!$D$6*0.4/('I_Inputs & Assumptions'!$B$8/2)),IF('I_Budget Input Data'!$E$6="Back-loaded",IF(23<='I_Inputs & Assumptions'!$B$8/2,'I_Budget Input Data'!$D$6*0.4/('I_Inputs & Assumptions'!$B$8/2),'I_Budget Input Data'!$D$6*0.6/('I_Inputs & Assumptions'!$B$8/2)),IF('I_Budget Input Data'!$E$6="Mid-weighted",IF(23<='I_Inputs & Assumptions'!$B$8/4,'I_Budget Input Data'!$D$6*0.2/('I_Inputs & Assumptions'!$B$8/4),IF(23<='I_Inputs & Assumptions'!$B$8*0.75,'I_Budget Input Data'!$D$6*0.6/('I_Inputs & Assumptions'!$B$8/2),'I_Budget Input Data'!$D$6*0.2/('I_Inputs & Assumptions'!$B$8/4))),IF('I_Budget Input Data'!$E$6="At Completion",IF(23='I_Inputs & Assumptions'!$B$8,'I_Budget Input Data'!$D$6,0),'I_Budget Input Data'!$D$6/'I_Inputs & Assumptions'!$B$8)))))),0) -> 0 | Z6: =IF(24<='I_Inputs & Assumptions'!$B$8,IF('I_Budget Input Data'!$E$6="Upfront",IF(24=1,'I_Budget Input Data'!$D$6,0),IF('I_Budget Input Data'!$E$6="Equal",'I_Budget Input Data'!$D$6/'I_Inputs & Assumptions'!$B$8,IF('I_Budget Input Data'!$E$6="Front-loaded",IF(24<='I_Inputs & Assumptions'!$B$8/2,'I_Budget Input Data'!$D$6*0.6/('I_Inputs & Assumptions'!$B$8/2),'I_Budget Input Data'!$D$6*0.4/('I_Inputs & Assumptions'!$B$8/2)),IF('I_Budget Input Data'!$E$6="Back-loaded",IF(24<='I_Inputs & Assumptions'!$B$8/2,'I_Budget Input Data'!$D$6*0.4/('I_Inputs & Assumptions'!$B$8/2),'I_Budget Input Data'!$D$6*0.6/('I_Inputs & Assumptions'!$B$8/2)),IF('I_Budget Input Data'!$E$6="Mid-weighted",IF(24<='I_Inputs & Assumptions'!$B$8/4,'I_Budget Input Data'!$D$6*0.2/('I_Inputs & Assumptions'!$B$8/4),IF(24<='I_Inputs & Assumptions'!$B$8*0.75,'I_Budget Input Data'!$D$6*0.6/('I_Inputs & Assumptions'!$B$8/2),'I_Budget Input Data'!$D$6*0.2/('I_Inputs & Assumptions'!$B$8/4))),IF('I_Budget Input Data'!$E$6="At Completion",IF(24='I_Inputs & Assumptions'!$B$8,'I_Budget Input Data'!$D$6,0),'I_Budget Input Data'!$D$6/'I_Inputs & Assumptions'!$B$8)))))),0) -> 0 | AA6: =IF(25<='I_Inputs & Assumptions'!$B$8,IF('I_Budget Input Data'!$E$6="Upfront",IF(25=1,'I_Budget Input Data'!$D$6,0),IF('I_Budget Input Data'!$E$6="Equal",'I_Budget Input Data'!$D$6/'I_Inputs & Assumptions'!$B$8,IF('I_Budget Input Data'!$E$6="Front-loaded",IF(25<='I_Inputs & Assumptions'!$B$8/2,'I_Budget Input Data'!$D$6*0.6/('I_Inputs & Assumptions'!$B$8/2),'I_Budget Input Data'!$D$6*0.4/('I_Inputs & Assumptions'!$B$8/2)),IF('I_Budget Input Data'!$E$6="Back-loaded",IF(25<='I_Inputs & Assumptions'!$B$8/2,'I_Budget Input Data'!$D$6*0.4/('I_Inputs & Assumptions'!$B$8/2),'I_Budget Input Data'!$D$6*0.6/('I_Inputs & Assumptions'!$B$8/2)),IF('I_Budget Input Data'!$E$6="Mid-weighted",IF(25<='I_Inputs & Assumptions'!$B$8/4,'I_Budget Input Data'!$D$6*0.2/('I_Inputs & Assumptions'!$B$8/4),IF(25<='I_Inputs & Assumptions'!$B$8*0.75,'I_Budget Input Data'!$D$6*0.6/('I_Inputs & Assumptions'!$B$8/2),'I_Budget Input Data'!$D$6*0.2/('I_Inputs & Assumptions'!$B$8/4))),IF('I_Budget Input Data'!$E$6="At Completion",IF(25='I_Inputs & Assumptions'!$B$8,'I_Budget Input Data'!$D$6,0),'I_Budget Input Data'!$D$6/'I_Inputs & Assumptions'!$B$8)))))),0) -> 0 | AB6: =IF(26<='I_Inputs & Assumptions'!$B$8,IF('I_Budget Input Data'!$E$6="Upfront",IF(26=1,'I_Budget Input Data'!$D$6,0),IF('I_Budget Input Data'!$E$6="Equal",'I_Budget Input Data'!$D$6/'I_Inputs & Assumptions'!$B$8,IF('I_Budget Input Data'!$E$6="Front-loaded",IF(26<='I_Inputs & Assumptions'!$B$8/2,'I_Budget Input Data'!$D$6*0.6/('I_Inputs & Assumptions'!$B$8/2),'I_Budget Input Data'!$D$6*0.4/('I_Inputs & Assumptions'!$B$8/2)),IF('I_Budget Input Data'!$E$6="Back-loaded",IF(26<='I_Inputs & Assumptions'!$B$8/2,'I_Budget Input Data'!$D$6*0.4/('I_Inputs & Assumptions'!$B$8/2),'I_Budget Input Data'!$D$6*0.6/('I_Inputs & Assumptions'!$B$8/2)),IF('I_Budget Input Data'!$E$6="Mid-weighted",IF(26<='I_Inputs & Assumptions'!$B$8/4,'I_Budget Input Data'!$D$6*0.2/('I_Inputs & Assumptions'!$B$8/4),IF(26<='I_Inputs & Assumptions'!$B$8*0.75,'I_Budget Input Data'!$D$6*0.6/('I_Inputs & Assumptions'!$B$8/2),'I_Budget Input Data'!$D$6*0.2/('I_Inputs & Assumptions'!$B$8/4))),IF('I_Budget Input Data'!$E$6="At Completion",IF(26='I_Inputs & Assumptions'!$B$8,'I_Budget Input Data'!$D$6,0),'I_Budget Input Data'!$D$6/'I_Inputs & Assumptions'!$B$8)))))),0) -> 0 | AC6: =IF(27<='I_Inputs & Assumptions'!$B$8,IF('I_Budget Input Data'!$E$6="Upfront",IF(27=1,'I_Budget Input Data'!$D$6,0),IF('I_Budget Input Data'!$E$6="Equal",'I_Budget Input Data'!$D$6/'I_Inputs & Assumptions'!$B$8,IF('I_Budget Input Data'!$E$6="Front-loaded",IF(27<='I_Inputs & Assumptions'!$B$8/2,'I_Budget Input Data'!$D$6*0.6/('I_Inputs & Assumptions'!$B$8/2),'I_Budget Input Data'!$D$6*0.4/('I_Inputs & Assumptions'!$B$8/2)),IF('I_Budget Input Data'!$E$6="Back-loaded",IF(27<='I_Inputs & Assumptions'!$B$8/2,'I_Budget Input Data'!$D$6*0.4/('I_Inputs & Assumptions'!$B$8/2),'I_Budget Input Data'!$D$6*0.6/('I_Inputs & Assumptions'!$B$8/2)),IF('I_Budget Input Data'!$E$6="Mid-weighted",IF(27<='I_Inputs & Assumptions'!$B$8/4,'I_Budget Input Data'!$D$6*0.2/('I_Inputs & Assumptions'!$B$8/4),IF(27<='I_Inputs & Assumptions'!$B$8*0.75,'I_Budget Input Data'!$D$6*0.6/('I_Inputs & Assumptions'!$B$8/2),'I_Budget Input Data'!$D$6*0.2/('I_Inputs & Assumptions'!$B$8/4))),IF('I_Budget Input Data'!$E$6="At Completion",IF(27='I_Inputs & Assumptions'!$B$8,'I_Budget Input Data'!$D$6,0),'I_Budget Input Data'!$D$6/'I_Inputs & Assumptions'!$B$8)))))),0) -> 0 | AD6: =IF(28<='I_Inputs & Assumptions'!$B$8,IF('I_Budget Input Data'!$E$6="Upfront",IF(28=1,'I_Budget Input Data'!$D$6,0),IF('I_Budget Input Data'!$E$6="Equal",'I_Budget Input Data'!$D$6/'I_Inputs & Assumptions'!$B$8,IF('I_Budget Input Data'!$E$6="Front-loaded",IF(28<='I_Inputs & Assumptions'!$B$8/2,'I_Budget Input Data'!$D$6*0.6/('I_Inputs & Assumptions'!$B$8/2),'I_Budget Input Data'!$D$6*0.4/('I_Inputs & Assumptions'!$B$8/2)),IF('I_Budget Input Data'!$E$6="Back-loaded",IF(28<='I_Inputs & Assumptions'!$B$8/2,'I_Budget Input Data'!$D$6*0.4/('I_Inputs & Assumptions'!$B$8/2),'I_Budget Input Data'!$D$6*0.6/('I_Inputs & Assumptions'!$B$8/2)),IF('I_Budget Input Data'!$E$6="Mid-weighted",IF(28<='I_Inputs & Assumptions'!$B$8/4,'I_Budget Input Data'!$D$6*0.2/('I_Inputs & Assumptions'!$B$8/4),IF(28<='I_Inputs & Assumptions'!$B$8*0.75,'I_Budget Input Data'!$D$6*0.6/('I_Inputs & Assumptions'!$B$8/2),'I_Budget Input Data'!$D$6*0.2/('I_Inputs & Assumptions'!$B$8/4))),IF('I_Budget Input Data'!$E$6="At Completion",IF(28='I_Inputs & Assumptions'!$B$8,'I_Budget Input Data'!$D$6,0),'I_Budget Input Data'!$D$6/'I_Inputs & Assumptions'!$B$8)))))),0) -> 0 | AE6: =IF(29<='I_Inputs & Assumptions'!$B$8,IF('I_Budget Input Data'!$E$6="Upfront",IF(29=1,'I_Budget Input Data'!$D$6,0),IF('I_Budget Input Data'!$E$6="Equal",'I_Budget Input Data'!$D$6/'I_Inputs & Assumptions'!$B$8,IF('I_Budget Input Data'!$E$6="Front-loaded",IF(29<='I_Inputs & Assumptions'!$B$8/2,'I_Budget Input Data'!$D$6*0.6/('I_Inputs & Assumptions'!$B$8/2),'I_Budget Input Data'!$D$6*0.4/('I_Inputs & Assumptions'!$B$8/2)),IF('I_Budget Input Data'!$E$6="Back-loaded",IF(29<='I_Inputs & Assumptions'!$B$8/2,'I_Budget Input Data'!$D$6*0.4/('I_Inputs & Assumptions'!$B$8/2),'I_Budget Input Data'!$D$6*0.6/('I_Inputs & Assumptions'!$B$8/2)),IF('I_Budget Input Data'!$E$6="Mid-weighted",IF(29<='I_Inputs & Assumptions'!$B$8/4,'I_Budget Input Data'!$D$6*0.2/('I_Inputs & Assumptions'!$B$8/4),IF(29<='I_Inputs & Assumptions'!$B$8*0.75,'I_Budget Input Data'!$D$6*0.6/('I_Inputs & Assumptions'!$B$8/2),'I_Budget Input Data'!$D$6*0.2/('I_Inputs & Assumptions'!$B$8/4))),IF('I_Budget Input Data'!$E$6="At Completion",IF(29='I_Inputs & Assumptions'!$B$8,'I_Budget Input Data'!$D$6,0),'I_Budget Input Data'!$D$6/'I_Inputs & Assumptions'!$B$8)))))),0) -> 0 | AF6: =IF(30<='I_Inputs & Assumptions'!$B$8,IF('I_Budget Input Data'!$E$6="Upfront",IF(30=1,'I_Budget Input Data'!$D$6,0),IF('I_Budget Input Data'!$E$6="Equal",'I_Budget Input Data'!$D$6/'I_Inputs & Assumptions'!$B$8,IF('I_Budget Input Data'!$E$6="Front-loaded",IF(30<='I_Inputs & Assumptions'!$B$8/2,'I_Budget Input Data'!$D$6*0.6/('I_Inputs & Assumptions'!$B$8/2),'I_Budget Input Data'!$D$6*0.4/('I_Inputs & Assumptions'!$B$8/2)),IF('I_Budget Input Data'!$E$6="Back-loaded",IF(30<='I_Inputs & Assumptions'!$B$8/2,'I_Budget Input Data'!$D$6*0.4/('I_Inputs & Assumptions'!$B$8/2),'I_Budget Input Data'!$D$6*0.6/('I_Inputs & Assumptions'!$B$8/2)),IF('I_Budget Input Data'!$E$6="Mid-weighted",IF(30<='I_Inputs & Assumptions'!$B$8/4,'I_Budget Input Data'!$D$6*0.2/('I_Inputs & Assumptions'!$B$8/4),IF(30<='I_Inputs & Assumptions'!$B$8*0.75,'I_Budget Input Data'!$D$6*0.6/('I_Inputs & Assumptions'!$B$8/2),'I_Budget Input Data'!$D$6*0.2/('I_Inputs & Assumptions'!$B$8/4))),IF('I_Budget Input Data'!$E$6="At Completion",IF(30='I_Inputs & Assumptions'!$B$8,'I_Budget Input Data'!$D$6,0),'I_Budget Input Data'!$D$6/'I_Inputs & Assumptions'!$B$8)))))),0) -> 0 | AG6: =IF(31<='I_Inputs & Assumptions'!$B$8,IF('I_Budget Input Data'!$E$6="Upfront",IF(31=1,'I_Budget Input Data'!$D$6,0),IF('I_Budget Input Data'!$E$6="Equal",'I_Budget Input Data'!$D$6/'I_Inputs & Assumptions'!$B$8,IF('I_Budget Input Data'!$E$6="Front-loaded",IF(31<='I_Inputs & Assumptions'!$B$8/2,'I_Budget Input Data'!$D$6*0.6/('I_Inputs & Assumptions'!$B$8/2),'I_Budget Input Data'!$D$6*0.4/('I_Inputs & Assumptions'!$B$8/2)),IF('I_Budget Input Data'!$E$6="Back-loaded",IF(31<='I_Inputs & Assumptions'!$B$8/2,'I_Budget Input Data'!$D$6*0.4/('I_Inputs & Assumptions'!$B$8/2),'I_Budget Input Data'!$D$6*0.6/('I_Inputs & Assumptions'!$B$8/2)),IF('I_Budget Input Data'!$E$6="Mid-weighted",IF(31<='I_Inputs & Assumptions'!$B$8/4,'I_Budget Input Data'!$D$6*0.2/('I_Inputs & Assumptions'!$B$8/4),IF(31<='I_Inputs & Assumptions'!$B$8*0.75,'I_Budget Input Data'!$D$6*0.6/('I_Inputs & Assumptions'!$B$8/2),'I_Budget Input Data'!$D$6*0.2/('I_Inputs & Assumptions'!$B$8/4))),IF('I_Budget Input Data'!$E$6="At Completion",IF(31='I_Inputs & Assumptions'!$B$8,'I_Budget Input Data'!$D$6,0),'I_Budget Input Data'!$D$6/'I_Inputs & Assumptions'!$B$8)))))),0) -> 0 | AH6: =IF(32<='I_Inputs & Assumptions'!$B$8,IF('I_Budget Input Data'!$E$6="Upfront",IF(32=1,'I_Budget Input Data'!$D$6,0),IF('I_Budget Input Data'!$E$6="Equal",'I_Budget Input Data'!$D$6/'I_Inputs & Assumptions'!$B$8,IF('I_Budget Input Data'!$E$6="Front-loaded",IF(32<='I_Inputs & Assumptions'!$B$8/2,'I_Budget Input Data'!$D$6*0.6/('I_Inputs & Assumptions'!$B$8/2),'I_Budget Input Data'!$D$6*0.4/('I_Inputs & Assumptions'!$B$8/2)),IF('I_Budget Input Data'!$E$6="Back-loaded",IF(32<='I_Inputs & Assumptions'!$B$8/2,'I_Budget Input Data'!$D$6*0.4/('I_Inputs & Assumptions'!$B$8/2),'I_Budget Input Data'!$D$6*0.6/('I_Inputs & Assumptions'!$B$8/2)),IF('I_Budget Input Data'!$E$6="Mid-weighted",IF(32<='I_Inputs & Assumptions'!$B$8/4,'I_Budget Input Data'!$D$6*0.2/('I_Inputs & Assumptions'!$B$8/4),IF(32<='I_Inputs & Assumptions'!$B$8*0.75,'I_Budget Input Data'!$D$6*0.6/('I_Inputs & Assumptions'!$B$8/2),'I_Budget Input Data'!$D$6*0.2/('I_Inputs & Assumptions'!$B$8/4))),IF('I_Budget Input Data'!$E$6="At Completion",IF(32='I_Inputs & Assumptions'!$B$8,'I_Budget Input Data'!$D$6,0),'I_Budget Input Data'!$D$6/'I_Inputs & Assumptions'!$B$8)))))),0) -> 0 | AI6: =IF(33<='I_Inputs & Assumptions'!$B$8,IF('I_Budget Input Data'!$E$6="Upfront",IF(33=1,'I_Budget Input Data'!$D$6,0),IF('I_Budget Input Data'!$E$6="Equal",'I_Budget Input Data'!$D$6/'I_Inputs & Assumptions'!$B$8,IF('I_Budget Input Data'!$E$6="Front-loaded",IF(33<='I_Inputs & Assumptions'!$B$8/2,'I_Budget Input Data'!$D$6*0.6/('I_Inputs & Assumptions'!$B$8/2),'I_Budget Input Data'!$D$6*0.4/('I_Inputs & Assumptions'!$B$8/2)),IF('I_Budget Input Data'!$E$6="Back-loaded",IF(33<='I_Inputs & Assumptions'!$B$8/2,'I_Budget Input Data'!$D$6*0.4/('I_Inputs & Assumptions'!$B$8/2),'I_Budget Input Data'!$D$6*0.6/('I_Inputs & Assumptions'!$B$8/2)),IF('I_Budget Input Data'!$E$6="Mid-weighted",IF(33<='I_Inputs & Assumptions'!$B$8/4,'I_Budget Input Data'!$D$6*0.2/('I_Inputs & Assumptions'!$B$8/4),IF(33<='I_Inputs & Assumptions'!$B$8*0.75,'I_Budget Input Data'!$D$6*0.6/('I_Inputs & Assumptions'!$B$8/2),'I_Budget Input Data'!$D$6*0.2/('I_Inputs & Assumptions'!$B$8/4))),IF('I_Budget Input Data'!$E$6="At Completion",IF(33='I_Inputs & Assumptions'!$B$8,'I_Budget Input Data'!$D$6,0),'I_Budget Input Data'!$D$6/'I_Inputs & Assumptions'!$B$8)))))),0) -> 0 | AJ6: =IF(34<='I_Inputs & Assumptions'!$B$8,IF('I_Budget Input Data'!$E$6="Upfront",IF(34=1,'I_Budget Input Data'!$D$6,0),IF('I_Budget Input Data'!$E$6="Equal",'I_Budget Input Data'!$D$6/'I_Inputs & Assumptions'!$B$8,IF('I_Budget Input Data'!$E$6="Front-loaded",IF(34<='I_Inputs & Assumptions'!$B$8/2,'I_Budget Input Data'!$D$6*0.6/('I_Inputs & Assumptions'!$B$8/2),'I_Budget Input Data'!$D$6*0.4/('I_Inputs & Assumptions'!$B$8/2)),IF('I_Budget Input Data'!$E$6="Back-loaded",IF(34<='I_Inputs & Assumptions'!$B$8/2,'I_Budget Input Data'!$D$6*0.4/('I_Inputs & Assumptions'!$B$8/2),'I_Budget Input Data'!$D$6*0.6/('I_Inputs & Assumptions'!$B$8/2)),IF('I_Budget Input Data'!$E$6="Mid-weighted",IF(34<='I_Inputs & Assumptions'!$B$8/4,'I_Budget Input Data'!$D$6*0.2/('I_Inputs & Assumptions'!$B$8/4),IF(34<='I_Inputs & Assumptions'!$B$8*0.75,'I_Budget Input Data'!$D$6*0.6/('I_Inputs & Assumptions'!$B$8/2),'I_Budget Input Data'!$D$6*0.2/('I_Inputs & Assumptions'!$B$8/4))),IF('I_Budget Input Data'!$E$6="At Completion",IF(34='I_Inputs & Assumptions'!$B$8,'I_Budget Input Data'!$D$6,0),'I_Budget Input Data'!$D$6/'I_Inputs & Assumptions'!$B$8)))))),0) -> 0 | AK6: =IF(35<='I_Inputs & Assumptions'!$B$8,IF('I_Budget Input Data'!$E$6="Upfront",IF(35=1,'I_Budget Input Data'!$D$6,0),IF('I_Budget Input Data'!$E$6="Equal",'I_Budget Input Data'!$D$6/'I_Inputs & Assumptions'!$B$8,IF('I_Budget Input Data'!$E$6="Front-loaded",IF(35<='I_Inputs & Assumptions'!$B$8/2,'I_Budget Input Data'!$D$6*0.6/('I_Inputs & Assumptions'!$B$8/2),'I_Budget Input Data'!$D$6*0.4/('I_Inputs & Assumptions'!$B$8/2)),IF('I_Budget Input Data'!$E$6="Back-loaded",IF(35<='I_Inputs & Assumptions'!$B$8/2,'I_Budget Input Data'!$D$6*0.4/('I_Inputs & Assumptions'!$B$8/2),'I_Budget Input Data'!$D$6*0.6/('I_Inputs & Assumptions'!$B$8/2)),IF('I_Budget Input Data'!$E$6="Mid-weighted",IF(35<='I_Inputs & Assumptions'!$B$8/4,'I_Budget Input Data'!$D$6*0.2/('I_Inputs & Assumptions'!$B$8/4),IF(35<='I_Inputs & Assumptions'!$B$8*0.75,'I_Budget Input Data'!$D$6*0.6/('I_Inputs & Assumptions'!$B$8/2),'I_Budget Input Data'!$D$6*0.2/('I_Inputs & Assumptions'!$B$8/4))),IF('I_Budget Input Data'!$E$6="At Completion",IF(35='I_Inputs & Assumptions'!$B$8,'I_Budget Input Data'!$D$6,0),'I_Budget Input Data'!$D$6/'I_Inputs & Assumptions'!$B$8)))))),0) -> 0 | AL6: =IF(36<='I_Inputs & Assumptions'!$B$8,IF('I_Budget Input Data'!$E$6="Upfront",IF(36=1,'I_Budget Input Data'!$D$6,0),IF('I_Budget Input Data'!$E$6="Equal",'I_Budget Input Data'!$D$6/'I_Inputs & Assumptions'!$B$8,IF('I_Budget Input Data'!$E$6="Front-loaded",IF(36<='I_Inputs & Assumptions'!$B$8/2,'I_Budget Input Data'!$D$6*0.6/('I_Inputs & Assumptions'!$B$8/2),'I_Budget Input Data'!$D$6*0.4/('I_Inputs & Assumptions'!$B$8/2)),IF('I_Budget Input Data'!$E$6="Back-loaded",IF(36<='I_Inputs & Assumptions'!$B$8/2,'I_Budget Input Data'!$D$6*0.4/('I_Inputs & Assumptions'!$B$8/2),'I_Budget Input Data'!$D$6*0.6/('I_Inputs & Assumptions'!$B$8/2)),IF('I_Budget Input Data'!$E$6="Mid-weighted",IF(36<='I_Inputs & Assumptions'!$B$8/4,'I_Budget Input Data'!$D$6*0.2/('I_Inputs & Assumptions'!$B$8/4),IF(36<='I_Inputs & Assumptions'!$B$8*0.75,'I_Budget Input Data'!$D$6*0.6/('I_Inputs & Assumptions'!$B$8/2),'I_Budget Input Data'!$D$6*0.2/('I_Inputs & Assumptions'!$B$8/4))),IF('I_Budget Input Data'!$E$6="At Completion",IF(36='I_Inputs & Assumptions'!$B$8,'I_Budget Input Data'!$D$6,0),'I_Budget Input Data'!$D$6/'I_Inputs & Assumptions'!$B$8)))))),0) -> 0
A7: 1. LAND | B7: Notary and cadastre | C7: =IF(1<='I_Inputs & Assumptions'!$B$8,IF('I_Budget Input Data'!$E$7="Upfront",IF(1=1,'I_Budget Input Data'!$D$7,0),IF('I_Budget Input Data'!$E$7="Equal",'I_Budget Input Data'!$D$7/'I_Inputs & Assumptions'!$B$8,IF('I_Budget Input Data'!$E$7="Front-loaded",IF(1<='I_Inputs & Assumptions'!$B$8/2,'I_Budget Input Data'!$D$7*0.6/('I_Inputs & Assumptions'!$B$8/2),'I_Budget Input Data'!$D$7*0.4/('I_Inputs & Assumptions'!$B$8/2)),IF('I_Budget Input Data'!$E$7="Back-loaded",IF(1<='I_Inputs & Assumptions'!$B$8/2,'I_Budget Input Data'!$D$7*0.4/('I_Inputs & Assumptions'!$B$8/2),'I_Budget Input Data'!$D$7*0.6/('I_Inputs & Assumptions'!$B$8/2)),IF('I_Budget Input Data'!$E$7="Mid-weighted",IF(1<='I_Inputs & Assumptions'!$B$8/4,'I_Budget Input Data'!$D$7*0.2/('I_Inputs & Assumptions'!$B$8/4),IF(1<='I_Inputs & Assumptions'!$B$8*0.75,'I_Budget Input Data'!$D$7*0.6/('I_Inputs & Assumptions'!$B$8/2),'I_Budget Input Data'!$D$7*0.2/('I_Inputs & Assumptions'!$B$8/4))),IF('I_Budget Input Data'!$E$7="At Completion",IF(1='I_Inputs & Assumptions'!$B$8,'I_Budget Input Data'!$D$7,0),'I_Budget Input Data'!$D$7/'I_Inputs & Assumptions'!$B$8)))))),0) -> 19808 | D7: =IF(2<='I_Inputs & Assumptions'!$B$8,IF('I_Budget Input Data'!$E$7="Upfront",IF(2=1,'I_Budget Input Data'!$D$7,0),IF('I_Budget Input Data'!$E$7="Equal",'I_Budget Input Data'!$D$7/'I_Inputs & Assumptions'!$B$8,IF('I_Budget Input Data'!$E$7="Front-loaded",IF(2<='I_Inputs & Assumptions'!$B$8/2,'I_Budget Input Data'!$D$7*0.6/('I_Inputs & Assumptions'!$B$8/2),'I_Budget Input Data'!$D$7*0.4/('I_Inputs & Assumptions'!$B$8/2)),IF('I_Budget Input Data'!$E$7="Back-loaded",IF(2<='I_Inputs & Assumptions'!$B$8/2,'I_Budget Input Data'!$D$7*0.4/('I_Inputs & Assumptions'!$B$8/2),'I_Budget Input Data'!$D$7*0.6/('I_Inputs & Assumptions'!$B$8/2)),IF('I_Budget Input Data'!$E$7="Mid-weighted",IF(2<='I_Inputs & Assumptions'!$B$8/4,'I_Budget Input Data'!$D$7*0.2/('I_Inputs & Assumptions'!$B$8/4),IF(2<='I_Inputs & Assumptions'!$B$8*0.75,'I_Budget Input Data'!$D$7*0.6/('I_Inputs & Assumptions'!$B$8/2),'I_Budget Input Data'!$D$7*0.2/('I_Inputs & Assumptions'!$B$8/4))),IF('I_Budget Input Data'!$E$7="At Completion",IF(2='I_Inputs & Assumptions'!$B$8,'I_Budget Input Data'!$D$7,0),'I_Budget Input Data'!$D$7/'I_Inputs & Assumptions'!$B$8)))))),0) -> 0 | E7: =IF(3<='I_Inputs & Assumptions'!$B$8,IF('I_Budget Input Data'!$E$7="Upfront",IF(3=1,'I_Budget Input Data'!$D$7,0),IF('I_Budget Input Data'!$E$7="Equal",'I_Budget Input Data'!$D$7/'I_Inputs & Assumptions'!$B$8,IF('I_Budget Input Data'!$E$7="Front-loaded",IF(3<='I_Inputs & Assumptions'!$B$8/2,'I_Budget Input Data'!$D$7*0.6/('I_Inputs & Assumptions'!$B$8/2),'I_Budget Input Data'!$D$7*0.4/('I_Inputs & Assumptions'!$B$8/2)),IF('I_Budget Input Data'!$E$7="Back-loaded",IF(3<='I_Inputs & Assumptions'!$B$8/2,'I_Budget Input Data'!$D$7*0.4/('I_Inputs & Assumptions'!$B$8/2),'I_Budget Input Data'!$D$7*0.6/('I_Inputs & Assumptions'!$B$8/2)),IF('I_Budget Input Data'!$E$7="Mid-weighted",IF(3<='I_Inputs & Assumptions'!$B$8/4,'I_Budget Input Data'!$D$7*0.2/('I_Inputs & Assumptions'!$B$8/4),IF(3<='I_Inputs & Assumptions'!$B$8*0.75,'I_Budget Input Data'!$D$7*0.6/('I_Inputs & Assumptions'!$B$8/2),'I_Budget Input Data'!$D$7*0.2/('I_Inputs & Assumptions'!$B$8/4))),IF('I_Budget Input Data'!$E$7="At Completion",IF(3='I_Inputs & Assumptions'!$B$8,'I_Budget Input Data'!$D$7,0),'I_Budget Input Data'!$D$7/'I_Inputs & Assumptions'!$B$8)))))),0) -> 0 | F7: =IF(4<='I_Inputs & Assumptions'!$B$8,IF('I_Budget Input Data'!$E$7="Upfront",IF(4=1,'I_Budget Input Data'!$D$7,0),IF('I_Budget Input Data'!$E$7="Equal",'I_Budget Input Data'!$D$7/'I_Inputs & Assumptions'!$B$8,IF('I_Budget Input Data'!$E$7="Front-loaded",IF(4<='I_Inputs & Assumptions'!$B$8/2,'I_Budget Input Data'!$D$7*0.6/('I_Inputs & Assumptions'!$B$8/2),'I_Budget Input Data'!$D$7*0.4/('I_Inputs & Assumptions'!$B$8/2)),IF('I_Budget Input Data'!$E$7="Back-loaded",IF(4<='I_Inputs & Assumptions'!$B$8/2,'I_Budget Input Data'!$D$7*0.4/('I_Inputs & Assumptions'!$B$8/2),'I_Budget Input Data'!$D$7*0.6/('I_Inputs & Assumptions'!$B$8/2)),IF('I_Budget Input Data'!$E$7="Mid-weighted",IF(4<='I_Inputs & Assumptions'!$B$8/4,'I_Budget Input Data'!$D$7*0.2/('I_Inputs & Assumptions'!$B$8/4),IF(4<='I_Inputs & Assumptions'!$B$8*0.75,'I_Budget Input Data'!$D$7*0.6/('I_Inputs & Assumptions'!$B$8/2),'I_Budget Input Data'!$D$7*0.2/('I_Inputs & Assumptions'!$B$8/4))),IF('I_Budget Input Data'!$E$7="At Completion",IF(4='I_Inputs & Assumptions'!$B$8,'I_Budget Input Data'!$D$7,0),'I_Budget Input Data'!$D$7/'I_Inputs & Assumptions'!$B$8)))))),0) -> 0 | G7: =IF(5<='I_Inputs & Assumptions'!$B$8,IF('I_Budget Input Data'!$E$7="Upfront",IF(5=1,'I_Budget Input Data'!$D$7,0),IF('I_Budget Input Data'!$E$7="Equal",'I_Budget Input Data'!$D$7/'I_Inputs & Assumptions'!$B$8,IF('I_Budget Input Data'!$E$7="Front-loaded",IF(5<='I_Inputs & Assumptions'!$B$8/2,'I_Budget Input Data'!$D$7*0.6/('I_Inputs & Assumptions'!$B$8/2),'I_Budget Input Data'!$D$7*0.4/('I_Inputs & Assumptions'!$B$8/2)),IF('I_Budget Input Data'!$E$7="Back-loaded",IF(5<='I_Inputs & Assumptions'!$B$8/2,'I_Budget Input Data'!$D$7*0.4/('I_Inputs & Assumptions'!$B$8/2),'I_Budget Input Data'!$D$7*0.6/('I_Inputs & Assumptions'!$B$8/2)),IF('I_Budget Input Data'!$E$7="Mid-weighted",IF(5<='I_Inputs & Assumptions'!$B$8/4,'I_Budget Input Data'!$D$7*0.2/('I_Inputs & Assumptions'!$B$8/4),IF(5<='I_Inputs & Assumptions'!$B$8*0.75,'I_Budget Input Data'!$D$7*0.6/('I_Inputs & Assumptions'!$B$8/2),'I_Budget Input Data'!$D$7*0.2/('I_Inputs & Assumptions'!$B$8/4))),IF('I_Budget Input Data'!$E$7="At Completion",IF(5='I_Inputs & Assumptions'!$B$8,'I_Budget Input Data'!$D$7,0),'I_Budget Input Data'!$D$7/'I_Inputs & Assumptions'!$B$8)))))),0) -> 0 | H7: =IF(6<='I_Inputs & Assumptions'!$B$8,IF('I_Budget Input Data'!$E$7="Upfront",IF(6=1,'I_Budget Input Data'!$D$7,0),IF('I_Budget Input Data'!$E$7="Equal",'I_Budget Input Data'!$D$7/'I_Inputs & Assumptions'!$B$8,IF('I_Budget Input Data'!$E$7="Front-loaded",IF(6<='I_Inputs & Assumptions'!$B$8/2,'I_Budget Input Data'!$D$7*0.6/('I_Inputs & Assumptions'!$B$8/2),'I_Budget Input Data'!$D$7*0.4/('I_Inputs & Assumptions'!$B$8/2)),IF('I_Budget Input Data'!$E$7="Back-loaded",IF(6<='I_Inputs & Assumptions'!$B$8/2,'I_Budget Input Data'!$D$7*0.4/('I_Inputs & Assumptions'!$B$8/2),'I_Budget Input Data'!$D$7*0.6/('I_Inputs & Assumptions'!$B$8/2)),IF('I_Budget Input Data'!$E$7="Mid-weighted",IF(6<='I_Inputs & Assumptions'!$B$8/4,'I_Budget Input Data'!$D$7*0.2/('I_Inputs & Assumptions'!$B$8/4),IF(6<='I_Inputs & Assumptions'!$B$8*0.75,'I_Budget Input Data'!$D$7*0.6/('I_Inputs & Assumptions'!$B$8/2),'I_Budget Input Data'!$D$7*0.2/('I_Inputs & Assumptions'!$B$8/4))),IF('I_Budget Input Data'!$E$7="At Completion",IF(6='I_Inputs & Assumptions'!$B$8,'I_Budget Input Data'!$D$7,0),'I_Budget Input Data'!$D$7/'I_Inputs & Assumptions'!$B$8)))))),0) -> 0 | I7: =IF(7<='I_Inputs & Assumptions'!$B$8,IF('I_Budget Input Data'!$E$7="Upfront",IF(7=1,'I_Budget Input Data'!$D$7,0),IF('I_Budget Input Data'!$E$7="Equal",'I_Budget Input Data'!$D$7/'I_Inputs & Assumptions'!$B$8,IF('I_Budget Input Data'!$E$7="Front-loaded",IF(7<='I_Inputs & Assumptions'!$B$8/2,'I_Budget Input Data'!$D$7*0.6/('I_Inputs & Assumptions'!$B$8/2),'I_Budget Input Data'!$D$7*0.4/('I_Inputs & Assumptions'!$B$8/2)),IF('I_Budget Input Data'!$E$7="Back-loaded",IF(7<='I_Inputs & Assumptions'!$B$8/2,'I_Budget Input Data'!$D$7*0.4/('I_Inputs & Assumptions'!$B$8/2),'I_Budget Input Data'!$D$7*0.6/('I_Inputs & Assumptions'!$B$8/2)),IF('I_Budget Input Data'!$E$7="Mid-weighted",IF(7<='I_Inputs & Assumptions'!$B$8/4,'I_Budget Input Data'!$D$7*0.2/('I_Inputs & Assumptions'!$B$8/4),IF(7<='I_Inputs & Assumptions'!$B$8*0.75,'I_Budget Input Data'!$D$7*0.6/('I_Inputs & Assumptions'!$B$8/2),'I_Budget Input Data'!$D$7*0.2/('I_Inputs & Assumptions'!$B$8/4))),IF('I_Budget Input Data'!$E$7="At Completion",IF(7='I_Inputs & Assumptions'!$B$8,'I_Budget Input Data'!$D$7,0),'I_Budget Input Data'!$D$7/'I_Inputs & Assumptions'!$B$8)))))),0) -> 0 | J7: =IF(8<='I_Inputs & Assumptions'!$B$8,IF('I_Budget Input Data'!$E$7="Upfront",IF(8=1,'I_Budget Input Data'!$D$7,0),IF('I_Budget Input Data'!$E$7="Equal",'I_Budget Input Data'!$D$7/'I_Inputs & Assumptions'!$B$8,IF('I_Budget Input Data'!$E$7="Front-loaded",IF(8<='I_Inputs & Assumptions'!$B$8/2,'I_Budget Input Data'!$D$7*0.6/('I_Inputs & Assumptions'!$B$8/2),'I_Budget Input Data'!$D$7*0.4/('I_Inputs & Assumptions'!$B$8/2)),IF('I_Budget Input Data'!$E$7="Back-loaded",IF(8<='I_Inputs & Assumptions'!$B$8/2,'I_Budget Input Data'!$D$7*0.4/('I_Inputs & Assumptions'!$B$8/2),'I_Budget Input Data'!$D$7*0.6/('I_Inputs & Assumptions'!$B$8/2)),IF('I_Budget Input Data'!$E$7="Mid-weighted",IF(8<='I_Inputs & Assumptions'!$B$8/4,'I_Budget Input Data'!$D$7*0.2/('I_Inputs & Assumptions'!$B$8/4),IF(8<='I_Inputs & Assumptions'!$B$8*0.75,'I_Budget Input Data'!$D$7*0.6/('I_Inputs & Assumptions'!$B$8/2),'I_Budget Input Data'!$D$7*0.2/('I_Inputs & Assumptions'!$B$8/4))),IF('I_Budget Input Data'!$E$7="At Completion",IF(8='I_Inputs & Assumptions'!$B$8,'I_Budget Input Data'!$D$7,0),'I_Budget Input Data'!$D$7/'I_Inputs & Assumptions'!$B$8)))))),0) -> 0 | K7: =IF(9<='I_Inputs & Assumptions'!$B$8,IF('I_Budget Input Data'!$E$7="Upfront",IF(9=1,'I_Budget Input Data'!$D$7,0),IF('I_Budget Input Data'!$E$7="Equal",'I_Budget Input Data'!$D$7/'I_Inputs & Assumptions'!$B$8,IF('I_Budget Input Data'!$E$7="Front-loaded",IF(9<='I_Inputs & Assumptions'!$B$8/2,'I_Budget Input Data'!$D$7*0.6/('I_Inputs & Assumptions'!$B$8/2),'I_Budget Input Data'!$D$7*0.4/('I_Inputs & Assumptions'!$B$8/2)),IF('I_Budget Input Data'!$E$7="Back-loaded",IF(9<='I_Inputs & Assumptions'!$B$8/2,'I_Budget Input Data'!$D$7*0.4/('I_Inputs & Assumptions'!$B$8/2),'I_Budget Input Data'!$D$7*0.6/('I_Inputs & Assumptions'!$B$8/2)),IF('I_Budget Input Data'!$E$7="Mid-weighted",IF(9<='I_Inputs & Assumptions'!$B$8/4,'I_Budget Input Data'!$D$7*0.2/('I_Inputs & Assumptions'!$B$8/4),IF(9<='I_Inputs & Assumptions'!$B$8*0.75,'I_Budget Input Data'!$D$7*0.6/('I_Inputs & Assumptions'!$B$8/2),'I_Budget Input Data'!$D$7*0.2/('I_Inputs & Assumptions'!$B$8/4))),IF('I_Budget Input Data'!$E$7="At Completion",IF(9='I_Inputs & Assumptions'!$B$8,'I_Budget Input Data'!$D$7,0),'I_Budget Input Data'!$D$7/'I_Inputs & Assumptions'!$B$8)))))),0) -> 0 | L7: =IF(10<='I_Inputs & Assumptions'!$B$8,IF('I_Budget Input Data'!$E$7="Upfront",IF(10=1,'I_Budget Input Data'!$D$7,0),IF('I_Budget Input Data'!$E$7="Equal",'I_Budget Input Data'!$D$7/'I_Inputs & Assumptions'!$B$8,IF('I_Budget Input Data'!$E$7="Front-loaded",IF(10<='I_Inputs & Assumptions'!$B$8/2,'I_Budget Input Data'!$D$7*0.6/('I_Inputs & Assumptions'!$B$8/2),'I_Budget Input Data'!$D$7*0.4/('I_Inputs & Assumptions'!$B$8/2)),IF('I_Budget Input Data'!$E$7="Back-loaded",IF(10<='I_Inputs & Assumptions'!$B$8/2,'I_Budget Input Data'!$D$7*0.4/('I_Inputs & Assumptions'!$B$8/2),'I_Budget Input Data'!$D$7*0.6/('I_Inputs & Assumptions'!$B$8/2)),IF('I_Budget Input Data'!$E$7="Mid-weighted",IF(10<='I_Inputs & Assumptions'!$B$8/4,'I_Budget Input Data'!$D$7*0.2/('I_Inputs & Assumptions'!$B$8/4),IF(10<='I_Inputs & Assumptions'!$B$8*0.75,'I_Budget Input Data'!$D$7*0.6/('I_Inputs & Assumptions'!$B$8/2),'I_Budget Input Data'!$D$7*0.2/('I_Inputs & Assumptions'!$B$8/4))),IF('I_Budget Input Data'!$E$7="At Completion",IF(10='I_Inputs & Assumptions'!$B$8,'I_Budget Input Data'!$D$7,0),'I_Budget Input Data'!$D$7/'I_Inputs & Assumptions'!$B$8)))))),0) -> 0 | M7: =IF(11<='I_Inputs & Assumptions'!$B$8,IF('I_Budget Input Data'!$E$7="Upfront",IF(11=1,'I_Budget Input Data'!$D$7,0),IF('I_Budget Input Data'!$E$7="Equal",'I_Budget Input Data'!$D$7/'I_Inputs & Assumptions'!$B$8,IF('I_Budget Input Data'!$E$7="Front-loaded",IF(11<='I_Inputs & Assumptions'!$B$8/2,'I_Budget Input Data'!$D$7*0.6/('I_Inputs & Assumptions'!$B$8/2),'I_Budget Input Data'!$D$7*0.4/('I_Inputs & Assumptions'!$B$8/2)),IF('I_Budget Input Data'!$E$7="Back-loaded",IF(11<='I_Inputs & Assumptions'!$B$8/2,'I_Budget Input Data'!$D$7*0.4/('I_Inputs & Assumptions'!$B$8/2),'I_Budget Input Data'!$D$7*0.6/('I_Inputs & Assumptions'!$B$8/2)),IF('I_Budget Input Data'!$E$7="Mid-weighted",IF(11<='I_Inputs & Assumptions'!$B$8/4,'I_Budget Input Data'!$D$7*0.2/('I_Inputs & Assumptions'!$B$8/4),IF(11<='I_Inputs & Assumptions'!$B$8*0.75,'I_Budget Input Data'!$D$7*0.6/('I_Inputs & Assumptions'!$B$8/2),'I_Budget Input Data'!$D$7*0.2/('I_Inputs & Assumptions'!$B$8/4))),IF('I_Budget Input Data'!$E$7="At Completion",IF(11='I_Inputs & Assumptions'!$B$8,'I_Budget Input Data'!$D$7,0),'I_Budget Input Data'!$D$7/'I_Inputs & Assumptions'!$B$8)))))),0) -> 0 | N7: =IF(12<='I_Inputs & Assumptions'!$B$8,IF('I_Budget Input Data'!$E$7="Upfront",IF(12=1,'I_Budget Input Data'!$D$7,0),IF('I_Budget Input Data'!$E$7="Equal",'I_Budget Input Data'!$D$7/'I_Inputs & Assumptions'!$B$8,IF('I_Budget Input Data'!$E$7="Front-loaded",IF(12<='I_Inputs & Assumptions'!$B$8/2,'I_Budget Input Data'!$D$7*0.6/('I_Inputs & Assumptions'!$B$8/2),'I_Budget Input Data'!$D$7*0.4/('I_Inputs & Assumptions'!$B$8/2)),IF('I_Budget Input Data'!$E$7="Back-loaded",IF(12<='I_Inputs & Assumptions'!$B$8/2,'I_Budget Input Data'!$D$7*0.4/('I_Inputs & Assumptions'!$B$8/2),'I_Budget Input Data'!$D$7*0.6/('I_Inputs & Assumptions'!$B$8/2)),IF('I_Budget Input Data'!$E$7="Mid-weighted",IF(12<='I_Inputs & Assumptions'!$B$8/4,'I_Budget Input Data'!$D$7*0.2/('I_Inputs & Assumptions'!$B$8/4),IF(12<='I_Inputs & Assumptions'!$B$8*0.75,'I_Budget Input Data'!$D$7*0.6/('I_Inputs & Assumptions'!$B$8/2),'I_Budget Input Data'!$D$7*0.2/('I_Inputs & Assumptions'!$B$8/4))),IF('I_Budget Input Data'!$E$7="At Completion",IF(12='I_Inputs & Assumptions'!$B$8,'I_Budget Input Data'!$D$7,0),'I_Budget Input Data'!$D$7/'I_Inputs & Assumptions'!$B$8)))))),0) -> 0 | O7: =IF(13<='I_Inputs & Assumptions'!$B$8,IF('I_Budget Input Data'!$E$7="Upfront",IF(13=1,'I_Budget Input Data'!$D$7,0),IF('I_Budget Input Data'!$E$7="Equal",'I_Budget Input Data'!$D$7/'I_Inputs & Assumptions'!$B$8,IF('I_Budget Input Data'!$E$7="Front-loaded",IF(13<='I_Inputs & Assumptions'!$B$8/2,'I_Budget Input Data'!$D$7*0.6/('I_Inputs & Assumptions'!$B$8/2),'I_Budget Input Data'!$D$7*0.4/('I_Inputs & Assumptions'!$B$8/2)),IF('I_Budget Input Data'!$E$7="Back-loaded",IF(13<='I_Inputs & Assumptions'!$B$8/2,'I_Budget Input Data'!$D$7*0.4/('I_Inputs & Assumptions'!$B$8/2),'I_Budget Input Data'!$D$7*0.6/('I_Inputs & Assumptions'!$B$8/2)),IF('I_Budget Input Data'!$E$7="Mid-weighted",IF(13<='I_Inputs & Assumptions'!$B$8/4,'I_Budget Input Data'!$D$7*0.2/('I_Inputs & Assumptions'!$B$8/4),IF(13<='I_Inputs & Assumptions'!$B$8*0.75,'I_Budget Input Data'!$D$7*0.6/('I_Inputs & Assumptions'!$B$8/2),'I_Budget Input Data'!$D$7*0.2/('I_Inputs & Assumptions'!$B$8/4))),IF('I_Budget Input Data'!$E$7="At Completion",IF(13='I_Inputs & Assumptions'!$B$8,'I_Budget Input Data'!$D$7,0),'I_Budget Input Data'!$D$7/'I_Inputs & Assumptions'!$B$8)))))),0) -> 0 | P7: =IF(14<='I_Inputs & Assumptions'!$B$8,IF('I_Budget Input Data'!$E$7="Upfront",IF(14=1,'I_Budget Input Data'!$D$7,0),IF('I_Budget Input Data'!$E$7="Equal",'I_Budget Input Data'!$D$7/'I_Inputs & Assumptions'!$B$8,IF('I_Budget Input Data'!$E$7="Front-loaded",IF(14<='I_Inputs & Assumptions'!$B$8/2,'I_Budget Input Data'!$D$7*0.6/('I_Inputs & Assumptions'!$B$8/2),'I_Budget Input Data'!$D$7*0.4/('I_Inputs & Assumptions'!$B$8/2)),IF('I_Budget Input Data'!$E$7="Back-loaded",IF(14<='I_Inputs & Assumptions'!$B$8/2,'I_Budget Input Data'!$D$7*0.4/('I_Inputs & Assumptions'!$B$8/2),'I_Budget Input Data'!$D$7*0.6/('I_Inputs & Assumptions'!$B$8/2)),IF('I_Budget Input Data'!$E$7="Mid-weighted",IF(14<='I_Inputs & Assumptions'!$B$8/4,'I_Budget Input Data'!$D$7*0.2/('I_Inputs & Assumptions'!$B$8/4),IF(14<='I_Inputs & Assumptions'!$B$8*0.75,'I_Budget Input Data'!$D$7*0.6/('I_Inputs & Assumptions'!$B$8/2),'I_Budget Input Data'!$D$7*0.2/('I_Inputs & Assumptions'!$B$8/4))),IF('I_Budget Input Data'!$E$7="At Completion",IF(14='I_Inputs & Assumptions'!$B$8,'I_Budget Input Data'!$D$7,0),'I_Budget Input Data'!$D$7/'I_Inputs & Assumptions'!$B$8)))))),0) -> 0 | Q7: =IF(15<='I_Inputs & Assumptions'!$B$8,IF('I_Budget Input Data'!$E$7="Upfront",IF(15=1,'I_Budget Input Data'!$D$7,0),IF('I_Budget Input Data'!$E$7="Equal",'I_Budget Input Data'!$D$7/'I_Inputs & Assumptions'!$B$8,IF('I_Budget Input Data'!$E$7="Front-loaded",IF(15<='I_Inputs & Assumptions'!$B$8/2,'I_Budget Input Data'!$D$7*0.6/('I_Inputs & Assumptions'!$B$8/2),'I_Budget Input Data'!$D$7*0.4/('I_Inputs & Assumptions'!$B$8/2)),IF('I_Budget Input Data'!$E$7="Back-loaded",IF(15<='I_Inputs & Assumptions'!$B$8/2,'I_Budget Input Data'!$D$7*0.4/('I_Inputs & Assumptions'!$B$8/2),'I_Budget Input Data'!$D$7*0.6/('I_Inputs & Assumptions'!$B$8/2)),IF('I_Budget Input Data'!$E$7="Mid-weighted",IF(15<='I_Inputs & Assumptions'!$B$8/4,'I_Budget Input Data'!$D$7*0.2/('I_Inputs & Assumptions'!$B$8/4),IF(15<='I_Inputs & Assumptions'!$B$8*0.75,'I_Budget Input Data'!$D$7*0.6/('I_Inputs & Assumptions'!$B$8/2),'I_Budget Input Data'!$D$7*0.2/('I_Inputs & Assumptions'!$B$8/4))),IF('I_Budget Input Data'!$E$7="At Completion",IF(15='I_Inputs & Assumptions'!$B$8,'I_Budget Input Data'!$D$7,0),'I_Budget Input Data'!$D$7/'I_Inputs & Assumptions'!$B$8)))))),0) -> 0 | R7: =IF(16<='I_Inputs & Assumptions'!$B$8,IF('I_Budget Input Data'!$E$7="Upfront",IF(16=1,'I_Budget Input Data'!$D$7,0),IF('I_Budget Input Data'!$E$7="Equal",'I_Budget Input Data'!$D$7/'I_Inputs & Assumptions'!$B$8,IF('I_Budget Input Data'!$E$7="Front-loaded",IF(16<='I_Inputs & Assumptions'!$B$8/2,'I_Budget Input Data'!$D$7*0.6/('I_Inputs & Assumptions'!$B$8/2),'I_Budget Input Data'!$D$7*0.4/('I_Inputs & Assumptions'!$B$8/2)),IF('I_Budget Input Data'!$E$7="Back-loaded",IF(16<='I_Inputs & Assumptions'!$B$8/2,'I_Budget Input Data'!$D$7*0.4/('I_Inputs & Assumptions'!$B$8/2),'I_Budget Input Data'!$D$7*0.6/('I_Inputs & Assumptions'!$B$8/2)),IF('I_Budget Input Data'!$E$7="Mid-weighted",IF(16<='I_Inputs & Assumptions'!$B$8/4,'I_Budget Input Data'!$D$7*0.2/('I_Inputs & Assumptions'!$B$8/4),IF(16<='I_Inputs & Assumptions'!$B$8*0.75,'I_Budget Input Data'!$D$7*0.6/('I_Inputs & Assumptions'!$B$8/2),'I_Budget Input Data'!$D$7*0.2/('I_Inputs & Assumptions'!$B$8/4))),IF('I_Budget Input Data'!$E$7="At Completion",IF(16='I_Inputs & Assumptions'!$B$8,'I_Budget Input Data'!$D$7,0),'I_Budget Input Data'!$D$7/'I_Inputs & Assumptions'!$B$8)))))),0) -> 0 | S7: =IF(17<='I_Inputs & Assumptions'!$B$8,IF('I_Budget Input Data'!$E$7="Upfront",IF(17=1,'I_Budget Input Data'!$D$7,0),IF('I_Budget Input Data'!$E$7="Equal",'I_Budget Input Data'!$D$7/'I_Inputs & Assumptions'!$B$8,IF('I_Budget Input Data'!$E$7="Front-loaded",IF(17<='I_Inputs & Assumptions'!$B$8/2,'I_Budget Input Data'!$D$7*0.6/('I_Inputs & Assumptions'!$B$8/2),'I_Budget Input Data'!$D$7*0.4/('I_Inputs & Assumptions'!$B$8/2)),IF('I_Budget Input Data'!$E$7="Back-loaded",IF(17<='I_Inputs & Assumptions'!$B$8/2,'I_Budget Input Data'!$D$7*0.4/('I_Inputs & Assumptions'!$B$8/2),'I_Budget Input Data'!$D$7*0.6/('I_Inputs & Assumptions'!$B$8/2)),IF('I_Budget Input Data'!$E$7="Mid-weighted",IF(17<='I_Inputs & Assumptions'!$B$8/4,'I_Budget Input Data'!$D$7*0.2/('I_Inputs & Assumptions'!$B$8/4),IF(17<='I_Inputs & Assumptions'!$B$8*0.75,'I_Budget Input Data'!$D$7*0.6/('I_Inputs & Assumptions'!$B$8/2),'I_Budget Input Data'!$D$7*0.2/('I_Inputs & Assumptions'!$B$8/4))),IF('I_Budget Input Data'!$E$7="At Completion",IF(17='I_Inputs & Assumptions'!$B$8,'I_Budget Input Data'!$D$7,0),'I_Budget Input Data'!$D$7/'I_Inputs & Assumptions'!$B$8)))))),0) -> 0 | T7: =IF(18<='I_Inputs & Assumptions'!$B$8,IF('I_Budget Input Data'!$E$7="Upfront",IF(18=1,'I_Budget Input Data'!$D$7,0),IF('I_Budget Input Data'!$E$7="Equal",'I_Budget Input Data'!$D$7/'I_Inputs & Assumptions'!$B$8,IF('I_Budget Input Data'!$E$7="Front-loaded",IF(18<='I_Inputs & Assumptions'!$B$8/2,'I_Budget Input Data'!$D$7*0.6/('I_Inputs & Assumptions'!$B$8/2),'I_Budget Input Data'!$D$7*0.4/('I_Inputs & Assumptions'!$B$8/2)),IF('I_Budget Input Data'!$E$7="Back-loaded",IF(18<='I_Inputs & Assumptions'!$B$8/2,'I_Budget Input Data'!$D$7*0.4/('I_Inputs & Assumptions'!$B$8/2),'I_Budget Input Data'!$D$7*0.6/('I_Inputs & Assumptions'!$B$8/2)),IF('I_Budget Input Data'!$E$7="Mid-weighted",IF(18<='I_Inputs & Assumptions'!$B$8/4,'I_Budget Input Data'!$D$7*0.2/('I_Inputs & Assumptions'!$B$8/4),IF(18<='I_Inputs & Assumptions'!$B$8*0.75,'I_Budget Input Data'!$D$7*0.6/('I_Inputs & Assumptions'!$B$8/2),'I_Budget Input Data'!$D$7*0.2/('I_Inputs & Assumptions'!$B$8/4))),IF('I_Budget Input Data'!$E$7="At Completion",IF(18='I_Inputs & Assumptions'!$B$8,'I_Budget Input Data'!$D$7,0),'I_Budget Input Data'!$D$7/'I_Inputs & Assumptions'!$B$8)))))),0) -> 0 | U7: =IF(19<='I_Inputs & Assumptions'!$B$8,IF('I_Budget Input Data'!$E$7="Upfront",IF(19=1,'I_Budget Input Data'!$D$7,0),IF('I_Budget Input Data'!$E$7="Equal",'I_Budget Input Data'!$D$7/'I_Inputs & Assumptions'!$B$8,IF('I_Budget Input Data'!$E$7="Front-loaded",IF(19<='I_Inputs & Assumptions'!$B$8/2,'I_Budget Input Data'!$D$7*0.6/('I_Inputs & Assumptions'!$B$8/2),'I_Budget Input Data'!$D$7*0.4/('I_Inputs & Assumptions'!$B$8/2)),IF('I_Budget Input Data'!$E$7="Back-loaded",IF(19<='I_Inputs & Assumptions'!$B$8/2,'I_Budget Input Data'!$D$7*0.4/('I_Inputs & Assumptions'!$B$8/2),'I_Budget Input Data'!$D$7*0.6/('I_Inputs & Assumptions'!$B$8/2)),IF('I_Budget Input Data'!$E$7="Mid-weighted",IF(19<='I_Inputs & Assumptions'!$B$8/4,'I_Budget Input Data'!$D$7*0.2/('I_Inputs & Assumptions'!$B$8/4),IF(19<='I_Inputs & Assumptions'!$B$8*0.75,'I_Budget Input Data'!$D$7*0.6/('I_Inputs & Assumptions'!$B$8/2),'I_Budget Input Data'!$D$7*0.2/('I_Inputs & Assumptions'!$B$8/4))),IF('I_Budget Input Data'!$E$7="At Completion",IF(19='I_Inputs & Assumptions'!$B$8,'I_Budget Input Data'!$D$7,0),'I_Budget Input Data'!$D$7/'I_Inputs & Assumptions'!$B$8)))))),0) -> 0 | V7: =IF(20<='I_Inputs & Assumptions'!$B$8,IF('I_Budget Input Data'!$E$7="Upfront",IF(20=1,'I_Budget Input Data'!$D$7,0),IF('I_Budget Input Data'!$E$7="Equal",'I_Budget Input Data'!$D$7/'I_Inputs & Assumptions'!$B$8,IF('I_Budget Input Data'!$E$7="Front-loaded",IF(20<='I_Inputs & Assumptions'!$B$8/2,'I_Budget Input Data'!$D$7*0.6/('I_Inputs & Assumptions'!$B$8/2),'I_Budget Input Data'!$D$7*0.4/('I_Inputs & Assumptions'!$B$8/2)),IF('I_Budget Input Data'!$E$7="Back-loaded",IF(20<='I_Inputs & Assumptions'!$B$8/2,'I_Budget Input Data'!$D$7*0.4/('I_Inputs & Assumptions'!$B$8/2),'I_Budget Input Data'!$D$7*0.6/('I_Inputs & Assumptions'!$B$8/2)),IF('I_Budget Input Data'!$E$7="Mid-weighted",IF(20<='I_Inputs & Assumptions'!$B$8/4,'I_Budget Input Data'!$D$7*0.2/('I_Inputs & Assumptions'!$B$8/4),IF(20<='I_Inputs & Assumptions'!$B$8*0.75,'I_Budget Input Data'!$D$7*0.6/('I_Inputs & Assumptions'!$B$8/2),'I_Budget Input Data'!$D$7*0.2/('I_Inputs & Assumptions'!$B$8/4))),IF('I_Budget Input Data'!$E$7="At Completion",IF(20='I_Inputs & Assumptions'!$B$8,'I_Budget Input Data'!$D$7,0),'I_Budget Input Data'!$D$7/'I_Inputs & Assumptions'!$B$8)))))),0) -> 0 | W7: =IF(21<='I_Inputs & Assumptions'!$B$8,IF('I_Budget Input Data'!$E$7="Upfront",IF(21=1,'I_Budget Input Data'!$D$7,0),IF('I_Budget Input Data'!$E$7="Equal",'I_Budget Input Data'!$D$7/'I_Inputs & Assumptions'!$B$8,IF('I_Budget Input Data'!$E$7="Front-loaded",IF(21<='I_Inputs & Assumptions'!$B$8/2,'I_Budget Input Data'!$D$7*0.6/('I_Inputs & Assumptions'!$B$8/2),'I_Budget Input Data'!$D$7*0.4/('I_Inputs & Assumptions'!$B$8/2)),IF('I_Budget Input Data'!$E$7="Back-loaded",IF(21<='I_Inputs & Assumptions'!$B$8/2,'I_Budget Input Data'!$D$7*0.4/('I_Inputs & Assumptions'!$B$8/2),'I_Budget Input Data'!$D$7*0.6/('I_Inputs & Assumptions'!$B$8/2)),IF('I_Budget Input Data'!$E$7="Mid-weighted",IF(21<='I_Inputs & Assumptions'!$B$8/4,'I_Budget Input Data'!$D$7*0.2/('I_Inputs & Assumptions'!$B$8/4),IF(21<='I_Inputs & Assumptions'!$B$8*0.75,'I_Budget Input Data'!$D$7*0.6/('I_Inputs & Assumptions'!$B$8/2),'I_Budget Input Data'!$D$7*0.2/('I_Inputs & Assumptions'!$B$8/4))),IF('I_Budget Input Data'!$E$7="At Completion",IF(21='I_Inputs & Assumptions'!$B$8,'I_Budget Input Data'!$D$7,0),'I_Budget Input Data'!$D$7/'I_Inputs & Assumptions'!$B$8)))))),0) -> 0 | X7: =IF(22<='I_Inputs & Assumptions'!$B$8,IF('I_Budget Input Data'!$E$7="Upfront",IF(22=1,'I_Budget Input Data'!$D$7,0),IF('I_Budget Input Data'!$E$7="Equal",'I_Budget Input Data'!$D$7/'I_Inputs & Assumptions'!$B$8,IF('I_Budget Input Data'!$E$7="Front-loaded",IF(22<='I_Inputs & Assumptions'!$B$8/2,'I_Budget Input Data'!$D$7*0.6/('I_Inputs & Assumptions'!$B$8/2),'I_Budget Input Data'!$D$7*0.4/('I_Inputs & Assumptions'!$B$8/2)),IF('I_Budget Input Data'!$E$7="Back-loaded",IF(22<='I_Inputs & Assumptions'!$B$8/2,'I_Budget Input Data'!$D$7*0.4/('I_Inputs & Assumptions'!$B$8/2),'I_Budget Input Data'!$D$7*0.6/('I_Inputs & Assumptions'!$B$8/2)),IF('I_Budget Input Data'!$E$7="Mid-weighted",IF(22<='I_Inputs & Assumptions'!$B$8/4,'I_Budget Input Data'!$D$7*0.2/('I_Inputs & Assumptions'!$B$8/4),IF(22<='I_Inputs & Assumptions'!$B$8*0.75,'I_Budget Input Data'!$D$7*0.6/('I_Inputs & Assumptions'!$B$8/2),'I_Budget Input Data'!$D$7*0.2/('I_Inputs & Assumptions'!$B$8/4))),IF('I_Budget Input Data'!$E$7="At Completion",IF(22='I_Inputs & Assumptions'!$B$8,'I_Budget Input Data'!$D$7,0),'I_Budget Input Data'!$D$7/'I_Inputs & Assumptions'!$B$8)))))),0) -> 0 | Y7: =IF(23<='I_Inputs & Assumptions'!$B$8,IF('I_Budget Input Data'!$E$7="Upfront",IF(23=1,'I_Budget Input Data'!$D$7,0),IF('I_Budget Input Data'!$E$7="Equal",'I_Budget Input Data'!$D$7/'I_Inputs & Assumptions'!$B$8,IF('I_Budget Input Data'!$E$7="Front-loaded",IF(23<='I_Inputs & Assumptions'!$B$8/2,'I_Budget Input Data'!$D$7*0.6/('I_Inputs & Assumptions'!$B$8/2),'I_Budget Input Data'!$D$7*0.4/('I_Inputs & Assumptions'!$B$8/2)),IF('I_Budget Input Data'!$E$7="Back-loaded",IF(23<='I_Inputs & Assumptions'!$B$8/2,'I_Budget Input Data'!$D$7*0.4/('I_Inputs & Assumptions'!$B$8/2),'I_Budget Input Data'!$D$7*0.6/('I_Inputs & Assumptions'!$B$8/2)),IF('I_Budget Input Data'!$E$7="Mid-weighted",IF(23<='I_Inputs & Assumptions'!$B$8/4,'I_Budget Input Data'!$D$7*0.2/('I_Inputs & Assumptions'!$B$8/4),IF(23<='I_Inputs & Assumptions'!$B$8*0.75,'I_Budget Input Data'!$D$7*0.6/('I_Inputs & Assumptions'!$B$8/2),'I_Budget Input Data'!$D$7*0.2/('I_Inputs & Assumptions'!$B$8/4))),IF('I_Budget Input Data'!$E$7="At Completion",IF(23='I_Inputs & Assumptions'!$B$8,'I_Budget Input Data'!$D$7,0),'I_Budget Input Data'!$D$7/'I_Inputs & Assumptions'!$B$8)))))),0) -> 0 | Z7: =IF(24<='I_Inputs & Assumptions'!$B$8,IF('I_Budget Input Data'!$E$7="Upfront",IF(24=1,'I_Budget Input Data'!$D$7,0),IF('I_Budget Input Data'!$E$7="Equal",'I_Budget Input Data'!$D$7/'I_Inputs & Assumptions'!$B$8,IF('I_Budget Input Data'!$E$7="Front-loaded",IF(24<='I_Inputs & Assumptions'!$B$8/2,'I_Budget Input Data'!$D$7*0.6/('I_Inputs & Assumptions'!$B$8/2),'I_Budget Input Data'!$D$7*0.4/('I_Inputs & Assumptions'!$B$8/2)),IF('I_Budget Input Data'!$E$7="Back-loaded",IF(24<='I_Inputs & Assumptions'!$B$8/2,'I_Budget Input Data'!$D$7*0.4/('I_Inputs & Assumptions'!$B$8/2),'I_Budget Input Data'!$D$7*0.6/('I_Inputs & Assumptions'!$B$8/2)),IF('I_Budget Input Data'!$E$7="Mid-weighted",IF(24<='I_Inputs & Assumptions'!$B$8/4,'I_Budget Input Data'!$D$7*0.2/('I_Inputs & Assumptions'!$B$8/4),IF(24<='I_Inputs & Assumptions'!$B$8*0.75,'I_Budget Input Data'!$D$7*0.6/('I_Inputs & Assumptions'!$B$8/2),'I_Budget Input Data'!$D$7*0.2/('I_Inputs & Assumptions'!$B$8/4))),IF('I_Budget Input Data'!$E$7="At Completion",IF(24='I_Inputs & Assumptions'!$B$8,'I_Budget Input Data'!$D$7,0),'I_Budget Input Data'!$D$7/'I_Inputs & Assumptions'!$B$8)))))),0) -> 0 | AA7: =IF(25<='I_Inputs & Assumptions'!$B$8,IF('I_Budget Input Data'!$E$7="Upfront",IF(25=1,'I_Budget Input Data'!$D$7,0),IF('I_Budget Input Data'!$E$7="Equal",'I_Budget Input Data'!$D$7/'I_Inputs & Assumptions'!$B$8,IF('I_Budget Input Data'!$E$7="Front-loaded",IF(25<='I_Inputs & Assumptions'!$B$8/2,'I_Budget Input Data'!$D$7*0.6/('I_Inputs & Assumptions'!$B$8/2),'I_Budget Input Data'!$D$7*0.4/('I_Inputs & Assumptions'!$B$8/2)),IF('I_Budget Input Data'!$E$7="Back-loaded",IF(25<='I_Inputs & Assumptions'!$B$8/2,'I_Budget Input Data'!$D$7*0.4/('I_Inputs & Assumptions'!$B$8/2),'I_Budget Input Data'!$D$7*0.6/('I_Inputs & Assumptions'!$B$8/2)),IF('I_Budget Input Data'!$E$7="Mid-weighted",IF(25<='I_Inputs & Assumptions'!$B$8/4,'I_Budget Input Data'!$D$7*0.2/('I_Inputs & Assumptions'!$B$8/4),IF(25<='I_Inputs & Assumptions'!$B$8*0.75,'I_Budget Input Data'!$D$7*0.6/('I_Inputs & Assumptions'!$B$8/2),'I_Budget Input Data'!$D$7*0.2/('I_Inputs & Assumptions'!$B$8/4))),IF('I_Budget Input Data'!$E$7="At Completion",IF(25='I_Inputs & Assumptions'!$B$8,'I_Budget Input Data'!$D$7,0),'I_Budget Input Data'!$D$7/'I_Inputs & Assumptions'!$B$8)))))),0) -> 0 | AB7: =IF(26<='I_Inputs & Assumptions'!$B$8,IF('I_Budget Input Data'!$E$7="Upfront",IF(26=1,'I_Budget Input Data'!$D$7,0),IF('I_Budget Input Data'!$E$7="Equal",'I_Budget Input Data'!$D$7/'I_Inputs & Assumptions'!$B$8,IF('I_Budget Input Data'!$E$7="Front-loaded",IF(26<='I_Inputs & Assumptions'!$B$8/2,'I_Budget Input Data'!$D$7*0.6/('I_Inputs & Assumptions'!$B$8/2),'I_Budget Input Data'!$D$7*0.4/('I_Inputs & Assumptions'!$B$8/2)),IF('I_Budget Input Data'!$E$7="Back-loaded",IF(26<='I_Inputs & Assumptions'!$B$8/2,'I_Budget Input Data'!$D$7*0.4/('I_Inputs & Assumptions'!$B$8/2),'I_Budget Input Data'!$D$7*0.6/('I_Inputs & Assumptions'!$B$8/2)),IF('I_Budget Input Data'!$E$7="Mid-weighted",IF(26<='I_Inputs & Assumptions'!$B$8/4,'I_Budget Input Data'!$D$7*0.2/('I_Inputs & Assumptions'!$B$8/4),IF(26<='I_Inputs & Assumptions'!$B$8*0.75,'I_Budget Input Data'!$D$7*0.6/('I_Inputs & Assumptions'!$B$8/2),'I_Budget Input Data'!$D$7*0.2/('I_Inputs & Assumptions'!$B$8/4))),IF('I_Budget Input Data'!$E$7="At Completion",IF(26='I_Inputs & Assumptions'!$B$8,'I_Budget Input Data'!$D$7,0),'I_Budget Input Data'!$D$7/'I_Inputs & Assumptions'!$B$8)))))),0) -> 0 | AC7: =IF(27<='I_Inputs & Assumptions'!$B$8,IF('I_Budget Input Data'!$E$7="Upfront",IF(27=1,'I_Budget Input Data'!$D$7,0),IF('I_Budget Input Data'!$E$7="Equal",'I_Budget Input Data'!$D$7/'I_Inputs & Assumptions'!$B$8,IF('I_Budget Input Data'!$E$7="Front-loaded",IF(27<='I_Inputs & Assumptions'!$B$8/2,'I_Budget Input Data'!$D$7*0.6/('I_Inputs & Assumptions'!$B$8/2),'I_Budget Input Data'!$D$7*0.4/('I_Inputs & Assumptions'!$B$8/2)),IF('I_Budget Input Data'!$E$7="Back-loaded",IF(27<='I_Inputs & Assumptions'!$B$8/2,'I_Budget Input Data'!$D$7*0.4/('I_Inputs & Assumptions'!$B$8/2),'I_Budget Input Data'!$D$7*0.6/('I_Inputs & Assumptions'!$B$8/2)),IF('I_Budget Input Data'!$E$7="Mid-weighted",IF(27<='I_Inputs & Assumptions'!$B$8/4,'I_Budget Input Data'!$D$7*0.2/('I_Inputs & Assumptions'!$B$8/4),IF(27<='I_Inputs & Assumptions'!$B$8*0.75,'I_Budget Input Data'!$D$7*0.6/('I_Inputs & Assumptions'!$B$8/2),'I_Budget Input Data'!$D$7*0.2/('I_Inputs & Assumptions'!$B$8/4))),IF('I_Budget Input Data'!$E$7="At Completion",IF(27='I_Inputs & Assumptions'!$B$8,'I_Budget Input Data'!$D$7,0),'I_Budget Input Data'!$D$7/'I_Inputs & Assumptions'!$B$8)))))),0) -> 0 | AD7: =IF(28<='I_Inputs & Assumptions'!$B$8,IF('I_Budget Input Data'!$E$7="Upfront",IF(28=1,'I_Budget Input Data'!$D$7,0),IF('I_Budget Input Data'!$E$7="Equal",'I_Budget Input Data'!$D$7/'I_Inputs & Assumptions'!$B$8,IF('I_Budget Input Data'!$E$7="Front-loaded",IF(28<='I_Inputs & Assumptions'!$B$8/2,'I_Budget Input Data'!$D$7*0.6/('I_Inputs & Assumptions'!$B$8/2),'I_Budget Input Data'!$D$7*0.4/('I_Inputs & Assumptions'!$B$8/2)),IF('I_Budget Input Data'!$E$7="Back-loaded",IF(28<='I_Inputs & Assumptions'!$B$8/2,'I_Budget Input Data'!$D$7*0.4/('I_Inputs & Assumptions'!$B$8/2),'I_Budget Input Data'!$D$7*0.6/('I_Inputs & Assumptions'!$B$8/2)),IF('I_Budget Input Data'!$E$7="Mid-weighted",IF(28<='I_Inputs & Assumptions'!$B$8/4,'I_Budget Input Data'!$D$7*0.2/('I_Inputs & Assumptions'!$B$8/4),IF(28<='I_Inputs & Assumptions'!$B$8*0.75,'I_Budget Input Data'!$D$7*0.6/('I_Inputs & Assumptions'!$B$8/2),'I_Budget Input Data'!$D$7*0.2/('I_Inputs & Assumptions'!$B$8/4))),IF('I_Budget Input Data'!$E$7="At Completion",IF(28='I_Inputs & Assumptions'!$B$8,'I_Budget Input Data'!$D$7,0),'I_Budget Input Data'!$D$7/'I_Inputs & Assumptions'!$B$8)))))),0) -> 0 | AE7: =IF(29<='I_Inputs & Assumptions'!$B$8,IF('I_Budget Input Data'!$E$7="Upfront",IF(29=1,'I_Budget Input Data'!$D$7,0),IF('I_Budget Input Data'!$E$7="Equal",'I_Budget Input Data'!$D$7/'I_Inputs & Assumptions'!$B$8,IF('I_Budget Input Data'!$E$7="Front-loaded",IF(29<='I_Inputs & Assumptions'!$B$8/2,'I_Budget Input Data'!$D$7*0.6/('I_Inputs & Assumptions'!$B$8/2),'I_Budget Input Data'!$D$7*0.4/('I_Inputs & Assumptions'!$B$8/2)),IF('I_Budget Input Data'!$E$7="Back-loaded",IF(29<='I_Inputs & Assumptions'!$B$8/2,'I_Budget Input Data'!$D$7*0.4/('I_Inputs & Assumptions'!$B$8/2),'I_Budget Input Data'!$D$7*0.6/('I_Inputs & Assumptions'!$B$8/2)),IF('I_Budget Input Data'!$E$7="Mid-weighted",IF(29<='I_Inputs & Assumptions'!$B$8/4,'I_Budget Input Data'!$D$7*0.2/('I_Inputs & Assumptions'!$B$8/4),IF(29<='I_Inputs & Assumptions'!$B$8*0.75,'I_Budget Input Data'!$D$7*0.6/('I_Inputs & Assumptions'!$B$8/2),'I_Budget Input Data'!$D$7*0.2/('I_Inputs & Assumptions'!$B$8/4))),IF('I_Budget Input Data'!$E$7="At Completion",IF(29='I_Inputs & Assumptions'!$B$8,'I_Budget Input Data'!$D$7,0),'I_Budget Input Data'!$D$7/'I_Inputs & Assumptions'!$B$8)))))),0) -> 0 | AF7: =IF(30<='I_Inputs & Assumptions'!$B$8,IF('I_Budget Input Data'!$E$7="Upfront",IF(30=1,'I_Budget Input Data'!$D$7,0),IF('I_Budget Input Data'!$E$7="Equal",'I_Budget Input Data'!$D$7/'I_Inputs & Assumptions'!$B$8,IF('I_Budget Input Data'!$E$7="Front-loaded",IF(30<='I_Inputs & Assumptions'!$B$8/2,'I_Budget Input Data'!$D$7*0.6/('I_Inputs & Assumptions'!$B$8/2),'I_Budget Input Data'!$D$7*0.4/('I_Inputs & Assumptions'!$B$8/2)),IF('I_Budget Input Data'!$E$7="Back-loaded",IF(30<='I_Inputs & Assumptions'!$B$8/2,'I_Budget Input Data'!$D$7*0.4/('I_Inputs & Assumptions'!$B$8/2),'I_Budget Input Data'!$D$7*0.6/('I_Inputs & Assumptions'!$B$8/2)),IF('I_Budget Input Data'!$E$7="Mid-weighted",IF(30<='I_Inputs & Assumptions'!$B$8/4,'I_Budget Input Data'!$D$7*0.2/('I_Inputs & Assumptions'!$B$8/4),IF(30<='I_Inputs & Assumptions'!$B$8*0.75,'I_Budget Input Data'!$D$7*0.6/('I_Inputs & Assumptions'!$B$8/2),'I_Budget Input Data'!$D$7*0.2/('I_Inputs & Assumptions'!$B$8/4))),IF('I_Budget Input Data'!$E$7="At Completion",IF(30='I_Inputs & Assumptions'!$B$8,'I_Budget Input Data'!$D$7,0),'I_Budget Input Data'!$D$7/'I_Inputs & Assumptions'!$B$8)))))),0) -> 0 | AG7: =IF(31<='I_Inputs & Assumptions'!$B$8,IF('I_Budget Input Data'!$E$7="Upfront",IF(31=1,'I_Budget Input Data'!$D$7,0),IF('I_Budget Input Data'!$E$7="Equal",'I_Budget Input Data'!$D$7/'I_Inputs & Assumptions'!$B$8,IF('I_Budget Input Data'!$E$7="Front-loaded",IF(31<='I_Inputs & Assumptions'!$B$8/2,'I_Budget Input Data'!$D$7*0.6/('I_Inputs & Assumptions'!$B$8/2),'I_Budget Input Data'!$D$7*0.4/('I_Inputs & Assumptions'!$B$8/2)),IF('I_Budget Input Data'!$E$7="Back-loaded",IF(31<='I_Inputs & Assumptions'!$B$8/2,'I_Budget Input Data'!$D$7*0.4/('I_Inputs & Assumptions'!$B$8/2),'I_Budget Input Data'!$D$7*0.6/('I_Inputs & Assumptions'!$B$8/2)),IF('I_Budget Input Data'!$E$7="Mid-weighted",IF(31<='I_Inputs & Assumptions'!$B$8/4,'I_Budget Input Data'!$D$7*0.2/('I_Inputs & Assumptions'!$B$8/4),IF(31<='I_Inputs & Assumptions'!$B$8*0.75,'I_Budget Input Data'!$D$7*0.6/('I_Inputs & Assumptions'!$B$8/2),'I_Budget Input Data'!$D$7*0.2/('I_Inputs & Assumptions'!$B$8/4))),IF('I_Budget Input Data'!$E$7="At Completion",IF(31='I_Inputs & Assumptions'!$B$8,'I_Budget Input Data'!$D$7,0),'I_Budget Input Data'!$D$7/'I_Inputs & Assumptions'!$B$8)))))),0) -> 0 | AH7: =IF(32<='I_Inputs & Assumptions'!$B$8,IF('I_Budget Input Data'!$E$7="Upfront",IF(32=1,'I_Budget Input Data'!$D$7,0),IF('I_Budget Input Data'!$E$7="Equal",'I_Budget Input Data'!$D$7/'I_Inputs & Assumptions'!$B$8,IF('I_Budget Input Data'!$E$7="Front-loaded",IF(32<='I_Inputs & Assumptions'!$B$8/2,'I_Budget Input Data'!$D$7*0.6/('I_Inputs & Assumptions'!$B$8/2),'I_Budget Input Data'!$D$7*0.4/('I_Inputs & Assumptions'!$B$8/2)),IF('I_Budget Input Data'!$E$7="Back-loaded",IF(32<='I_Inputs & Assumptions'!$B$8/2,'I_Budget Input Data'!$D$7*0.4/('I_Inputs & Assumptions'!$B$8/2),'I_Budget Input Data'!$D$7*0.6/('I_Inputs & Assumptions'!$B$8/2)),IF('I_Budget Input Data'!$E$7="Mid-weighted",IF(32<='I_Inputs & Assumptions'!$B$8/4,'I_Budget Input Data'!$D$7*0.2/('I_Inputs & Assumptions'!$B$8/4),IF(32<='I_Inputs & Assumptions'!$B$8*0.75,'I_Budget Input Data'!$D$7*0.6/('I_Inputs & Assumptions'!$B$8/2),'I_Budget Input Data'!$D$7*0.2/('I_Inputs & Assumptions'!$B$8/4))),IF('I_Budget Input Data'!$E$7="At Completion",IF(32='I_Inputs & Assumptions'!$B$8,'I_Budget Input Data'!$D$7,0),'I_Budget Input Data'!$D$7/'I_Inputs & Assumptions'!$B$8)))))),0) -> 0 | AI7: =IF(33<='I_Inputs & Assumptions'!$B$8,IF('I_Budget Input Data'!$E$7="Upfront",IF(33=1,'I_Budget Input Data'!$D$7,0),IF('I_Budget Input Data'!$E$7="Equal",'I_Budget Input Data'!$D$7/'I_Inputs & Assumptions'!$B$8,IF('I_Budget Input Data'!$E$7="Front-loaded",IF(33<='I_Inputs & Assumptions'!$B$8/2,'I_Budget Input Data'!$D$7*0.6/('I_Inputs & Assumptions'!$B$8/2),'I_Budget Input Data'!$D$7*0.4/('I_Inputs & Assumptions'!$B$8/2)),IF('I_Budget Input Data'!$E$7="Back-loaded",IF(33<='I_Inputs & Assumptions'!$B$8/2,'I_Budget Input Data'!$D$7*0.4/('I_Inputs & Assumptions'!$B$8/2),'I_Budget Input Data'!$D$7*0.6/('I_Inputs & Assumptions'!$B$8/2)),IF('I_Budget Input Data'!$E$7="Mid-weighted",IF(33<='I_Inputs & Assumptions'!$B$8/4,'I_Budget Input Data'!$D$7*0.2/('I_Inputs & Assumptions'!$B$8/4),IF(33<='I_Inputs & Assumptions'!$B$8*0.75,'I_Budget Input Data'!$D$7*0.6/('I_Inputs & Assumptions'!$B$8/2),'I_Budget Input Data'!$D$7*0.2/('I_Inputs & Assumptions'!$B$8/4))),IF('I_Budget Input Data'!$E$7="At Completion",IF(33='I_Inputs & Assumptions'!$B$8,'I_Budget Input Data'!$D$7,0),'I_Budget Input Data'!$D$7/'I_Inputs & Assumptions'!$B$8)))))),0) -> 0 | AJ7: =IF(34<='I_Inputs & Assumptions'!$B$8,IF('I_Budget Input Data'!$E$7="Upfront",IF(34=1,'I_Budget Input Data'!$D$7,0),IF('I_Budget Input Data'!$E$7="Equal",'I_Budget Input Data'!$D$7/'I_Inputs & Assumptions'!$B$8,IF('I_Budget Input Data'!$E$7="Front-loaded",IF(34<='I_Inputs & Assumptions'!$B$8/2,'I_Budget Input Data'!$D$7*0.6/('I_Inputs & Assumptions'!$B$8/2),'I_Budget Input Data'!$D$7*0.4/('I_Inputs & Assumptions'!$B$8/2)),IF('I_Budget Input Data'!$E$7="Back-loaded",IF(34<='I_Inputs & Assumptions'!$B$8/2,'I_Budget Input Data'!$D$7*0.4/('I_Inputs & Assumptions'!$B$8/2),'I_Budget Input Data'!$D$7*0.6/('I_Inputs & Assumptions'!$B$8/2)),IF('I_Budget Input Data'!$E$7="Mid-weighted",IF(34<='I_Inputs & Assumptions'!$B$8/4,'I_Budget Input Data'!$D$7*0.2/('I_Inputs & Assumptions'!$B$8/4),IF(34<='I_Inputs & Assumptions'!$B$8*0.75,'I_Budget Input Data'!$D$7*0.6/('I_Inputs & Assumptions'!$B$8/2),'I_Budget Input Data'!$D$7*0.2/('I_Inputs & Assumptions'!$B$8/4))),IF('I_Budget Input Data'!$E$7="At Completion",IF(34='I_Inputs & Assumptions'!$B$8,'I_Budget Input Data'!$D$7,0),'I_Budget Input Data'!$D$7/'I_Inputs & Assumptions'!$B$8)))))),0) -> 0 | AK7: =IF(35<='I_Inputs & Assumptions'!$B$8,IF('I_Budget Input Data'!$E$7="Upfront",IF(35=1,'I_Budget Input Data'!$D$7,0),IF('I_Budget Input Data'!$E$7="Equal",'I_Budget Input Data'!$D$7/'I_Inputs & Assumptions'!$B$8,IF('I_Budget Input Data'!$E$7="Front-loaded",IF(35<='I_Inputs & Assumptions'!$B$8/2,'I_Budget Input Data'!$D$7*0.6/('I_Inputs & Assumptions'!$B$8/2),'I_Budget Input Data'!$D$7*0.4/('I_Inputs & Assumptions'!$B$8/2)),IF('I_Budget Input Data'!$E$7="Back-loaded",IF(35<='I_Inputs & Assumptions'!$B$8/2,'I_Budget Input Data'!$D$7*0.4/('I_Inputs & Assumptions'!$B$8/2),'I_Budget Input Data'!$D$7*0.6/('I_Inputs & Assumptions'!$B$8/2)),IF('I_Budget Input Data'!$E$7="Mid-weighted",IF(35<='I_Inputs & Assumptions'!$B$8/4,'I_Budget Input Data'!$D$7*0.2/('I_Inputs & Assumptions'!$B$8/4),IF(35<='I_Inputs & Assumptions'!$B$8*0.75,'I_Budget Input Data'!$D$7*0.6/('I_Inputs & Assumptions'!$B$8/2),'I_Budget Input Data'!$D$7*0.2/('I_Inputs & Assumptions'!$B$8/4))),IF('I_Budget Input Data'!$E$7="At Completion",IF(35='I_Inputs & Assumptions'!$B$8,'I_Budget Input Data'!$D$7,0),'I_Budget Input Data'!$D$7/'I_Inputs & Assumptions'!$B$8)))))),0) -> 0 | AL7: =IF(36<='I_Inputs & Assumptions'!$B$8,IF('I_Budget Input Data'!$E$7="Upfront",IF(36=1,'I_Budget Input Data'!$D$7,0),IF('I_Budget Input Data'!$E$7="Equal",'I_Budget Input Data'!$D$7/'I_Inputs & Assumptions'!$B$8,IF('I_Budget Input Data'!$E$7="Front-loaded",IF(36<='I_Inputs & Assumptions'!$B$8/2,'I_Budget Input Data'!$D$7*0.6/('I_Inputs & Assumptions'!$B$8/2),'I_Budget Input Data'!$D$7*0.4/('I_Inputs & Assumptions'!$B$8/2)),IF('I_Budget Input Data'!$E$7="Back-loaded",IF(36<='I_Inputs & Assumptions'!$B$8/2,'I_Budget Input Data'!$D$7*0.4/('I_Inputs & Assumptions'!$B$8/2),'I_Budget Input Data'!$D$7*0.6/('I_Inputs & Assumptions'!$B$8/2)),IF('I_Budget Input Data'!$E$7="Mid-weighted",IF(36<='I_Inputs & Assumptions'!$B$8/4,'I_Budget Input Data'!$D$7*0.2/('I_Inputs & Assumptions'!$B$8/4),IF(36<='I_Inputs & Assumptions'!$B$8*0.75,'I_Budget Input Data'!$D$7*0.6/('I_Inputs & Assumptions'!$B$8/2),'I_Budget Input Data'!$D$7*0.2/('I_Inputs & Assumptions'!$B$8/4))),IF('I_Budget Input Data'!$E$7="At Completion",IF(36='I_Inputs & Assumptions'!$B$8,'I_Budget Input Data'!$D$7,0),'I_Budget Input Data'!$D$7/'I_Inputs & Assumptions'!$B$8)))))),0) -> 0
A8: 1. LAND | B8: Cadastral operation | C8: =IF(1<='I_Inputs & Assumptions'!$B$8,IF('I_Budget Input Data'!$E$8="Upfront",IF(1=1,'I_Budget Input Data'!$D$8,0),IF('I_Budget Input Data'!$E$8="Equal",'I_Budget Input Data'!$D$8/'I_Inputs & Assumptions'!$B$8,IF('I_Budget Input Data'!$E$8="Front-loaded",IF(1<='I_Inputs & Assumptions'!$B$8/2,'I_Budget Input Data'!$D$8*0.6/('I_Inputs & Assumptions'!$B$8/2),'I_Budget Input Data'!$D$8*0.4/('I_Inputs & Assumptions'!$B$8/2)),IF('I_Budget Input Data'!$E$8="Back-loaded",IF(1<='I_Inputs & Assumptions'!$B$8/2,'I_Budget Input Data'!$D$8*0.4/('I_Inputs & Assumptions'!$B$8/2),'I_Budget Input Data'!$D$8*0.6/('I_Inputs & Assumptions'!$B$8/2)),IF('I_Budget Input Data'!$E$8="Mid-weighted",IF(1<='I_Inputs & Assumptions'!$B$8/4,'I_Budget Input Data'!$D$8*0.2/('I_Inputs & Assumptions'!$B$8/4),IF(1<='I_Inputs & Assumptions'!$B$8*0.75,'I_Budget Input Data'!$D$8*0.6/('I_Inputs & Assumptions'!$B$8/2),'I_Budget Input Data'!$D$8*0.2/('I_Inputs & Assumptions'!$B$8/4))),IF('I_Budget Input Data'!$E$8="At Completion",IF(1='I_Inputs & Assumptions'!$B$8,'I_Budget Input Data'!$D$8,0),'I_Budget Input Data'!$D$8/'I_Inputs & Assumptions'!$B$8)))))),0) -> 105360 | D8: =IF(2<='I_Inputs & Assumptions'!$B$8,IF('I_Budget Input Data'!$E$8="Upfront",IF(2=1,'I_Budget Input Data'!$D$8,0),IF('I_Budget Input Data'!$E$8="Equal",'I_Budget Input Data'!$D$8/'I_Inputs & Assumptions'!$B$8,IF('I_Budget Input Data'!$E$8="Front-loaded",IF(2<='I_Inputs & Assumptions'!$B$8/2,'I_Budget Input Data'!$D$8*0.6/('I_Inputs & Assumptions'!$B$8/2),'I_Budget Input Data'!$D$8*0.4/('I_Inputs & Assumptions'!$B$8/2)),IF('I_Budget Input Data'!$E$8="Back-loaded",IF(2<='I_Inputs & Assumptions'!$B$8/2,'I_Budget Input Data'!$D$8*0.4/('I_Inputs & Assumptions'!$B$8/2),'I_Budget Input Data'!$D$8*0.6/('I_Inputs & Assumptions'!$B$8/2)),IF('I_Budget Input Data'!$E$8="Mid-weighted",IF(2<='I_Inputs & Assumptions'!$B$8/4,'I_Budget Input Data'!$D$8*0.2/('I_Inputs & Assumptions'!$B$8/4),IF(2<='I_Inputs & Assumptions'!$B$8*0.75,'I_Budget Input Data'!$D$8*0.6/('I_Inputs & Assumptions'!$B$8/2),'I_Budget Input Data'!$D$8*0.2/('I_Inputs & Assumptions'!$B$8/4))),IF('I_Budget Input Data'!$E$8="At Completion",IF(2='I_Inputs & Assumptions'!$B$8,'I_Budget Input Data'!$D$8,0),'I_Budget Input Data'!$D$8/'I_Inputs & Assumptions'!$B$8)))))),0) -> 0 | E8: =IF(3<='I_Inputs & Assumptions'!$B$8,IF('I_Budget Input Data'!$E$8="Upfront",IF(3=1,'I_Budget Input Data'!$D$8,0),IF('I_Budget Input Data'!$E$8="Equal",'I_Budget Input Data'!$D$8/'I_Inputs & Assumptions'!$B$8,IF('I_Budget Input Data'!$E$8="Front-loaded",IF(3<='I_Inputs & Assumptions'!$B$8/2,'I_Budget Input Data'!$D$8*0.6/('I_Inputs & Assumptions'!$B$8/2),'I_Budget Input Data'!$D$8*0.4/('I_Inputs & Assumptions'!$B$8/2)),IF('I_Budget Input Data'!$E$8="Back-loaded",IF(3<='I_Inputs & Assumptions'!$B$8/2,'I_Budget Input Data'!$D$8*0.4/('I_Inputs & Assumptions'!$B$8/2),'I_Budget Input Data'!$D$8*0.6/('I_Inputs & Assumptions'!$B$8/2)),IF('I_Budget Input Data'!$E$8="Mid-weighted",IF(3<='I_Inputs & Assumptions'!$B$8/4,'I_Budget Input Data'!$D$8*0.2/('I_Inputs & Assumptions'!$B$8/4),IF(3<='I_Inputs & Assumptions'!$B$8*0.75,'I_Budget Input Data'!$D$8*0.6/('I_Inputs & Assumptions'!$B$8/2),'I_Budget Input Data'!$D$8*0.2/('I_Inputs & Assumptions'!$B$8/4))),IF('I_Budget Input Data'!$E$8="At Completion",IF(3='I_Inputs & Assumptions'!$B$8,'I_Budget Input Data'!$D$8,0),'I_Budget Input Data'!$D$8/'I_Inputs & Assumptions'!$B$8)))))),0) -> 0 | F8: =IF(4<='I_Inputs & Assumptions'!$B$8,IF('I_Budget Input Data'!$E$8="Upfront",IF(4=1,'I_Budget Input Data'!$D$8,0),IF('I_Budget Input Data'!$E$8="Equal",'I_Budget Input Data'!$D$8/'I_Inputs & Assumptions'!$B$8,IF('I_Budget Input Data'!$E$8="Front-loaded",IF(4<='I_Inputs & Assumptions'!$B$8/2,'I_Budget Input Data'!$D$8*0.6/('I_Inputs & Assumptions'!$B$8/2),'I_Budget Input Data'!$D$8*0.4/('I_Inputs & Assumptions'!$B$8/2)),IF('I_Budget Input Data'!$E$8="Back-loaded",IF(4<='I_Inputs & Assumptions'!$B$8/2,'I_Budget Input Data'!$D$8*0.4/('I_Inputs & Assumptions'!$B$8/2),'I_Budget Input Data'!$D$8*0.6/('I_Inputs & Assumptions'!$B$8/2)),IF('I_Budget Input Data'!$E$8="Mid-weighted",IF(4<='I_Inputs & Assumptions'!$B$8/4,'I_Budget Input Data'!$D$8*0.2/('I_Inputs & Assumptions'!$B$8/4),IF(4<='I_Inputs & Assumptions'!$B$8*0.75,'I_Budget Input Data'!$D$8*0.6/('I_Inputs & Assumptions'!$B$8/2),'I_Budget Input Data'!$D$8*0.2/('I_Inputs & Assumptions'!$B$8/4))),IF('I_Budget Input Data'!$E$8="At Completion",IF(4='I_Inputs & Assumptions'!$B$8,'I_Budget Input Data'!$D$8,0),'I_Budget Input Data'!$D$8/'I_Inputs & Assumptions'!$B$8)))))),0) -> 0 | G8: =IF(5<='I_Inputs & Assumptions'!$B$8,IF('I_Budget Input Data'!$E$8="Upfront",IF(5=1,'I_Budget Input Data'!$D$8,0),IF('I_Budget Input Data'!$E$8="Equal",'I_Budget Input Data'!$D$8/'I_Inputs & Assumptions'!$B$8,IF('I_Budget Input Data'!$E$8="Front-loaded",IF(5<='I_Inputs & Assumptions'!$B$8/2,'I_Budget Input Data'!$D$8*0.6/('I_Inputs & Assumptions'!$B$8/2),'I_Budget Input Data'!$D$8*0.4/('I_Inputs & Assumptions'!$B$8/2)),IF('I_Budget Input Data'!$E$8="Back-loaded",IF(5<='I_Inputs & Assumptions'!$B$8/2,'I_Budget Input Data'!$D$8*0.4/('I_Inputs & Assumptions'!$B$8/2),'I_Budget Input Data'!$D$8*0.6/('I_Inputs & Assumptions'!$B$8/2)),IF('I_Budget Input Data'!$E$8="Mid-weighted",IF(5<='I_Inputs & Assumptions'!$B$8/4,'I_Budget Input Data'!$D$8*0.2/('I_Inputs & Assumptions'!$B$8/4),IF(5<='I_Inputs & Assumptions'!$B$8*0.75,'I_Budget Input Data'!$D$8*0.6/('I_Inputs & Assumptions'!$B$8/2),'I_Budget Input Data'!$D$8*0.2/('I_Inputs & Assumptions'!$B$8/4))),IF('I_Budget Input Data'!$E$8="At Completion",IF(5='I_Inputs & Assumptions'!$B$8,'I_Budget Input Data'!$D$8,0),'I_Budget Input Data'!$D$8/'I_Inputs & Assumptions'!$B$8)))))),0) -> 0 | H8: =IF(6<='I_Inputs & Assumptions'!$B$8,IF('I_Budget Input Data'!$E$8="Upfront",IF(6=1,'I_Budget Input Data'!$D$8,0),IF('I_Budget Input Data'!$E$8="Equal",'I_Budget Input Data'!$D$8/'I_Inputs & Assumptions'!$B$8,IF('I_Budget Input Data'!$E$8="Front-loaded",IF(6<='I_Inputs & Assumptions'!$B$8/2,'I_Budget Input Data'!$D$8*0.6/('I_Inputs & Assumptions'!$B$8/2),'I_Budget Input Data'!$D$8*0.4/('I_Inputs & Assumptions'!$B$8/2)),IF('I_Budget Input Data'!$E$8="Back-loaded",IF(6<='I_Inputs & Assumptions'!$B$8/2,'I_Budget Input Data'!$D$8*0.4/('I_Inputs & Assumptions'!$B$8/2),'I_Budget Input Data'!$D$8*0.6/('I_Inputs & Assumptions'!$B$8/2)),IF('I_Budget Input Data'!$E$8="Mid-weighted",IF(6<='I_Inputs & Assumptions'!$B$8/4,'I_Budget Input Data'!$D$8*0.2/('I_Inputs & Assumptions'!$B$8/4),IF(6<='I_Inputs & Assumptions'!$B$8*0.75,'I_Budget Input Data'!$D$8*0.6/('I_Inputs & Assumptions'!$B$8/2),'I_Budget Input Data'!$D$8*0.2/('I_Inputs & Assumptions'!$B$8/4))),IF('I_Budget Input Data'!$E$8="At Completion",IF(6='I_Inputs & Assumptions'!$B$8,'I_Budget Input Data'!$D$8,0),'I_Budget Input Data'!$D$8/'I_Inputs & Assumptions'!$B$8)))))),0) -> 0 | I8: =IF(7<='I_Inputs & Assumptions'!$B$8,IF('I_Budget Input Data'!$E$8="Upfront",IF(7=1,'I_Budget Input Data'!$D$8,0),IF('I_Budget Input Data'!$E$8="Equal",'I_Budget Input Data'!$D$8/'I_Inputs & Assumptions'!$B$8,IF('I_Budget Input Data'!$E$8="Front-loaded",IF(7<='I_Inputs & Assumptions'!$B$8/2,'I_Budget Input Data'!$D$8*0.6/('I_Inputs & Assumptions'!$B$8/2),'I_Budget Input Data'!$D$8*0.4/('I_Inputs & Assumptions'!$B$8/2)),IF('I_Budget Input Data'!$E$8="Back-loaded",IF(7<='I_Inputs & Assumptions'!$B$8/2,'I_Budget Input Data'!$D$8*0.4/('I_Inputs & Assumptions'!$B$8/2),'I_Budget Input Data'!$D$8*0.6/('I_Inputs & Assumptions'!$B$8/2)),IF('I_Budget Input Data'!$E$8="Mid-weighted",IF(7<='I_Inputs & Assumptions'!$B$8/4,'I_Budget Input Data'!$D$8*0.2/('I_Inputs & Assumptions'!$B$8/4),IF(7<='I_Inputs & Assumptions'!$B$8*0.75,'I_Budget Input Data'!$D$8*0.6/('I_Inputs & Assumptions'!$B$8/2),'I_Budget Input Data'!$D$8*0.2/('I_Inputs & Assumptions'!$B$8/4))),IF('I_Budget Input Data'!$E$8="At Completion",IF(7='I_Inputs & Assumptions'!$B$8,'I_Budget Input Data'!$D$8,0),'I_Budget Input Data'!$D$8/'I_Inputs & Assumptions'!$B$8)))))),0) -> 0 | J8: =IF(8<='I_Inputs & Assumptions'!$B$8,IF('I_Budget Input Data'!$E$8="Upfront",IF(8=1,'I_Budget Input Data'!$D$8,0),IF('I_Budget Input Data'!$E$8="Equal",'I_Budget Input Data'!$D$8/'I_Inputs & Assumptions'!$B$8,IF('I_Budget Input Data'!$E$8="Front-loaded",IF(8<='I_Inputs & Assumptions'!$B$8/2,'I_Budget Input Data'!$D$8*0.6/('I_Inputs & Assumptions'!$B$8/2),'I_Budget Input Data'!$D$8*0.4/('I_Inputs & Assumptions'!$B$8/2)),IF('I_Budget Input Data'!$E$8="Back-loaded",IF(8<='I_Inputs & Assumptions'!$B$8/2,'I_Budget Input Data'!$D$8*0.4/('I_Inputs & Assumptions'!$B$8/2),'I_Budget Input Data'!$D$8*0.6/('I_Inputs & Assumptions'!$B$8/2)),IF('I_Budget Input Data'!$E$8="Mid-weighted",IF(8<='I_Inputs & Assumptions'!$B$8/4,'I_Budget Input Data'!$D$8*0.2/('I_Inputs & Assumptions'!$B$8/4),IF(8<='I_Inputs & Assumptions'!$B$8*0.75,'I_Budget Input Data'!$D$8*0.6/('I_Inputs & Assumptions'!$B$8/2),'I_Budget Input Data'!$D$8*0.2/('I_Inputs & Assumptions'!$B$8/4))),IF('I_Budget Input Data'!$E$8="At Completion",IF(8='I_Inputs & Assumptions'!$B$8,'I_Budget Input Data'!$D$8,0),'I_Budget Input Data'!$D$8/'I_Inputs & Assumptions'!$B$8)))))),0) -> 0 | K8: =IF(9<='I_Inputs & Assumptions'!$B$8,IF('I_Budget Input Data'!$E$8="Upfront",IF(9=1,'I_Budget Input Data'!$D$8,0),IF('I_Budget Input Data'!$E$8="Equal",'I_Budget Input Data'!$D$8/'I_Inputs & Assumptions'!$B$8,IF('I_Budget Input Data'!$E$8="Front-loaded",IF(9<='I_Inputs & Assumptions'!$B$8/2,'I_Budget Input Data'!$D$8*0.6/('I_Inputs & Assumptions'!$B$8/2),'I_Budget Input Data'!$D$8*0.4/('I_Inputs & Assumptions'!$B$8/2)),IF('I_Budget Input Data'!$E$8="Back-loaded",IF(9<='I_Inputs & Assumptions'!$B$8/2,'I_Budget Input Data'!$D$8*0.4/('I_Inputs & Assumptions'!$B$8/2),'I_Budget Input Data'!$D$8*0.6/('I_Inputs & Assumptions'!$B$8/2)),IF('I_Budget Input Data'!$E$8="Mid-weighted",IF(9<='I_Inputs & Assumptions'!$B$8/4,'I_Budget Input Data'!$D$8*0.2/('I_Inputs & Assumptions'!$B$8/4),IF(9<='I_Inputs & Assumptions'!$B$8*0.75,'I_Budget Input Data'!$D$8*0.6/('I_Inputs & Assumptions'!$B$8/2),'I_Budget Input Data'!$D$8*0.2/('I_Inputs & Assumptions'!$B$8/4))),IF('I_Budget Input Data'!$E$8="At Completion",IF(9='I_Inputs & Assumptions'!$B$8,'I_Budget Input Data'!$D$8,0),'I_Budget Input Data'!$D$8/'I_Inputs & Assumptions'!$B$8)))))),0) -> 0 | L8: =IF(10<='I_Inputs & Assumptions'!$B$8,IF('I_Budget Input Data'!$E$8="Upfront",IF(10=1,'I_Budget Input Data'!$D$8,0),IF('I_Budget Input Data'!$E$8="Equal",'I_Budget Input Data'!$D$8/'I_Inputs & Assumptions'!$B$8,IF('I_Budget Input Data'!$E$8="Front-loaded",IF(10<='I_Inputs & Assumptions'!$B$8/2,'I_Budget Input Data'!$D$8*0.6/('I_Inputs & Assumptions'!$B$8/2),'I_Budget Input Data'!$D$8*0.4/('I_Inputs & Assumptions'!$B$8/2)),IF('I_Budget Input Data'!$E$8="Back-loaded",IF(10<='I_Inputs & Assumptions'!$B$8/2,'I_Budget Input Data'!$D$8*0.4/('I_Inputs & Assumptions'!$B$8/2),'I_Budget Input Data'!$D$8*0.6/('I_Inputs & Assumptions'!$B$8/2)),IF('I_Budget Input Data'!$E$8="Mid-weighted",IF(10<='I_Inputs & Assumptions'!$B$8/4,'I_Budget Input Data'!$D$8*0.2/('I_Inputs & Assumptions'!$B$8/4),IF(10<='I_Inputs & Assumptions'!$B$8*0.75,'I_Budget Input Data'!$D$8*0.6/('I_Inputs & Assumptions'!$B$8/2),'I_Budget Input Data'!$D$8*0.2/('I_Inputs & Assumptions'!$B$8/4))),IF('I_Budget Input Data'!$E$8="At Completion",IF(10='I_Inputs & Assumptions'!$B$8,'I_Budget Input Data'!$D$8,0),'I_Budget Input Data'!$D$8/'I_Inputs & Assumptions'!$B$8)))))),0) -> 0 | M8: =IF(11<='I_Inputs & Assumptions'!$B$8,IF('I_Budget Input Data'!$E$8="Upfront",IF(11=1,'I_Budget Input Data'!$D$8,0),IF('I_Budget Input Data'!$E$8="Equal",'I_Budget Input Data'!$D$8/'I_Inputs & Assumptions'!$B$8,IF('I_Budget Input Data'!$E$8="Front-loaded",IF(11<='I_Inputs & Assumptions'!$B$8/2,'I_Budget Input Data'!$D$8*0.6/('I_Inputs & Assumptions'!$B$8/2),'I_Budget Input Data'!$D$8*0.4/('I_Inputs & Assumptions'!$B$8/2)),IF('I_Budget Input Data'!$E$8="Back-loaded",IF(11<='I_Inputs & Assumptions'!$B$8/2,'I_Budget Input Data'!$D$8*0.4/('I_Inputs & Assumptions'!$B$8/2),'I_Budget Input Data'!$D$8*0.6/('I_Inputs & Assumptions'!$B$8/2)),IF('I_Budget Input Data'!$E$8="Mid-weighted",IF(11<='I_Inputs & Assumptions'!$B$8/4,'I_Budget Input Data'!$D$8*0.2/('I_Inputs & Assumptions'!$B$8/4),IF(11<='I_Inputs & Assumptions'!$B$8*0.75,'I_Budget Input Data'!$D$8*0.6/('I_Inputs & Assumptions'!$B$8/2),'I_Budget Input Data'!$D$8*0.2/('I_Inputs & Assumptions'!$B$8/4))),IF('I_Budget Input Data'!$E$8="At Completion",IF(11='I_Inputs & Assumptions'!$B$8,'I_Budget Input Data'!$D$8,0),'I_Budget Input Data'!$D$8/'I_Inputs & Assumptions'!$B$8)))))),0) -> 0 | N8: =IF(12<='I_Inputs & Assumptions'!$B$8,IF('I_Budget Input Data'!$E$8="Upfront",IF(12=1,'I_Budget Input Data'!$D$8,0),IF('I_Budget Input Data'!$E$8="Equal",'I_Budget Input Data'!$D$8/'I_Inputs & Assumptions'!$B$8,IF('I_Budget Input Data'!$E$8="Front-loaded",IF(12<='I_Inputs & Assumptions'!$B$8/2,'I_Budget Input Data'!$D$8*0.6/('I_Inputs & Assumptions'!$B$8/2),'I_Budget Input Data'!$D$8*0.4/('I_Inputs & Assumptions'!$B$8/2)),IF('I_Budget Input Data'!$E$8="Back-loaded",IF(12<='I_Inputs & Assumptions'!$B$8/2,'I_Budget Input Data'!$D$8*0.4/('I_Inputs & Assumptions'!$B$8/2),'I_Budget Input Data'!$D$8*0.6/('I_Inputs & Assumptions'!$B$8/2)),IF('I_Budget Input Data'!$E$8="Mid-weighted",IF(12<='I_Inputs & Assumptions'!$B$8/4,'I_Budget Input Data'!$D$8*0.2/('I_Inputs & Assumptions'!$B$8/4),IF(12<='I_Inputs & Assumptions'!$B$8*0.75,'I_Budget Input Data'!$D$8*0.6/('I_Inputs & Assumptions'!$B$8/2),'I_Budget Input Data'!$D$8*0.2/('I_Inputs & Assumptions'!$B$8/4))),IF('I_Budget Input Data'!$E$8="At Completion",IF(12='I_Inputs & Assumptions'!$B$8,'I_Budget Input Data'!$D$8,0),'I_Budget Input Data'!$D$8/'I_Inputs & Assumptions'!$B$8)))))),0) -> 0 | O8: =IF(13<='I_Inputs & Assumptions'!$B$8,IF('I_Budget Input Data'!$E$8="Upfront",IF(13=1,'I_Budget Input Data'!$D$8,0),IF('I_Budget Input Data'!$E$8="Equal",'I_Budget Input Data'!$D$8/'I_Inputs & Assumptions'!$B$8,IF('I_Budget Input Data'!$E$8="Front-loaded",IF(13<='I_Inputs & Assumptions'!$B$8/2,'I_Budget Input Data'!$D$8*0.6/('I_Inputs & Assumptions'!$B$8/2),'I_Budget Input Data'!$D$8*0.4/('I_Inputs & Assumptions'!$B$8/2)),IF('I_Budget Input Data'!$E$8="Back-loaded",IF(13<='I_Inputs & Assumptions'!$B$8/2,'I_Budget Input Data'!$D$8*0.4/('I_Inputs & Assumptions'!$B$8/2),'I_Budget Input Data'!$D$8*0.6/('I_Inputs & Assumptions'!$B$8/2)),IF('I_Budget Input Data'!$E$8="Mid-weighted",IF(13<='I_Inputs & Assumptions'!$B$8/4,'I_Budget Input Data'!$D$8*0.2/('I_Inputs & Assumptions'!$B$8/4),IF(13<='I_Inputs & Assumptions'!$B$8*0.75,'I_Budget Input Data'!$D$8*0.6/('I_Inputs & Assumptions'!$B$8/2),'I_Budget Input Data'!$D$8*0.2/('I_Inputs & Assumptions'!$B$8/4))),IF('I_Budget Input Data'!$E$8="At Completion",IF(13='I_Inputs & Assumptions'!$B$8,'I_Budget Input Data'!$D$8,0),'I_Budget Input Data'!$D$8/'I_Inputs & Assumptions'!$B$8)))))),0) -> 0 | P8: =IF(14<='I_Inputs & Assumptions'!$B$8,IF('I_Budget Input Data'!$E$8="Upfront",IF(14=1,'I_Budget Input Data'!$D$8,0),IF('I_Budget Input Data'!$E$8="Equal",'I_Budget Input Data'!$D$8/'I_Inputs & Assumptions'!$B$8,IF('I_Budget Input Data'!$E$8="Front-loaded",IF(14<='I_Inputs & Assumptions'!$B$8/2,'I_Budget Input Data'!$D$8*0.6/('I_Inputs & Assumptions'!$B$8/2),'I_Budget Input Data'!$D$8*0.4/('I_Inputs & Assumptions'!$B$8/2)),IF('I_Budget Input Data'!$E$8="Back-loaded",IF(14<='I_Inputs & Assumptions'!$B$8/2,'I_Budget Input Data'!$D$8*0.4/('I_Inputs & Assumptions'!$B$8/2),'I_Budget Input Data'!$D$8*0.6/('I_Inputs & Assumptions'!$B$8/2)),IF('I_Budget Input Data'!$E$8="Mid-weighted",IF(14<='I_Inputs & Assumptions'!$B$8/4,'I_Budget Input Data'!$D$8*0.2/('I_Inputs & Assumptions'!$B$8/4),IF(14<='I_Inputs & Assumptions'!$B$8*0.75,'I_Budget Input Data'!$D$8*0.6/('I_Inputs & Assumptions'!$B$8/2),'I_Budget Input Data'!$D$8*0.2/('I_Inputs & Assumptions'!$B$8/4))),IF('I_Budget Input Data'!$E$8="At Completion",IF(14='I_Inputs & Assumptions'!$B$8,'I_Budget Input Data'!$D$8,0),'I_Budget Input Data'!$D$8/'I_Inputs & Assumptions'!$B$8)))))),0) -> 0 | Q8: =IF(15<='I_Inputs & Assumptions'!$B$8,IF('I_Budget Input Data'!$E$8="Upfront",IF(15=1,'I_Budget Input Data'!$D$8,0),IF('I_Budget Input Data'!$E$8="Equal",'I_Budget Input Data'!$D$8/'I_Inputs & Assumptions'!$B$8,IF('I_Budget Input Data'!$E$8="Front-loaded",IF(15<='I_Inputs & Assumptions'!$B$8/2,'I_Budget Input Data'!$D$8*0.6/('I_Inputs & Assumptions'!$B$8/2),'I_Budget Input Data'!$D$8*0.4/('I_Inputs & Assumptions'!$B$8/2)),IF('I_Budget Input Data'!$E$8="Back-loaded",IF(15<='I_Inputs & Assumptions'!$B$8/2,'I_Budget Input Data'!$D$8*0.4/('I_Inputs & Assumptions'!$B$8/2),'I_Budget Input Data'!$D$8*0.6/('I_Inputs & Assumptions'!$B$8/2)),IF('I_Budget Input Data'!$E$8="Mid-weighted",IF(15<='I_Inputs & Assumptions'!$B$8/4,'I_Budget Input Data'!$D$8*0.2/('I_Inputs & Assumptions'!$B$8/4),IF(15<='I_Inputs & Assumptions'!$B$8*0.75,'I_Budget Input Data'!$D$8*0.6/('I_Inputs & Assumptions'!$B$8/2),'I_Budget Input Data'!$D$8*0.2/('I_Inputs & Assumptions'!$B$8/4))),IF('I_Budget Input Data'!$E$8="At Completion",IF(15='I_Inputs & Assumptions'!$B$8,'I_Budget Input Data'!$D$8,0),'I_Budget Input Data'!$D$8/'I_Inputs & Assumptions'!$B$8)))))),0) -> 0 | R8: =IF(16<='I_Inputs & Assumptions'!$B$8,IF('I_Budget Input Data'!$E$8="Upfront",IF(16=1,'I_Budget Input Data'!$D$8,0),IF('I_Budget Input Data'!$E$8="Equal",'I_Budget Input Data'!$D$8/'I_Inputs & Assumptions'!$B$8,IF('I_Budget Input Data'!$E$8="Front-loaded",IF(16<='I_Inputs & Assumptions'!$B$8/2,'I_Budget Input Data'!$D$8*0.6/('I_Inputs & Assumptions'!$B$8/2),'I_Budget Input Data'!$D$8*0.4/('I_Inputs & Assumptions'!$B$8/2)),IF('I_Budget Input Data'!$E$8="Back-loaded",IF(16<='I_Inputs & Assumptions'!$B$8/2,'I_Budget Input Data'!$D$8*0.4/('I_Inputs & Assumptions'!$B$8/2),'I_Budget Input Data'!$D$8*0.6/('I_Inputs & Assumptions'!$B$8/2)),IF('I_Budget Input Data'!$E$8="Mid-weighted",IF(16<='I_Inputs & Assumptions'!$B$8/4,'I_Budget Input Data'!$D$8*0.2/('I_Inputs & Assumptions'!$B$8/4),IF(16<='I_Inputs & Assumptions'!$B$8*0.75,'I_Budget Input Data'!$D$8*0.6/('I_Inputs & Assumptions'!$B$8/2),'I_Budget Input Data'!$D$8*0.2/('I_Inputs & Assumptions'!$B$8/4))),IF('I_Budget Input Data'!$E$8="At Completion",IF(16='I_Inputs & Assumptions'!$B$8,'I_Budget Input Data'!$D$8,0),'I_Budget Input Data'!$D$8/'I_Inputs & Assumptions'!$B$8)))))),0) -> 0 | S8: =IF(17<='I_Inputs & Assumptions'!$B$8,IF('I_Budget Input Data'!$E$8="Upfront",IF(17=1,'I_Budget Input Data'!$D$8,0),IF('I_Budget Input Data'!$E$8="Equal",'I_Budget Input Data'!$D$8/'I_Inputs & Assumptions'!$B$8,IF('I_Budget Input Data'!$E$8="Front-loaded",IF(17<='I_Inputs & Assumptions'!$B$8/2,'I_Budget Input Data'!$D$8*0.6/('I_Inputs & Assumptions'!$B$8/2),'I_Budget Input Data'!$D$8*0.4/('I_Inputs & Assumptions'!$B$8/2)),IF('I_Budget Input Data'!$E$8="Back-loaded",IF(17<='I_Inputs & Assumptions'!$B$8/2,'I_Budget Input Data'!$D$8*0.4/('I_Inputs & Assumptions'!$B$8/2),'I_Budget Input Data'!$D$8*0.6/('I_Inputs & Assumptions'!$B$8/2)),IF('I_Budget Input Data'!$E$8="Mid-weighted",IF(17<='I_Inputs & Assumptions'!$B$8/4,'I_Budget Input Data'!$D$8*0.2/('I_Inputs & Assumptions'!$B$8/4),IF(17<='I_Inputs & Assumptions'!$B$8*0.75,'I_Budget Input Data'!$D$8*0.6/('I_Inputs & Assumptions'!$B$8/2),'I_Budget Input Data'!$D$8*0.2/('I_Inputs & Assumptions'!$B$8/4))),IF('I_Budget Input Data'!$E$8="At Completion",IF(17='I_Inputs & Assumptions'!$B$8,'I_Budget Input Data'!$D$8,0),'I_Budget Input Data'!$D$8/'I_Inputs & Assumptions'!$B$8)))))),0) -> 0 | T8: =IF(18<='I_Inputs & Assumptions'!$B$8,IF('I_Budget Input Data'!$E$8="Upfront",IF(18=1,'I_Budget Input Data'!$D$8,0),IF('I_Budget Input Data'!$E$8="Equal",'I_Budget Input Data'!$D$8/'I_Inputs & Assumptions'!$B$8,IF('I_Budget Input Data'!$E$8="Front-loaded",IF(18<='I_Inputs & Assumptions'!$B$8/2,'I_Budget Input Data'!$D$8*0.6/('I_Inputs & Assumptions'!$B$8/2),'I_Budget Input Data'!$D$8*0.4/('I_Inputs & Assumptions'!$B$8/2)),IF('I_Budget Input Data'!$E$8="Back-loaded",IF(18<='I_Inputs & Assumptions'!$B$8/2,'I_Budget Input Data'!$D$8*0.4/('I_Inputs & Assumptions'!$B$8/2),'I_Budget Input Data'!$D$8*0.6/('I_Inputs & Assumptions'!$B$8/2)),IF('I_Budget Input Data'!$E$8="Mid-weighted",IF(18<='I_Inputs & Assumptions'!$B$8/4,'I_Budget Input Data'!$D$8*0.2/('I_Inputs & Assumptions'!$B$8/4),IF(18<='I_Inputs & Assumptions'!$B$8*0.75,'I_Budget Input Data'!$D$8*0.6/('I_Inputs & Assumptions'!$B$8/2),'I_Budget Input Data'!$D$8*0.2/('I_Inputs & Assumptions'!$B$8/4))),IF('I_Budget Input Data'!$E$8="At Completion",IF(18='I_Inputs & Assumptions'!$B$8,'I_Budget Input Data'!$D$8,0),'I_Budget Input Data'!$D$8/'I_Inputs & Assumptions'!$B$8)))))),0) -> 0 | U8: =IF(19<='I_Inputs & Assumptions'!$B$8,IF('I_Budget Input Data'!$E$8="Upfront",IF(19=1,'I_Budget Input Data'!$D$8,0),IF('I_Budget Input Data'!$E$8="Equal",'I_Budget Input Data'!$D$8/'I_Inputs & Assumptions'!$B$8,IF('I_Budget Input Data'!$E$8="Front-loaded",IF(19<='I_Inputs & Assumptions'!$B$8/2,'I_Budget Input Data'!$D$8*0.6/('I_Inputs & Assumptions'!$B$8/2),'I_Budget Input Data'!$D$8*0.4/('I_Inputs & Assumptions'!$B$8/2)),IF('I_Budget Input Data'!$E$8="Back-loaded",IF(19<='I_Inputs & Assumptions'!$B$8/2,'I_Budget Input Data'!$D$8*0.4/('I_Inputs & Assumptions'!$B$8/2),'I_Budget Input Data'!$D$8*0.6/('I_Inputs & Assumptions'!$B$8/2)),IF('I_Budget Input Data'!$E$8="Mid-weighted",IF(19<='I_Inputs & Assumptions'!$B$8/4,'I_Budget Input Data'!$D$8*0.2/('I_Inputs & Assumptions'!$B$8/4),IF(19<='I_Inputs & Assumptions'!$B$8*0.75,'I_Budget Input Data'!$D$8*0.6/('I_Inputs & Assumptions'!$B$8/2),'I_Budget Input Data'!$D$8*0.2/('I_Inputs & Assumptions'!$B$8/4))),IF('I_Budget Input Data'!$E$8="At Completion",IF(19='I_Inputs & Assumptions'!$B$8,'I_Budget Input Data'!$D$8,0),'I_Budget Input Data'!$D$8/'I_Inputs & Assumptions'!$B$8)))))),0) -> 0 | V8: =IF(20<='I_Inputs & Assumptions'!$B$8,IF('I_Budget Input Data'!$E$8="Upfront",IF(20=1,'I_Budget Input Data'!$D$8,0),IF('I_Budget Input Data'!$E$8="Equal",'I_Budget Input Data'!$D$8/'I_Inputs & Assumptions'!$B$8,IF('I_Budget Input Data'!$E$8="Front-loaded",IF(20<='I_Inputs & Assumptions'!$B$8/2,'I_Budget Input Data'!$D$8*0.6/('I_Inputs & Assumptions'!$B$8/2),'I_Budget Input Data'!$D$8*0.4/('I_Inputs & Assumptions'!$B$8/2)),IF('I_Budget Input Data'!$E$8="Back-loaded",IF(20<='I_Inputs & Assumptions'!$B$8/2,'I_Budget Input Data'!$D$8*0.4/('I_Inputs & Assumptions'!$B$8/2),'I_Budget Input Data'!$D$8*0.6/('I_Inputs & Assumptions'!$B$8/2)),IF('I_Budget Input Data'!$E$8="Mid-weighted",IF(20<='I_Inputs & Assumptions'!$B$8/4,'I_Budget Input Data'!$D$8*0.2/('I_Inputs & Assumptions'!$B$8/4),IF(20<='I_Inputs & Assumptions'!$B$8*0.75,'I_Budget Input Data'!$D$8*0.6/('I_Inputs & Assumptions'!$B$8/2),'I_Budget Input Data'!$D$8*0.2/('I_Inputs & Assumptions'!$B$8/4))),IF('I_Budget Input Data'!$E$8="At Completion",IF(20='I_Inputs & Assumptions'!$B$8,'I_Budget Input Data'!$D$8,0),'I_Budget Input Data'!$D$8/'I_Inputs & Assumptions'!$B$8)))))),0) -> 0 | W8: =IF(21<='I_Inputs & Assumptions'!$B$8,IF('I_Budget Input Data'!$E$8="Upfront",IF(21=1,'I_Budget Input Data'!$D$8,0),IF('I_Budget Input Data'!$E$8="Equal",'I_Budget Input Data'!$D$8/'I_Inputs & Assumptions'!$B$8,IF('I_Budget Input Data'!$E$8="Front-loaded",IF(21<='I_Inputs & Assumptions'!$B$8/2,'I_Budget Input Data'!$D$8*0.6/('I_Inputs & Assumptions'!$B$8/2),'I_Budget Input Data'!$D$8*0.4/('I_Inputs & Assumptions'!$B$8/2)),IF('I_Budget Input Data'!$E$8="Back-loaded",IF(21<='I_Inputs & Assumptions'!$B$8/2,'I_Budget Input Data'!$D$8*0.4/('I_Inputs & Assumptions'!$B$8/2),'I_Budget Input Data'!$D$8*0.6/('I_Inputs & Assumptions'!$B$8/2)),IF('I_Budget Input Data'!$E$8="Mid-weighted",IF(21<='I_Inputs & Assumptions'!$B$8/4,'I_Budget Input Data'!$D$8*0.2/('I_Inputs & Assumptions'!$B$8/4),IF(21<='I_Inputs & Assumptions'!$B$8*0.75,'I_Budget Input Data'!$D$8*0.6/('I_Inputs & Assumptions'!$B$8/2),'I_Budget Input Data'!$D$8*0.2/('I_Inputs & Assumptions'!$B$8/4))),IF('I_Budget Input Data'!$E$8="At Completion",IF(21='I_Inputs & Assumptions'!$B$8,'I_Budget Input Data'!$D$8,0),'I_Budget Input Data'!$D$8/'I_Inputs & Assumptions'!$B$8)))))),0) -> 0 | X8: =IF(22<='I_Inputs & Assumptions'!$B$8,IF('I_Budget Input Data'!$E$8="Upfront",IF(22=1,'I_Budget Input Data'!$D$8,0),IF('I_Budget Input Data'!$E$8="Equal",'I_Budget Input Data'!$D$8/'I_Inputs & Assumptions'!$B$8,IF('I_Budget Input Data'!$E$8="Front-loaded",IF(22<='I_Inputs & Assumptions'!$B$8/2,'I_Budget Input Data'!$D$8*0.6/('I_Inputs & Assumptions'!$B$8/2),'I_Budget Input Data'!$D$8*0.4/('I_Inputs & Assumptions'!$B$8/2)),IF('I_Budget Input Data'!$E$8="Back-loaded",IF(22<='I_Inputs & Assumptions'!$B$8/2,'I_Budget Input Data'!$D$8*0.4/('I_Inputs & Assumptions'!$B$8/2),'I_Budget Input Data'!$D$8*0.6/('I_Inputs & Assumptions'!$B$8/2)),IF('I_Budget Input Data'!$E$8="Mid-weighted",IF(22<='I_Inputs & Assumptions'!$B$8/4,'I_Budget Input Data'!$D$8*0.2/('I_Inputs & Assumptions'!$B$8/4),IF(22<='I_Inputs & Assumptions'!$B$8*0.75,'I_Budget Input Data'!$D$8*0.6/('I_Inputs & Assumptions'!$B$8/2),'I_Budget Input Data'!$D$8*0.2/('I_Inputs & Assumptions'!$B$8/4))),IF('I_Budget Input Data'!$E$8="At Completion",IF(22='I_Inputs & Assumptions'!$B$8,'I_Budget Input Data'!$D$8,0),'I_Budget Input Data'!$D$8/'I_Inputs & Assumptions'!$B$8)))))),0) -> 0 | Y8: =IF(23<='I_Inputs & Assumptions'!$B$8,IF('I_Budget Input Data'!$E$8="Upfront",IF(23=1,'I_Budget Input Data'!$D$8,0),IF('I_Budget Input Data'!$E$8="Equal",'I_Budget Input Data'!$D$8/'I_Inputs & Assumptions'!$B$8,IF('I_Budget Input Data'!$E$8="Front-loaded",IF(23<='I_Inputs & Assumptions'!$B$8/2,'I_Budget Input Data'!$D$8*0.6/('I_Inputs & Assumptions'!$B$8/2),'I_Budget Input Data'!$D$8*0.4/('I_Inputs & Assumptions'!$B$8/2)),IF('I_Budget Input Data'!$E$8="Back-loaded",IF(23<='I_Inputs & Assumptions'!$B$8/2,'I_Budget Input Data'!$D$8*0.4/('I_Inputs & Assumptions'!$B$8/2),'I_Budget Input Data'!$D$8*0.6/('I_Inputs & Assumptions'!$B$8/2)),IF('I_Budget Input Data'!$E$8="Mid-weighted",IF(23<='I_Inputs & Assumptions'!$B$8/4,'I_Budget Input Data'!$D$8*0.2/('I_Inputs & Assumptions'!$B$8/4),IF(23<='I_Inputs & Assumptions'!$B$8*0.75,'I_Budget Input Data'!$D$8*0.6/('I_Inputs & Assumptions'!$B$8/2),'I_Budget Input Data'!$D$8*0.2/('I_Inputs & Assumptions'!$B$8/4))),IF('I_Budget Input Data'!$E$8="At Completion",IF(23='I_Inputs & Assumptions'!$B$8,'I_Budget Input Data'!$D$8,0),'I_Budget Input Data'!$D$8/'I_Inputs & Assumptions'!$B$8)))))),0) -> 0 | Z8: =IF(24<='I_Inputs & Assumptions'!$B$8,IF('I_Budget Input Data'!$E$8="Upfront",IF(24=1,'I_Budget Input Data'!$D$8,0),IF('I_Budget Input Data'!$E$8="Equal",'I_Budget Input Data'!$D$8/'I_Inputs & Assumptions'!$B$8,IF('I_Budget Input Data'!$E$8="Front-loaded",IF(24<='I_Inputs & Assumptions'!$B$8/2,'I_Budget Input Data'!$D$8*0.6/('I_Inputs & Assumptions'!$B$8/2),'I_Budget Input Data'!$D$8*0.4/('I_Inputs & Assumptions'!$B$8/2)),IF('I_Budget Input Data'!$E$8="Back-loaded",IF(24<='I_Inputs & Assumptions'!$B$8/2,'I_Budget Input Data'!$D$8*0.4/('I_Inputs & Assumptions'!$B$8/2),'I_Budget Input Data'!$D$8*0.6/('I_Inputs & Assumptions'!$B$8/2)),IF('I_Budget Input Data'!$E$8="Mid-weighted",IF(24<='I_Inputs & Assumptions'!$B$8/4,'I_Budget Input Data'!$D$8*0.2/('I_Inputs & Assumptions'!$B$8/4),IF(24<='I_Inputs & Assumptions'!$B$8*0.75,'I_Budget Input Data'!$D$8*0.6/('I_Inputs & Assumptions'!$B$8/2),'I_Budget Input Data'!$D$8*0.2/('I_Inputs & Assumptions'!$B$8/4))),IF('I_Budget Input Data'!$E$8="At Completion",IF(24='I_Inputs & Assumptions'!$B$8,'I_Budget Input Data'!$D$8,0),'I_Budget Input Data'!$D$8/'I_Inputs & Assumptions'!$B$8)))))),0) -> 0 | AA8: =IF(25<='I_Inputs & Assumptions'!$B$8,IF('I_Budget Input Data'!$E$8="Upfront",IF(25=1,'I_Budget Input Data'!$D$8,0),IF('I_Budget Input Data'!$E$8="Equal",'I_Budget Input Data'!$D$8/'I_Inputs & Assumptions'!$B$8,IF('I_Budget Input Data'!$E$8="Front-loaded",IF(25<='I_Inputs & Assumptions'!$B$8/2,'I_Budget Input Data'!$D$8*0.6/('I_Inputs & Assumptions'!$B$8/2),'I_Budget Input Data'!$D$8*0.4/('I_Inputs & Assumptions'!$B$8/2)),IF('I_Budget Input Data'!$E$8="Back-loaded",IF(25<='I_Inputs & Assumptions'!$B$8/2,'I_Budget Input Data'!$D$8*0.4/('I_Inputs & Assumptions'!$B$8/2),'I_Budget Input Data'!$D$8*0.6/('I_Inputs & Assumptions'!$B$8/2)),IF('I_Budget Input Data'!$E$8="Mid-weighted",IF(25<='I_Inputs & Assumptions'!$B$8/4,'I_Budget Input Data'!$D$8*0.2/('I_Inputs & Assumptions'!$B$8/4),IF(25<='I_Inputs & Assumptions'!$B$8*0.75,'I_Budget Input Data'!$D$8*0.6/('I_Inputs & Assumptions'!$B$8/2),'I_Budget Input Data'!$D$8*0.2/('I_Inputs & Assumptions'!$B$8/4))),IF('I_Budget Input Data'!$E$8="At Completion",IF(25='I_Inputs & Assumptions'!$B$8,'I_Budget Input Data'!$D$8,0),'I_Budget Input Data'!$D$8/'I_Inputs & Assumptions'!$B$8)))))),0) -> 0 | AB8: =IF(26<='I_Inputs & Assumptions'!$B$8,IF('I_Budget Input Data'!$E$8="Upfront",IF(26=1,'I_Budget Input Data'!$D$8,0),IF('I_Budget Input Data'!$E$8="Equal",'I_Budget Input Data'!$D$8/'I_Inputs & Assumptions'!$B$8,IF('I_Budget Input Data'!$E$8="Front-loaded",IF(26<='I_Inputs & Assumptions'!$B$8/2,'I_Budget Input Data'!$D$8*0.6/('I_Inputs & Assumptions'!$B$8/2),'I_Budget Input Data'!$D$8*0.4/('I_Inputs & Assumptions'!$B$8/2)),IF('I_Budget Input Data'!$E$8="Back-loaded",IF(26<='I_Inputs & Assumptions'!$B$8/2,'I_Budget Input Data'!$D$8*0.4/('I_Inputs & Assumptions'!$B$8/2),'I_Budget Input Data'!$D$8*0.6/('I_Inputs & Assumptions'!$B$8/2)),IF('I_Budget Input Data'!$E$8="Mid-weighted",IF(26<='I_Inputs & Assumptions'!$B$8/4,'I_Budget Input Data'!$D$8*0.2/('I_Inputs & Assumptions'!$B$8/4),IF(26<='I_Inputs & Assumptions'!$B$8*0.75,'I_Budget Input Data'!$D$8*0.6/('I_Inputs & Assumptions'!$B$8/2),'I_Budget Input Data'!$D$8*0.2/('I_Inputs & Assumptions'!$B$8/4))),IF('I_Budget Input Data'!$E$8="At Completion",IF(26='I_Inputs & Assumptions'!$B$8,'I_Budget Input Data'!$D$8,0),'I_Budget Input Data'!$D$8/'I_Inputs & Assumptions'!$B$8)))))),0) -> 0 | AC8: =IF(27<='I_Inputs & Assumptions'!$B$8,IF('I_Budget Input Data'!$E$8="Upfront",IF(27=1,'I_Budget Input Data'!$D$8,0),IF('I_Budget Input Data'!$E$8="Equal",'I_Budget Input Data'!$D$8/'I_Inputs & Assumptions'!$B$8,IF('I_Budget Input Data'!$E$8="Front-loaded",IF(27<='I_Inputs & Assumptions'!$B$8/2,'I_Budget Input Data'!$D$8*0.6/('I_Inputs & Assumptions'!$B$8/2),'I_Budget Input Data'!$D$8*0.4/('I_Inputs & Assumptions'!$B$8/2)),IF('I_Budget Input Data'!$E$8="Back-loaded",IF(27<='I_Inputs & Assumptions'!$B$8/2,'I_Budget Input Data'!$D$8*0.4/('I_Inputs & Assumptions'!$B$8/2),'I_Budget Input Data'!$D$8*0.6/('I_Inputs & Assumptions'!$B$8/2)),IF('I_Budget Input Data'!$E$8="Mid-weighted",IF(27<='I_Inputs & Assumptions'!$B$8/4,'I_Budget Input Data'!$D$8*0.2/('I_Inputs & Assumptions'!$B$8/4),IF(27<='I_Inputs & Assumptions'!$B$8*0.75,'I_Budget Input Data'!$D$8*0.6/('I_Inputs & Assumptions'!$B$8/2),'I_Budget Input Data'!$D$8*0.2/('I_Inputs & Assumptions'!$B$8/4))),IF('I_Budget Input Data'!$E$8="At Completion",IF(27='I_Inputs & Assumptions'!$B$8,'I_Budget Input Data'!$D$8,0),'I_Budget Input Data'!$D$8/'I_Inputs & Assumptions'!$B$8)))))),0) -> 0 | AD8: =IF(28<='I_Inputs & Assumptions'!$B$8,IF('I_Budget Input Data'!$E$8="Upfront",IF(28=1,'I_Budget Input Data'!$D$8,0),IF('I_Budget Input Data'!$E$8="Equal",'I_Budget Input Data'!$D$8/'I_Inputs & Assumptions'!$B$8,IF('I_Budget Input Data'!$E$8="Front-loaded",IF(28<='I_Inputs & Assumptions'!$B$8/2,'I_Budget Input Data'!$D$8*0.6/('I_Inputs & Assumptions'!$B$8/2),'I_Budget Input Data'!$D$8*0.4/('I_Inputs & Assumptions'!$B$8/2)),IF('I_Budget Input Data'!$E$8="Back-loaded",IF(28<='I_Inputs & Assumptions'!$B$8/2,'I_Budget Input Data'!$D$8*0.4/('I_Inputs & Assumptions'!$B$8/2),'I_Budget Input Data'!$D$8*0.6/('I_Inputs & Assumptions'!$B$8/2)),IF('I_Budget Input Data'!$E$8="Mid-weighted",IF(28<='I_Inputs & Assumptions'!$B$8/4,'I_Budget Input Data'!$D$8*0.2/('I_Inputs & Assumptions'!$B$8/4),IF(28<='I_Inputs & Assumptions'!$B$8*0.75,'I_Budget Input Data'!$D$8*0.6/('I_Inputs & Assumptions'!$B$8/2),'I_Budget Input Data'!$D$8*0.2/('I_Inputs & Assumptions'!$B$8/4))),IF('I_Budget Input Data'!$E$8="At Completion",IF(28='I_Inputs & Assumptions'!$B$8,'I_Budget Input Data'!$D$8,0),'I_Budget Input Data'!$D$8/'I_Inputs & Assumptions'!$B$8)))))),0) -> 0 | AE8: =IF(29<='I_Inputs & Assumptions'!$B$8,IF('I_Budget Input Data'!$E$8="Upfront",IF(29=1,'I_Budget Input Data'!$D$8,0),IF('I_Budget Input Data'!$E$8="Equal",'I_Budget Input Data'!$D$8/'I_Inputs & Assumptions'!$B$8,IF('I_Budget Input Data'!$E$8="Front-loaded",IF(29<='I_Inputs & Assumptions'!$B$8/2,'I_Budget Input Data'!$D$8*0.6/('I_Inputs & Assumptions'!$B$8/2),'I_Budget Input Data'!$D$8*0.4/('I_Inputs & Assumptions'!$B$8/2)),IF('I_Budget Input Data'!$E$8="Back-loaded",IF(29<='I_Inputs & Assumptions'!$B$8/2,'I_Budget Input Data'!$D$8*0.4/('I_Inputs & Assumptions'!$B$8/2),'I_Budget Input Data'!$D$8*0.6/('I_Inputs & Assumptions'!$B$8/2)),IF('I_Budget Input Data'!$E$8="Mid-weighted",IF(29<='I_Inputs & Assumptions'!$B$8/4,'I_Budget Input Data'!$D$8*0.2/('I_Inputs & Assumptions'!$B$8/4),IF(29<='I_Inputs & Assumptions'!$B$8*0.75,'I_Budget Input Data'!$D$8*0.6/('I_Inputs & Assumptions'!$B$8/2),'I_Budget Input Data'!$D$8*0.2/('I_Inputs & Assumptions'!$B$8/4))),IF('I_Budget Input Data'!$E$8="At Completion",IF(29='I_Inputs & Assumptions'!$B$8,'I_Budget Input Data'!$D$8,0),'I_Budget Input Data'!$D$8/'I_Inputs & Assumptions'!$B$8)))))),0) -> 0 | AF8: =IF(30<='I_Inputs & Assumptions'!$B$8,IF('I_Budget Input Data'!$E$8="Upfront",IF(30=1,'I_Budget Input Data'!$D$8,0),IF('I_Budget Input Data'!$E$8="Equal",'I_Budget Input Data'!$D$8/'I_Inputs & Assumptions'!$B$8,IF('I_Budget Input Data'!$E$8="Front-loaded",IF(30<='I_Inputs & Assumptions'!$B$8/2,'I_Budget Input Data'!$D$8*0.6/('I_Inputs & Assumptions'!$B$8/2),'I_Budget Input Data'!$D$8*0.4/('I_Inputs & Assumptions'!$B$8/2)),IF('I_Budget Input Data'!$E$8="Back-loaded",IF(30<='I_Inputs & Assumptions'!$B$8/2,'I_Budget Input Data'!$D$8*0.4/('I_Inputs & Assumptions'!$B$8/2),'I_Budget Input Data'!$D$8*0.6/('I_Inputs & Assumptions'!$B$8/2)),IF('I_Budget Input Data'!$E$8="Mid-weighted",IF(30<='I_Inputs & Assumptions'!$B$8/4,'I_Budget Input Data'!$D$8*0.2/('I_Inputs & Assumptions'!$B$8/4),IF(30<='I_Inputs & Assumptions'!$B$8*0.75,'I_Budget Input Data'!$D$8*0.6/('I_Inputs & Assumptions'!$B$8/2),'I_Budget Input Data'!$D$8*0.2/('I_Inputs & Assumptions'!$B$8/4))),IF('I_Budget Input Data'!$E$8="At Completion",IF(30='I_Inputs & Assumptions'!$B$8,'I_Budget Input Data'!$D$8,0),'I_Budget Input Data'!$D$8/'I_Inputs & Assumptions'!$B$8)))))),0) -> 0 | AG8: =IF(31<='I_Inputs & Assumptions'!$B$8,IF('I_Budget Input Data'!$E$8="Upfront",IF(31=1,'I_Budget Input Data'!$D$8,0),IF('I_Budget Input Data'!$E$8="Equal",'I_Budget Input Data'!$D$8/'I_Inputs & Assumptions'!$B$8,IF('I_Budget Input Data'!$E$8="Front-loaded",IF(31<='I_Inputs & Assumptions'!$B$8/2,'I_Budget Input Data'!$D$8*0.6/('I_Inputs & Assumptions'!$B$8/2),'I_Budget Input Data'!$D$8*0.4/('I_Inputs & Assumptions'!$B$8/2)),IF('I_Budget Input Data'!$E$8="Back-loaded",IF(31<='I_Inputs & Assumptions'!$B$8/2,'I_Budget Input Data'!$D$8*0.4/('I_Inputs & Assumptions'!$B$8/2),'I_Budget Input Data'!$D$8*0.6/('I_Inputs & Assumptions'!$B$8/2)),IF('I_Budget Input Data'!$E$8="Mid-weighted",IF(31<='I_Inputs & Assumptions'!$B$8/4,'I_Budget Input Data'!$D$8*0.2/('I_Inputs & Assumptions'!$B$8/4),IF(31<='I_Inputs & Assumptions'!$B$8*0.75,'I_Budget Input Data'!$D$8*0.6/('I_Inputs & Assumptions'!$B$8/2),'I_Budget Input Data'!$D$8*0.2/('I_Inputs & Assumptions'!$B$8/4))),IF('I_Budget Input Data'!$E$8="At Completion",IF(31='I_Inputs & Assumptions'!$B$8,'I_Budget Input Data'!$D$8,0),'I_Budget Input Data'!$D$8/'I_Inputs & Assumptions'!$B$8)))))),0) -> 0 | AH8: =IF(32<='I_Inputs & Assumptions'!$B$8,IF('I_Budget Input Data'!$E$8="Upfront",IF(32=1,'I_Budget Input Data'!$D$8,0),IF('I_Budget Input Data'!$E$8="Equal",'I_Budget Input Data'!$D$8/'I_Inputs & Assumptions'!$B$8,IF('I_Budget Input Data'!$E$8="Front-loaded",IF(32<='I_Inputs & Assumptions'!$B$8/2,'I_Budget Input Data'!$D$8*0.6/('I_Inputs & Assumptions'!$B$8/2),'I_Budget Input Data'!$D$8*0.4/('I_Inputs & Assumptions'!$B$8/2)),IF('I_Budget Input Data'!$E$8="Back-loaded",IF(32<='I_Inputs & Assumptions'!$B$8/2,'I_Budget Input Data'!$D$8*0.4/('I_Inputs & Assumptions'!$B$8/2),'I_Budget Input Data'!$D$8*0.6/('I_Inputs & Assumptions'!$B$8/2)),IF('I_Budget Input Data'!$E$8="Mid-weighted",IF(32<='I_Inputs & Assumptions'!$B$8/4,'I_Budget Input Data'!$D$8*0.2/('I_Inputs & Assumptions'!$B$8/4),IF(32<='I_Inputs & Assumptions'!$B$8*0.75,'I_Budget Input Data'!$D$8*0.6/('I_Inputs & Assumptions'!$B$8/2),'I_Budget Input Data'!$D$8*0.2/('I_Inputs & Assumptions'!$B$8/4))),IF('I_Budget Input Data'!$E$8="At Completion",IF(32='I_Inputs & Assumptions'!$B$8,'I_Budget Input Data'!$D$8,0),'I_Budget Input Data'!$D$8/'I_Inputs & Assumptions'!$B$8)))))),0) -> 0 | AI8: =IF(33<='I_Inputs & Assumptions'!$B$8,IF('I_Budget Input Data'!$E$8="Upfront",IF(33=1,'I_Budget Input Data'!$D$8,0),IF('I_Budget Input Data'!$E$8="Equal",'I_Budget Input Data'!$D$8/'I_Inputs & Assumptions'!$B$8,IF('I_Budget Input Data'!$E$8="Front-loaded",IF(33<='I_Inputs & Assumptions'!$B$8/2,'I_Budget Input Data'!$D$8*0.6/('I_Inputs & Assumptions'!$B$8/2),'I_Budget Input Data'!$D$8*0.4/('I_Inputs & Assumptions'!$B$8/2)),IF('I_Budget Input Data'!$E$8="Back-loaded",IF(33<='I_Inputs & Assumptions'!$B$8/2,'I_Budget Input Data'!$D$8*0.4/('I_Inputs & Assumptions'!$B$8/2),'I_Budget Input Data'!$D$8*0.6/('I_Inputs & Assumptions'!$B$8/2)),IF('I_Budget Input Data'!$E$8="Mid-weighted",IF(33<='I_Inputs & Assumptions'!$B$8/4,'I_Budget Input Data'!$D$8*0.2/('I_Inputs & Assumptions'!$B$8/4),IF(33<='I_Inputs & Assumptions'!$B$8*0.75,'I_Budget Input Data'!$D$8*0.6/('I_Inputs & Assumptions'!$B$8/2),'I_Budget Input Data'!$D$8*0.2/('I_Inputs & Assumptions'!$B$8/4))),IF('I_Budget Input Data'!$E$8="At Completion",IF(33='I_Inputs & Assumptions'!$B$8,'I_Budget Input Data'!$D$8,0),'I_Budget Input Data'!$D$8/'I_Inputs & Assumptions'!$B$8)))))),0) -> 0 | AJ8: =IF(34<='I_Inputs & Assumptions'!$B$8,IF('I_Budget Input Data'!$E$8="Upfront",IF(34=1,'I_Budget Input Data'!$D$8,0),IF('I_Budget Input Data'!$E$8="Equal",'I_Budget Input Data'!$D$8/'I_Inputs & Assumptions'!$B$8,IF('I_Budget Input Data'!$E$8="Front-loaded",IF(34<='I_Inputs & Assumptions'!$B$8/2,'I_Budget Input Data'!$D$8*0.6/('I_Inputs & Assumptions'!$B$8/2),'I_Budget Input Data'!$D$8*0.4/('I_Inputs & Assumptions'!$B$8/2)),IF('I_Budget Input Data'!$E$8="Back-loaded",IF(34<='I_Inputs & Assumptions'!$B$8/2,'I_Budget Input Data'!$D$8*0.4/('I_Inputs & Assumptions'!$B$8/2),'I_Budget Input Data'!$D$8*0.6/('I_Inputs & Assumptions'!$B$8/2)),IF('I_Budget Input Data'!$E$8="Mid-weighted",IF(34<='I_Inputs & Assumptions'!$B$8/4,'I_Budget Input Data'!$D$8*0.2/('I_Inputs & Assumptions'!$B$8/4),IF(34<='I_Inputs & Assumptions'!$B$8*0.75,'I_Budget Input Data'!$D$8*0.6/('I_Inputs & Assumptions'!$B$8/2),'I_Budget Input Data'!$D$8*0.2/('I_Inputs & Assumptions'!$B$8/4))),IF('I_Budget Input Data'!$E$8="At Completion",IF(34='I_Inputs & Assumptions'!$B$8,'I_Budget Input Data'!$D$8,0),'I_Budget Input Data'!$D$8/'I_Inputs & Assumptions'!$B$8)))))),0) -> 0 | AK8: =IF(35<='I_Inputs & Assumptions'!$B$8,IF('I_Budget Input Data'!$E$8="Upfront",IF(35=1,'I_Budget Input Data'!$D$8,0),IF('I_Budget Input Data'!$E$8="Equal",'I_Budget Input Data'!$D$8/'I_Inputs & Assumptions'!$B$8,IF('I_Budget Input Data'!$E$8="Front-loaded",IF(35<='I_Inputs & Assumptions'!$B$8/2,'I_Budget Input Data'!$D$8*0.6/('I_Inputs & Assumptions'!$B$8/2),'I_Budget Input Data'!$D$8*0.4/('I_Inputs & Assumptions'!$B$8/2)),IF('I_Budget Input Data'!$E$8="Back-loaded",IF(35<='I_Inputs & Assumptions'!$B$8/2,'I_Budget Input Data'!$D$8*0.4/('I_Inputs & Assumptions'!$B$8/2),'I_Budget Input Data'!$D$8*0.6/('I_Inputs & Assumptions'!$B$8/2)),IF('I_Budget Input Data'!$E$8="Mid-weighted",IF(35<='I_Inputs & Assumptions'!$B$8/4,'I_Budget Input Data'!$D$8*0.2/('I_Inputs & Assumptions'!$B$8/4),IF(35<='I_Inputs & Assumptions'!$B$8*0.75,'I_Budget Input Data'!$D$8*0.6/('I_Inputs & Assumptions'!$B$8/2),'I_Budget Input Data'!$D$8*0.2/('I_Inputs & Assumptions'!$B$8/4))),IF('I_Budget Input Data'!$E$8="At Completion",IF(35='I_Inputs & Assumptions'!$B$8,'I_Budget Input Data'!$D$8,0),'I_Budget Input Data'!$D$8/'I_Inputs & Assumptions'!$B$8)))))),0) -> 0 | AL8: =IF(36<='I_Inputs & Assumptions'!$B$8,IF('I_Budget Input Data'!$E$8="Upfront",IF(36=1,'I_Budget Input Data'!$D$8,0),IF('I_Budget Input Data'!$E$8="Equal",'I_Budget Input Data'!$D$8/'I_Inputs & Assumptions'!$B$8,IF('I_Budget Input Data'!$E$8="Front-loaded",IF(36<='I_Inputs & Assumptions'!$B$8/2,'I_Budget Input Data'!$D$8*0.6/('I_Inputs & Assumptions'!$B$8/2),'I_Budget Input Data'!$D$8*0.4/('I_Inputs & Assumptions'!$B$8/2)),IF('I_Budget Input Data'!$E$8="Back-loaded",IF(36<='I_Inputs & Assumptions'!$B$8/2,'I_Budget Input Data'!$D$8*0.4/('I_Inputs & Assumptions'!$B$8/2),'I_Budget Input Data'!$D$8*0.6/('I_Inputs & Assumptions'!$B$8/2)),IF('I_Budget Input Data'!$E$8="Mid-weighted",IF(36<='I_Inputs & Assumptions'!$B$8/4,'I_Budget Input Data'!$D$8*0.2/('I_Inputs & Assumptions'!$B$8/4),IF(36<='I_Inputs & Assumptions'!$B$8*0.75,'I_Budget Input Data'!$D$8*0.6/('I_Inputs & Assumptions'!$B$8/2),'I_Budget Input Data'!$D$8*0.2/('I_Inputs & Assumptions'!$B$8/4))),IF('I_Budget Input Data'!$E$8="At Completion",IF(36='I_Inputs & Assumptions'!$B$8,'I_Budget Input Data'!$D$8,0),'I_Budget Input Data'!$D$8/'I_Inputs & Assumptions'!$B$8)))))),0) -> 0
